[
    {
        "id": "1906470493192561323",
        "matchStartTime": "19:00",
        "tournament": "Delray Beach ATP • Ćwierćfinał",
        "eventName": "Chak Lam Coleman Wong - Flavio Cobolli",
        "p1": "Chak Lam Coleman Wong",
        "p2": "Flavio Cobolli",
        "atp": true,
        "tags1": null,
        "tags2": null,
        "updateTime": "06:50",
        "stats1": {
            "ace": "13#14#15#15#21#6",
            "ace2": "11#8#11#2#10#2",
            "df": "0#3#2#1#2#2",
            "df2": "0#3#3#2#4#2",
            "b": "1#2#2#3#2#1",
            "b2": "1#0#0#0#2#3",
            "aceAvgPerSet": "5.00",
            "dfAvgPerSet": "0.85",
            "secSrvToDf": "8.66",
            "srvGameToDf": "3.73",
            "bAvgPerSet": "1.13"
        },
        "stats2": {
            "ace": "9#4#3#7#5#8",
            "ace2": "9#11#7#6#13#8",
            "df": "2#2#1#8#5#1",
            "df2": "4#2#1#0#3#3",
            "b": "2#0#0#3#4#1",
            "b2": "1#4#4#6#5#0",
            "aceAvgPerSet": "3.56",
            "dfAvgPerSet": "1.15",
            "secSrvToDf": "8.53",
            "srvGameToDf": "4.52",
            "bAvgPerSet": "1.13"
        },
        "A": [
            {
                "book": "superbet",
                "under": "-17.5 @1.72",
                "lineType": "meczowa",
                "over": "+17.5 @2"
            },
            {
                "book": "betclic",
                "lineType": "meczowa",
                "over": "+20.5 @1.8"
            },
            {
                "book": "superbet",
                "under": "-10.5 @1.85",
                "lineType": "player1",
                "over": "+10.5 @1.85"
            },
            {
                "book": "betclic",
                "lineType": "player1",
                "over": "+11.5 @1.8"
            },
            {
                "book": "superbet",
                "under": "- 6.5 @1.85",
                "lineType": "player2",
                "over": "+ 6.5 @1.85"
            },
            {
                "book": "betclic",
                "lineType": "player2",
                "over": "+ 8.5 @1.8"
            }
        ],
        "A_cnt": 6,
        "A_book_cnt": 2,
        "DF": [
            {
                "book": "superbet",
                "under": "- 4.5 @2.02",
                "lineType": "meczowa",
                "over": "+ 4.5 @1.7"
            },
            {
                "book": "superbet",
                "under": "- 1.5 @2.42",
                "lineType": "player1",
                "over": "+ 1.5 @1.5"
            },
            {
                "book": "superbet",
                "under": "- 2.5 @1.97",
                "lineType": "player2",
                "over": "+ 2.5 @1.75"
            }
        ],
        "DF_cnt": 3,
        "DF_book_cnt": 1,
        "B": [
            {
                "book": "superbet",
                "lineType": "meczowa",
                "over": "+ 4.5 @2.2"
            },
            {
                "book": "superbet",
                "lineType": "player1",
                "over": "+ 1.5 @1.55"
            },
            {
                "book": "superbet",
                "lineType": "player2",
                "over": "+ 2.5 @2.1"
            }
        ],
        "B_cnt": 3,
        "B_book_cnt": 1
    },
    {
        "id": "5807486728263651824",
        "matchStartTime": "20:30",
        "tournament": "Delray Beach ATP • Ćwierćfinał",
        "eventName": "Sebastian Korda - Casper Ruud",
        "p1": "Sebastian Korda",
        "p2": "Casper Ruud",
        "atp": true,
        "tags1": null,
        "tags2": null,
        "updateTime": "06:50",
        "stats1": {
            "ace": "10#14#12#8#9#2",
            "ace2": "7#2#22#8#3#2",
            "df": "2#0#0#1#1#1",
            "df2": "2#3#3#1#1#1",
            "b": "4#2#0#4#2#1",
            "b2": "2#0#1#1#0#2",
            "aceAvgPerSet": "4.17",
            "dfAvgPerSet": "0.96",
            "secSrvToDf": "8.16",
            "srvGameToDf": "3.68",
            "bAvgPerSet": "0.95"
        },
        "stats2": {
            "ace": "20#9#25#5#10#6",
            "ace2": "9#14#18#5#8#4",
            "df": "0#6#4#3#2#0",
            "df2": "2#4#6#4#3#0",
            "b": "1#1#4#3#5#0",
            "b2": "1#3#2#0#0#2",
            "aceAvgPerSet": "3.21",
            "dfAvgPerSet": "0.66",
            "secSrvToDf": "8.04",
            "srvGameToDf": "3.99",
            "bAvgPerSet": "1.04"
        },
        "A": [
            {
                "book": "betclic",
                "lineType": "meczowa",
                "over": "+17.5 @1.8"
            },
            {
                "book": "superbet",
                "under": "-17.5 @2",
                "lineType": "meczowa",
                "over": "+17.5 @1.72"
            },
            {
                "book": "superbet",
                "under": "-10.5 @1.85",
                "lineType": "player1",
                "over": "+10.5 @1.85"
            },
            {
                "book": "betclic",
                "lineType": "player1",
                "over": "+10.5 @1.8"
            },
            {
                "book": "superbet",
                "under": "- 7.5 @1.72",
                "lineType": "player2",
                "over": "+ 7.5 @2"
            },
            {
                "book": "betclic",
                "lineType": "player2",
                "over": "+ 7.5 @1.8"
            }
        ],
        "A_cnt": 6,
        "A_book_cnt": 2,
        "DF": [
            {
                "book": "superbet",
                "under": "- 4.5 @1.69",
                "lineType": "meczowa",
                "over": "+ 4.5 @2.05"
            },
            {
                "book": "superbet",
                "under": "- 1.5 @2.2",
                "lineType": "player1",
                "over": "+ 1.5 @1.6"
            },
            {
                "book": "superbet",
                "under": "- 2.5 @1.66",
                "lineType": "player2",
                "over": "+ 2.5 @2.1"
            }
        ],
        "DF_cnt": 3,
        "DF_book_cnt": 1,
        "B": [
            {
                "book": "superbet",
                "lineType": "meczowa",
                "over": "+ 3.5 @2.25"
            },
            {
                "book": "superbet",
                "lineType": "player1",
                "over": "+ 1.5 @1.7"
            },
            {
                "book": "superbet",
                "lineType": "player2",
                "over": "+ 1.5 @1.95"
            }
        ],
        "B_cnt": 3,
        "B_book_cnt": 1
    },
    {
        "id": "5302470712140573058",
        "matchStartTime": "17:30",
        "tournament": "Doha ATP • Półfinał",
        "eventName": "Carlos Alcaraz - Andrey Rublev",
        "p1": "Carlos Alcaraz",
        "p2": "Andrey Rublev",
        "atp": true,
        "tags1": null,
        "tags2": null,
        "updateTime": "06:50",
        "stats1": {
            "ace": "8#4#2#9#12#5",
            "ace2": "4#2#6#4#17#1",
            "df": "2#2#1#2#5#3",
            "df2": "2#2#1#2#4#0",
            "b": "2#3#1#5#4#7",
            "b2": "0#0#0#2#2#2",
            "aceAvgPerSet": "2.24",
            "dfAvgPerSet": "0.77",
            "secSrvToDf": "7.68",
            "srvGameToDf": "4.08",
            "bAvgPerSet": "1.45"
        },
        "stats2": {
            "ace": "5#6#4#5#6#8",
            "ace2": "8#4#5#8#10#4",
            "df": "2#0#2#5#3#2",
            "df2": "1#4#1#2#5#4",
            "b": "2#3#5#1#5#5",
            "b2": "0#0#2#3#2#0",
            "aceAvgPerSet": "2.79",
            "dfAvgPerSet": "1.08",
            "secSrvToDf": "8.50",
            "srvGameToDf": "3.59",
            "bAvgPerSet": "1.10"
        },
        "A": [
            {
                "book": "superbet",
                "under": "-10.5 @1.85",
                "lineType": "meczowa",
                "over": "+10.5 @1.85"
            },
            {
                "book": "betclic",
                "lineType": "meczowa",
                "over": "+11.5 @1.8"
            },
            {
                "book": "fortuna-BB",
                "lineType": "player1",
                "over": "+ 4.5 @1.75"
            },
            {
                "book": "fortuna-BB",
                "lineType": "player1",
                "over": "+ 5.5 @2.38"
            },
            {
                "book": "superbet",
                "under": "- 5.5 @1.9",
                "lineType": "player1",
                "over": "+ 5.5 @1.8"
            },
            {
                "book": "fortuna-BB",
                "lineType": "player1",
                "over": "+ 6.5 @3.4"
            },
            {
                "book": "betclic",
                "lineType": "player1",
                "over": "+ 6.5 @1.8"
            },
            {
                "book": "fortuna-BB",
                "lineType": "player1",
                "over": "+ 7.5 @5"
            },
            {
                "book": "betclic",
                "lineType": "player2",
                "over": "+ 4.5 @1.8"
            },
            {
                "book": "superbet",
                "under": "- 4.5 @1.95",
                "lineType": "player2",
                "over": "+ 4.5 @1.75"
            },
            {
                "book": "fortuna-BB",
                "lineType": "player2",
                "over": "+ 4.5 @1.65"
            },
            {
                "book": "fortuna-BB",
                "lineType": "player2",
                "over": "+ 5.5 @2.15"
            },
            {
                "book": "fortuna-BB",
                "lineType": "player2",
                "over": "+ 6.5 @2.9"
            },
            {
                "book": "fortuna-BB",
                "lineType": "player2",
                "over": "+ 7.5 @4.1"
            }
        ],
        "A_cnt": 14,
        "A_book_cnt": 3,
        "DF": [
            {
                "book": "superbet",
                "under": "- 3.5 @2.1",
                "lineType": "meczowa",
                "over": "+ 3.5 @1.65"
            },
            {
                "book": "superbet",
                "under": "- 1.5 @1.9",
                "lineType": "player1",
                "over": "+ 1.5 @1.8"
            },
            {
                "book": "superbet",
                "under": "- 2.5 @1.65",
                "lineType": "player2",
                "over": "+ 2.5 @2.1"
            }
        ],
        "DF_cnt": 3,
        "DF_book_cnt": 1,
        "B": [
            {
                "book": "betclic",
                "under": "- 4.5 @1.4",
                "lineType": "meczowa",
                "over": "+ 4.5 @2.25"
            },
            {
                "book": "superbet",
                "lineType": "meczowa",
                "over": "+ 4.5 @2.25"
            },
            {
                "book": "superbet",
                "lineType": "player1",
                "over": "+ 3.5 @2.3"
            },
            {
                "book": "betclic",
                "under": "- 3.5 @1.4",
                "lineType": "player1",
                "over": "+ 3.5 @2.25"
            },
            {
                "book": "superbet",
                "lineType": "player2",
                "over": "+ 0.5 @1.5"
            },
            {
                "book": "betclic",
                "under": "- 0.5 @2.1",
                "lineType": "player2",
                "over": "+ 0.5 @1.48"
            }
        ],
        "B_cnt": 6,
        "B_book_cnt": 2
    },
    {
        "id": "-1308521518367955123",
        "matchStartTime": "16:00",
        "tournament": "Dubaj WTA • Półfinał",
        "eventName": "Elina Svitolina - Coco Gauff",
        "p1": "Elina Svitolina",
        "p2": "Coco Gauff",
        "atp": false,
        "tags1": null,
        "tags2": "DF;T",
        "updateTime": "06:50",
        "stats1": {
            "ace": "7#9#5#4#2#4",
            "ace2": "0#0#1#1#0#0",
            "df": "7#4#2#2#3#0",
            "df2": "1#5#2#4#1#5",
            "b": "5#7#1#6#1#6",
            "b2": "3#4#4#2#4#1",
            "aceAvgPerSet": "1.56",
            "dfAvgPerSet": "1.34",
            "secSrvToDf": "7.95",
            "srvGameToDf": "3.50",
            "bAvgPerSet": "1.94"
        },
        "stats2": {
            "ace": "1#1#4#2#0#2",
            "ace2": "0#3#0#0#4#2",
            "df": "8#16#12#3#5#3",
            "df2": "1#6#2#2#0#1",
            "b": "6#7#6#1#1#4",
            "b2": "1#7#4#4#6#2",
            "aceAvgPerSet": "1.30",
            "dfAvgPerSet": "3.06",
            "secSrvToDf": "7.46",
            "srvGameToDf": "3.76",
            "bAvgPerSet": "2.05"
        },
        "A": [
            {
                "book": "betclic",
                "lineType": "meczowa",
                "over": "+ 6.5 @1.8"
            },
            {
                "book": "betclic",
                "lineType": "player1",
                "over": "+ 3.5 @1.6"
            },
            {
                "book": "betclic",
                "lineType": "player2",
                "over": "+ 2.5 @1.6"
            }
        ],
        "A_cnt": 3,
        "A_book_cnt": 1,
        "DF": [
            {
                "book": "betclic",
                "under": "-11.5 @1.7",
                "lineType": "meczowa",
                "over": "+11.5 @1.7"
            },
            {
                "book": "betclic",
                "under": "- 3.5 @1.7",
                "lineType": "player1",
                "over": "+ 3.5 @1.7"
            },
            {
                "book": "betclic",
                "under": "- 8.5 @1.7",
                "lineType": "player2",
                "over": "+ 8.5 @1.7"
            }
        ],
        "DF_cnt": 3,
        "DF_book_cnt": 1,
        "B": [
            {
                "book": "betclic",
                "under": "- 6.5 @1.7",
                "lineType": "meczowa",
                "over": "+ 6.5 @1.7"
            },
            {
                "book": "betclic",
                "under": "- 3.5 @1.6",
                "lineType": "player1",
                "over": "+ 3.5 @1.88"
            },
            {
                "book": "betclic",
                "under": "- 3.5 @2.1",
                "lineType": "player2",
                "over": "+ 3.5 @1.48"
            }
        ],
        "B_cnt": 3,
        "B_book_cnt": 1
    },
    {
        "id": "5400547135295520974",
        "matchStartTime": "14:00",
        "tournament": "Dubaj WTA • Półfinał",
        "eventName": "Jessica Pegula - Amanda Anisimova",
        "p1": "Jessica Pegula",
        "p2": "Amanda Anisimova",
        "atp": false,
        "tags1": null,
        "tags2": null,
        "updateTime": "06:50",
        "stats1": {
            "ace": "7#5#4#2#6#2",
            "ace2": "6#3#2#6#2#4",
            "df": "2#1#1#0#2#1",
            "df2": "3#1#3#0#7#6",
            "b": "1#3#5#3#4#4",
            "b2": "2#0#1#4#2#2",
            "aceAvgPerSet": "1.32",
            "dfAvgPerSet": "0.74",
            "secSrvToDf": "7.48",
            "srvGameToDf": "3.77",
            "bAvgPerSet": "1.83"
        },
        "stats2": {
            "ace": "0#2#2#7#4#3",
            "ace2": "6#0#6#6#2#1",
            "df": "8#4#7#1#7#8",
            "df2": "7#6#2#3#1#7",
            "b": "8#6#2#2#5#4",
            "b2": "9#2#4#1#2#1",
            "aceAvgPerSet": "1.72",
            "dfAvgPerSet": "1.71",
            "secSrvToDf": "6.30",
            "srvGameToDf": "3.02",
            "bAvgPerSet": "1.75"
        },
        "A": [
            {
                "book": "etoto",
                "under": "- 8.5 @1.85",
                "lineType": "meczowa",
                "over": "+ 8.5 @1.85"
            },
            {
                "book": "superbet",
                "under": "- 8.5 @2.12",
                "lineType": "meczowa",
                "over": "+ 8.5 @1.65"
            },
            {
                "book": "superbet",
                "under": "- 9.5 @1.72",
                "lineType": "meczowa",
                "over": "+ 9.5 @2"
            },
            {
                "book": "betclic",
                "lineType": "meczowa",
                "over": "+ 9.5 @1.8"
            },
            {
                "book": "fortuna-BB",
                "lineType": "player1",
                "over": "+ 3.5 @1.5"
            },
            {
                "book": "superbet",
                "under": "- 3.5 @2.57",
                "lineType": "player1",
                "over": "+ 3.5 @1.45"
            },
            {
                "book": "etoto",
                "under": "- 4.5 @1.7",
                "lineType": "player1",
                "over": "+ 4.5 @2.05"
            },
            {
                "book": "fortuna-BB",
                "lineType": "player1",
                "over": "+ 4.5 @2.05"
            },
            {
                "book": "superbet",
                "under": "- 4.5 @1.76",
                "lineType": "player1",
                "over": "+ 4.5 @1.95"
            },
            {
                "book": "fortuna-BB",
                "lineType": "player1",
                "over": "+ 5.5 @3"
            },
            {
                "book": "betclic",
                "lineType": "player1",
                "over": "+ 5.5 @1.8"
            },
            {
                "book": "fortuna-BB",
                "lineType": "player1",
                "over": "+ 6.5 @4.5"
            },
            {
                "book": "fortuna-BB",
                "lineType": "player2",
                "over": "+ 3.5 @1.46"
            },
            {
                "book": "etoto",
                "under": "- 4.5 @1.7",
                "lineType": "player2",
                "over": "+ 4.5 @2.05"
            },
            {
                "book": "fortuna-BB",
                "lineType": "player2",
                "over": "+ 4.5 @1.9"
            },
            {
                "book": "superbet",
                "under": "- 4.5 @1.85",
                "lineType": "player2",
                "over": "+ 4.5 @1.85"
            },
            {
                "book": "betclic",
                "lineType": "player2",
                "over": "+ 4.5 @1.8"
            },
            {
                "book": "fortuna-BB",
                "lineType": "player2",
                "over": "+ 5.5 @2.63"
            },
            {
                "book": "superbet",
                "under": "- 5.5 @1.47",
                "lineType": "player2",
                "over": "+ 5.5 @2.5"
            },
            {
                "book": "fortuna-BB",
                "lineType": "player2",
                "over": "+ 6.5 @3.9"
            },
            {
                "book": "fortuna-BB",
                "lineType": "player2",
                "over": "+ 7.5 @5.75"
            }
        ],
        "A_cnt": 21,
        "A_book_cnt": 4,
        "DF": [
            {
                "book": "etoto",
                "under": "- 6.5 @2.05",
                "lineType": "meczowa",
                "over": "+ 6.5 @1.7"
            },
            {
                "book": "superbet",
                "under": "- 6.5 @2.02",
                "lineType": "meczowa",
                "over": "+ 6.5 @1.7"
            },
            {
                "book": "superbet",
                "under": "- 7.5 @1.66",
                "lineType": "meczowa",
                "over": "+ 7.5 @2.1"
            },
            {
                "book": "betclic",
                "under": "- 7.5 @1.88",
                "lineType": "meczowa",
                "over": "+ 7.5 @1.6"
            },
            {
                "book": "etoto",
                "under": "- 1.5 @2.2",
                "lineType": "player1",
                "over": "+ 1.5 @1.6"
            },
            {
                "book": "superbet",
                "under": "- 1.5 @2.3",
                "lineType": "player1",
                "over": "+ 1.5 @1.55"
            },
            {
                "book": "betclic",
                "under": "- 1.5 @2.05",
                "lineType": "player1",
                "over": "+ 1.5 @1.5"
            },
            {
                "book": "superbet",
                "under": "- 2.5 @1.45",
                "lineType": "player1",
                "over": "+ 2.5 @2.55"
            },
            {
                "book": "superbet",
                "under": "- 4.5 @2.12",
                "lineType": "player2",
                "over": "+ 4.5 @1.65"
            },
            {
                "book": "etoto",
                "under": "- 4.5 @2.2",
                "lineType": "player2",
                "over": "+ 4.5 @1.6"
            },
            {
                "book": "superbet",
                "under": "- 5.5 @1.6",
                "lineType": "player2",
                "over": "+ 5.5 @2.2"
            },
            {
                "book": "betclic",
                "under": "- 5.5 @1.88",
                "lineType": "player2",
                "over": "+ 5.5 @1.6"
            }
        ],
        "DF_cnt": 12,
        "DF_book_cnt": 3,
        "B": [
            {
                "book": "etoto",
                "under": "- 6.5 @1.8",
                "lineType": "meczowa",
                "over": "+ 6.5 @1.9"
            },
            {
                "book": "superbet",
                "lineType": "meczowa",
                "over": "+ 6.5 @1.8"
            },
            {
                "book": "betclic",
                "under": "- 7.5 @1.55",
                "lineType": "meczowa",
                "over": "+ 7.5 @1.95"
            },
            {
                "book": "superbet",
                "lineType": "player1",
                "over": "+ 3.5 @1.85"
            },
            {
                "book": "etoto",
                "under": "- 3.5 @1.95",
                "lineType": "player1",
                "over": "+ 3.5 @1.75"
            },
            {
                "book": "betclic",
                "under": "- 3.5 @1.95",
                "lineType": "player1",
                "over": "+ 3.5 @1.55"
            },
            {
                "book": "etoto",
                "under": "- 3.5 @1.65",
                "lineType": "player2",
                "over": "+ 3.5 @2.1"
            },
            {
                "book": "superbet",
                "lineType": "player2",
                "over": "+ 3.5 @2"
            },
            {
                "book": "betclic",
                "under": "- 3.5 @1.55",
                "lineType": "player2",
                "over": "+ 3.5 @1.95"
            }
        ],
        "B_cnt": 9,
        "B_book_cnt": 3
    },
    {
        "id": "4793722446659329939",
        "matchStartTime": "00:10",
        "tournament": "Rio de Janeiro ATP • Ćwierćfinał",
        "eventName": "Thiago Agustin Tirante - Alejandro Tabilo",
        "p1": "Thiago Agustin Tirante",
        "p2": "Alejandro Tabilo",
        "atp": true,
        "tags1": null,
        "tags2": null,
        "updateTime": "06:50",
        "stats1": {
            "ace": "12#12#20#5#7#6",
            "ace2": "2#4#8#3#3#3",
            "df": "0#3#2#1#3#3",
            "df2": "5#1#2#1#4#2",
            "b": "3#0#5#0#5#0",
            "b2": "0#4#0#3#2#5",
            "aceAvgPerSet": "2.92",
            "dfAvgPerSet": "0.96",
            "secSrvToDf": "7.07",
            "srvGameToDf": "2.86",
            "bAvgPerSet": "1.19"
        },
        "stats2": {
            "ace": "4#3#2#5#2#7",
            "ace2": "4#6#9#5#6#9",
            "df": "0#0#3#1#1#1",
            "df2": "1#3#0#0#2#5",
            "b": "3#2#3#4#1#4",
            "b2": "2#0#3#3#0#1",
            "aceAvgPerSet": "2.74",
            "dfAvgPerSet": "1.04",
            "secSrvToDf": "9.81",
            "srvGameToDf": "5.00",
            "bAvgPerSet": "1.33"
        },
        "A": [
            {
                "book": "betclic",
                "lineType": "meczowa",
                "over": "+10.5 @1.8"
            },
            {
                "book": "superbet",
                "under": "-11.5 @2.12",
                "lineType": "meczowa",
                "over": "+11.5 @1.65"
            },
            {
                "book": "betclic",
                "lineType": "player1",
                "over": "+ 6.5 @1.8"
            },
            {
                "book": "fortuna-BB",
                "lineType": "player1",
                "over": "+ 6.5 @1.55"
            },
            {
                "book": "fortuna-BB",
                "lineType": "player1",
                "over": "+ 7.5 @1.9"
            },
            {
                "book": "superbet",
                "under": "- 7.5 @1.9",
                "lineType": "player1",
                "over": "+ 7.5 @1.8"
            },
            {
                "book": "fortuna-BB",
                "lineType": "player1",
                "over": "+ 8.5 @2.4"
            },
            {
                "book": "fortuna-BB",
                "lineType": "player1",
                "over": "+ 9.5 @3.1"
            },
            {
                "book": "betclic",
                "lineType": "player2",
                "over": "+ 3.5 @1.55"
            },
            {
                "book": "fortuna-BB",
                "lineType": "player2",
                "over": "+ 3.5 @1.46"
            },
            {
                "book": "fortuna-BB",
                "lineType": "player2",
                "over": "+ 4.5 @1.98"
            },
            {
                "book": "superbet",
                "under": "- 4.5 @1.76",
                "lineType": "player2",
                "over": "+ 4.5 @1.95"
            },
            {
                "book": "fortuna-BB",
                "lineType": "player2",
                "over": "+ 5.5 @2.8"
            },
            {
                "book": "fortuna-BB",
                "lineType": "player2",
                "over": "+ 6.5 @4.2"
            },
            {
                "book": "fortuna-BB",
                "lineType": "player2",
                "over": "+ 7.5 @6.5"
            }
        ],
        "A_cnt": 15,
        "A_book_cnt": 3,
        "DF": [
            {
                "book": "superbet",
                "under": "- 2.5 @1.97",
                "lineType": "meczowa",
                "over": "+ 2.5 @1.75"
            },
            {
                "book": "superbet",
                "under": "- 1.5 @1.76",
                "lineType": "player1",
                "over": "+ 1.5 @1.95"
            },
            {
                "book": "superbet",
                "under": "- 1.5 @1.6",
                "lineType": "player2",
                "over": "+ 1.5 @2.2"
            }
        ],
        "DF_cnt": 3,
        "DF_book_cnt": 1,
        "B": [
            {
                "book": "superbet",
                "lineType": "meczowa",
                "over": "+ 5.5 @2"
            },
            {
                "book": "superbet",
                "lineType": "player1",
                "over": "+ 2.5 @1.9"
            },
            {
                "book": "superbet",
                "lineType": "player2",
                "over": "+ 3.5 @2.25"
            }
        ],
        "B_cnt": 3,
        "B_book_cnt": 1
    },
    {
        "id": "6804373618129857436",
        "matchStartTime": "20:00",
        "tournament": "Rio de Janeiro ATP • Ćwierćfinał",
        "eventName": "Vit Kopriva - Juan Manuel Cerundolo",
        "p1": "Vit Kopriva",
        "p2": "Juan Manuel Cerundolo",
        "atp": true,
        "tags1": null,
        "tags2": null,
        "updateTime": "06:50",
        "stats1": {
            "ace": "3#2#2#0#4#3",
            "ace2": "6#1#3#4#4#15",
            "df": "2#1#4#0#5#2",
            "df2": "2#1#2#0#4#1",
            "b": "3#3#2#2#5#1",
            "b2": "0#0#3#0#4#4",
            "aceAvgPerSet": "1.42",
            "dfAvgPerSet": "1.23",
            "secSrvToDf": "6.29",
            "srvGameToDf": "2.74",
            "bAvgPerSet": "1.27"
        },
        "stats2": {
            "ace": "9#4#3#0#2#5",
            "ace2": "6#1#0#2#1#10",
            "df": "3#2#2#0#1#6",
            "df2": "3#2#3#4#1#1",
            "b": "5#3#1#4#5#0",
            "b2": "2#2#3#0#0#6",
            "aceAvgPerSet": "3.07",
            "dfAvgPerSet": "1.44",
            "secSrvToDf": "8.39",
            "srvGameToDf": "3.69",
            "bAvgPerSet": "1.56"
        },
        "A": [
            {
                "book": "betclic",
                "lineType": "meczowa",
                "over": "+ 5.5 @1.8"
            },
            {
                "book": "superbet",
                "under": "- 5.5 @2.12",
                "lineType": "meczowa",
                "over": "+ 5.5 @1.65"
            },
            {
                "book": "superbet",
                "under": "- 2.5 @1.57",
                "lineType": "player1",
                "over": "+ 2.5 @2.25"
            },
            {
                "book": "betclic",
                "lineType": "player1",
                "over": "+ 2.5 @1.88"
            },
            {
                "book": "fortuna-BB",
                "lineType": "player1",
                "over": "+ 3.5 @3.6"
            },
            {
                "book": "fortuna-BB",
                "lineType": "player1",
                "over": "+ 4.5 @6.5"
            },
            {
                "book": "superbet",
                "under": "- 3.5 @1.85",
                "lineType": "player2",
                "over": "+ 3.5 @1.85"
            },
            {
                "book": "fortuna-BB",
                "lineType": "player2",
                "over": "+ 3.5 @1.83"
            },
            {
                "book": "betclic",
                "lineType": "player2",
                "over": "+ 3.5 @1.8"
            },
            {
                "book": "fortuna-BB",
                "lineType": "player2",
                "over": "+ 4.5 @2.63"
            },
            {
                "book": "fortuna-BB",
                "lineType": "player2",
                "over": "+ 5.5 @4.2"
            },
            {
                "book": "fortuna-BB",
                "lineType": "player2",
                "over": "+ 6.5 @6.75"
            }
        ],
        "A_cnt": 12,
        "A_book_cnt": 3,
        "DF": [
            {
                "book": "superbet",
                "under": "- 5.5 @1.85",
                "lineType": "meczowa",
                "over": "+ 5.5 @1.85"
            },
            {
                "book": "superbet",
                "under": "- 2.5 @2.12",
                "lineType": "player1",
                "over": "+ 2.5 @1.65"
            },
            {
                "book": "superbet",
                "under": "- 2.5 @1.97",
                "lineType": "player2",
                "over": "+ 2.5 @1.75"
            }
        ],
        "DF_cnt": 3,
        "DF_book_cnt": 1,
        "B": [
            {
                "book": "superbet",
                "lineType": "meczowa",
                "over": "+ 5.5 @1.9"
            },
            {
                "book": "superbet",
                "lineType": "player1",
                "over": "+ 2.5 @1.55"
            },
            {
                "book": "superbet",
                "lineType": "player2",
                "over": "+ 2.5 @1.65"
            }
        ],
        "B_cnt": 3,
        "B_book_cnt": 1
    }
]