[
  {
    "id": "-4992336316593115353",
    "matchStartTime": "16:00",
    "tournament": "Miami ATP • 1/64 finału",
    "eventName": "Kamil Majchrzak - Miomir Kecmanovic",
    "p1": "Kamil Majchrzak",
    "p2": "Miomir Kecmanovic",
    "atp": true,
    "tags1": null,
    "tags2": null,
    "updateTime": "10:10",
    "stats1": {
      "sb_a1": "7#5#6#6",
      "sb_a2": "7#18#9#6",
      "sb_am": "13#25#15#13",
      "sb_df1": "3#1#2#2",
      "sb_df2": "2#2#2#2",
      "sb_dfm": "4#3#4#4",
      "sb_b1": "1#2#2",
      "sb_b2": "4#2#3",
      "sb_bm": "5#4#4",
      "ace": "3^#6^#4^#7^#3^#5 ",
      "ace2": "5^#11^#10^#5^#5^#12 ",
      "df": "1^#1^#2^#5^#4^#1 ",
      "df2": "5^#7^#0^#5^#2^#10 ",
      "b": "2^#1^#2^#1^#4^#4 ",
      "b2": "5^#3^#3^#3^#6^#5 ",
      "aceAvgPerSet": "2.82",
      "dfAvgPerSet": "0.71",
      "secSrvToDf": "9.85",
      "srvGameToDf": "4.12",
      "bAvgPerSet": "1.06",
      "last_aceAvgPerSet": "1.17",
      "last_dfAvgPerSet": "1.00",
      "last_secSrvToDf": "10.89",
      "last_srvGameToDf": "4.33",
      "last_bAvgPerSet": "1.00"
    },
    "stats2": {
      "sb_a1": "6#7#4#5#5",
      "sb_a2": "10#10#10#9#7",
      "sb_am": "15#17#14#14#12",
      "sb_df1": "2#2#4#2#3",
      "sb_df2": "3#3#2#4#4",
      "sb_dfm": "6#5#4#6#6",
      "sb_b1": "3#3#1#3#2",
      "sb_b2": "3#2#4#2#3",
      "sb_bm": "5#5#5#5#4",
      "ace": "1^#7^#5 #13^#7 #12^",
      "ace2": "13^#13^#6 #17^#4 #20^",
      "df": "2^#2^#0 #3^#2 #2^",
      "df2": "8^#3^#2 #2^#3 #5^",
      "b": "1^#4^#4 #2^#4 #0^",
      "b2": "1^#4^#1 #1^#0 #2^",
      "aceAvgPerSet": "2.90",
      "dfAvgPerSet": "1.23",
      "secSrvToDf": "9.68",
      "srvGameToDf": "3.95",
      "bAvgPerSet": "1.03",
      "last_aceAvgPerSet": "3.50",
      "last_dfAvgPerSet": "0.67",
      "last_secSrvToDf": "10.17",
      "last_srvGameToDf": "5.00",
      "last_bAvgPerSet": "1.33"
    },
    "A": [
      {
        "book": "betclic",
        "lineType": "meczowa",
        "over": "+15.5 @1.8"
      },
      {
        "book": "betclic",
        "lineType": "player1",
        "over": "+ 8.5 @1.8"
      },
      {
        "book": "betclic",
        "lineType": "player2",
        "over": "+ 6.5 @1.8"
      }
    ],
    "A_cnt": 3,
    "A_book_cnt": 1,
    "DF": null,
    "DF_cnt": 0,
    "DF_book_cnt": 0,
    "B": null,
    "B_cnt": 0,
    "B_book_cnt": 0
  },
  {
    "id": "7330267057445810435",
    "matchStartTime": "16:00",
    "tournament": "Miami ATP • 1/64 finału",
    "eventName": "Marin Cilic - Alexei Popyrin",
    "p1": "Marin Cilic",
    "p2": "Alexei Popyrin",
    "atp": true,
    "tags1": null,
    "tags2": null,
    "updateTime": "10:10",
    "stats1": {
      "sb_a1": "10#9#12#11#10#10",
      "sb_a2": "8#9#14#9#9#8",
      "sb_am": "19#22#26#19#18#17",
      "sb_df1": "3#2#4#3#4#4",
      "sb_df2": "2#1#2#4#3#3",
      "sb_dfm": "5#4#6#7#6#7",
      "sb_b1": "2#3#2#2",
      "sb_b2": "3#2#2#3",
      "sb_bm": "4#4#3#4",
      "ace": "17 #8 #16 #16 #15 #9 ",
      "ace2": "5 #13 #22 #3 #12 #9 ",
      "df": "1 #1 #8 #0 #5 #3 ",
      "df2": "1 #0 #0 #3 #1 #6 ",
      "b": "1 #0 #0 #2 #1 #3 ",
      "b2": "2 #0 #0 #0 #0 #2 ",
      "aceAvgPerSet": "4.69",
      "dfAvgPerSet": "1.28",
      "secSrvToDf": "8.16",
      "srvGameToDf": "3.45",
      "bAvgPerSet": "0.89",
      "last_aceAvgPerSet": "7.00",
      "last_dfAvgPerSet": "0.67",
      "last_secSrvToDf": "10.94",
      "last_srvGameToDf": "4.67",
      "last_bAvgPerSet": "1.17"
    },
    "stats2": {
      "sb_a1": "8#9#9#8#10",
      "sb_a2": "2#10#6#8#13",
      "sb_am": "10#20#15#16#23",
      "sb_df1": "2#3#2#3#3",
      "sb_df2": "2#3#2#1#3",
      "sb_dfm": "5#6#4#4#6",
      "sb_b1": "1#2#1#1",
      "sb_b2": "3#2#4#2",
      "sb_bm": "4#4#4#3",
      "ace": "8 #4 #10^#4 #5 #6 ",
      "ace2": "2 #7 #4^#7 #0 #8 ",
      "df": "0 #0 #0^#0 #1 #1 ",
      "df2": "1 #2 #2^#0 #6 #3 ",
      "b": "0 #0 #3^#0 #2 #0 ",
      "b2": "2 #2 #2^#1 #0 #2 ",
      "aceAvgPerSet": "4.05",
      "dfAvgPerSet": "1.04",
      "secSrvToDf": "8.98",
      "srvGameToDf": "4.02",
      "bAvgPerSet": "0.95",
      "last_aceAvgPerSet": "3.00",
      "last_dfAvgPerSet": "0.00",
      "last_secSrvToDf": "8.50",
      "last_srvGameToDf": "4.50",
      "last_bAvgPerSet": "0.50"
    },
    "A": [
      {
        "book": "betclic",
        "lineType": "meczowa",
        "over": "+22.5 @1.8"
      },
      {
        "book": "betclic",
        "lineType": "player1",
        "over": "+10.5 @1.8"
      },
      {
        "book": "betclic",
        "lineType": "player2",
        "over": "+11.5 @1.8"
      }
    ],
    "A_cnt": 3,
    "A_book_cnt": 1,
    "DF": null,
    "DF_cnt": 0,
    "DF_book_cnt": 0,
    "B": null,
    "B_cnt": 0,
    "B_book_cnt": 0
  },
  {
    "id": "3706439123870098373",
    "matchStartTime": "16:00",
    "tournament": "Miami ATP • 1/64 finału",
    "eventName": "Fabian Marozsan - Joao Fonseca",
    "p1": "Fabian Marozsan",
    "p2": "Joao Fonseca",
    "atp": true,
    "tags1": null,
    "tags2": null,
    "updateTime": "10:10",
    "stats1": {
      "sb_a1": "6#4#5#4",
      "sb_a2": "4#10#8#6",
      "sb_am": "11#14#12#11",
      "sb_df1": "2#1#2#2",
      "sb_df2": "2#1#2#2",
      "sb_dfm": "4#3#4#4",
      "sb_b1": "2#3#3",
      "sb_b2": "2#3#3",
      "sb_bm": "3#5#5",
      "ace": "7^#7^#4 #1 #0 #5^",
      "ace2": "4^#13^#6 #1 #19 #3^",
      "df": "3^#2^#4 #1 #2 #2^",
      "df2": "2^#0^#0 #2 #10 #4^",
      "b": "1^#1^#0 #1 #7 #6^",
      "b2": "3^#2^#3 #0 #11 #4^",
      "aceAvgPerSet": "1.76",
      "dfAvgPerSet": "0.83",
      "secSrvToDf": "8.72",
      "srvGameToDf": "4.36",
      "bAvgPerSet": "0.94",
      "last_aceAvgPerSet": "2.00",
      "last_dfAvgPerSet": "0.67",
      "last_secSrvToDf": "11.33",
      "last_srvGameToDf": "5.00",
      "last_bAvgPerSet": "1.17"
    },
    "stats2": {
      "sb_a1": "4#5#5#5#5#4",
      "sb_a2": "6#6#6#7#3#4",
      "sb_am": "10#10#11#13#7#9",
      "sb_df1": "2#2#2#1#2#2",
      "sb_df2": "2#2#3#2#2#2",
      "sb_dfm": "4#4#5#3#4#3",
      "sb_b1": "1#3#3#4#4",
      "sb_b2": "4#3#3#2#2",
      "sb_bm": "5#5#5#6#5",
      "ace": "9 #2 #11^#3 #2^#7 ",
      "ace2": "15 #2 #12^#5 #8^#9 ",
      "df": "3 #0 #3^#0 #3^#1 ",
      "df2": "1 #2 #3^#4 #5^#2 ",
      "b": "1 #4 #2^#2 #1^#1 ",
      "b2": "1 #1 #3^#1 #2^#0 ",
      "aceAvgPerSet": "2.96",
      "dfAvgPerSet": "1.14",
      "secSrvToDf": "8.98",
      "srvGameToDf": "3.95",
      "bAvgPerSet": "1.08",
      "last_aceAvgPerSet": "2.50",
      "last_dfAvgPerSet": "0.50",
      "last_secSrvToDf": "8.25",
      "last_srvGameToDf": "4.75",
      "last_bAvgPerSet": "1.17"
    },
    "A": [
      {
        "book": "betclic",
        "lineType": "meczowa",
        "over": "+15.5 @1.8"
      },
      {
        "book": "betclic",
        "lineType": "player1",
        "over": "+ 7.5 @1.8"
      },
      {
        "book": "betclic",
        "lineType": "player2",
        "over": "+ 8.5 @1.8"
      }
    ],
    "A_cnt": 3,
    "A_book_cnt": 1,
    "DF": null,
    "DF_cnt": 0,
    "DF_book_cnt": 0,
    "B": null,
    "B_cnt": 0,
    "B_book_cnt": 0
  },
  {
    "id": "3901149654445863281",
    "matchStartTime": "16:00",
    "tournament": "Miami ATP • 1/64 finału",
    "eventName": "Matteo Arnaldi - Alexander Shevchenko",
    "p1": "Matteo Arnaldi",
    "p2": "Alexander Shevchenko",
    "atp": true,
    "tags1": null,
    "tags2": null,
    "updateTime": "10:10",
    "stats1": {
      "sb_a1": "6",
      "sb_a2": "4",
      "sb_am": "9",
      "sb_df1": "4",
      "sb_df2": "2",
      "sb_dfm": "4",
      "sb_b1": null,
      "sb_b2": null,
      "sb_bm": null,
      "ace": "2 #4^#10^#4 #6 #12 ",
      "ace2": "2 #8^#4^#0 #6 #5 ",
      "df": "5 #4^#5^#7 #4 #4 ",
      "df2": "0 #2^#1^#3 #1 #1 ",
      "b": "0 #0^#5^#1 #0 #2 ",
      "b2": "5 #5^#4^#4 #2 #0 ",
      "aceAvgPerSet": "2.31",
      "dfAvgPerSet": "1.46",
      "secSrvToDf": "8.75",
      "srvGameToDf": "3.06",
      "bAvgPerSet": "0.79",
      "last_aceAvgPerSet": "3.67",
      "last_dfAvgPerSet": "2.50",
      "last_secSrvToDf": "8.38",
      "last_srvGameToDf": "2.85",
      "last_bAvgPerSet": "0.50"
    },
    "stats2": {
      "sb_a1": "7#6#6",
      "sb_a2": "7#6#6",
      "sb_am": "14#13#14",
      "sb_df1": "3#2#2",
      "sb_df2": "2#2#2",
      "sb_dfm": "5#6#4",
      "sb_b1": "2#1",
      "sb_b2": "3#3",
      "sb_bm": "4#4",
      "ace": "9 #8^#12^#8 #11 #1 ",
      "ace2": "5 #6^#4^#15 #14 #5 ",
      "df": "2 #0^#3^#1 #2 #1 ",
      "df2": "0 #10^#3^#5 #3 #5 ",
      "b": "0 #2^#0^#0 #1 #1 ",
      "b2": "1 #1^#3^#1 #0 #5 ",
      "aceAvgPerSet": "3.21",
      "dfAvgPerSet": "1.08",
      "secSrvToDf": "8.91",
      "srvGameToDf": "4.02",
      "bAvgPerSet": "0.96",
      "last_aceAvgPerSet": "3.50",
      "last_dfAvgPerSet": "1.00",
      "last_secSrvToDf": "10.00",
      "last_srvGameToDf": "3.75",
      "last_bAvgPerSet": "0.00"
    },
    "A": [
      {
        "book": "betclic",
        "lineType": "meczowa",
        "over": "+16.5 @1.8"
      },
      {
        "book": "betclic",
        "lineType": "player1",
        "over": "+ 8.5 @1.8"
      },
      {
        "book": "betclic",
        "lineType": "player2",
        "over": "+ 7.5 @1.8"
      }
    ],
    "A_cnt": 3,
    "A_book_cnt": 1,
    "DF": null,
    "DF_cnt": 0,
    "DF_book_cnt": 0,
    "B": null,
    "B_cnt": 0,
    "B_book_cnt": 0
  },
  {
    "id": "-2797269215044599303",
    "matchStartTime": "16:00",
    "tournament": "Miami ATP • 1/64 finału",
    "eventName": "Raphael Collignon - Grigor Dimitrov",
    "p1": "Raphael Collignon",
    "p2": "Grigor Dimitrov",
    "atp": true,
    "tags1": "DF",
    "tags2": null,
    "updateTime": "10:10",
    "stats1": {
      "sb_a1": "7",
      "sb_a2": "5",
      "sb_am": "13",
      "sb_df1": "2",
      "sb_df2": "1",
      "sb_dfm": "3",
      "sb_b1": null,
      "sb_b2": null,
      "sb_bm": null,
      "ace": "5 #4 #3 #10 #2 #8 ",
      "ace2": "3 #5 #7 #11 #3 #10 ",
      "df": "4 #1 #1 #2 #0 #4 ",
      "df2": "0 #1 #0 #2 #3 #2 ",
      "b": "1 #0 #0 #1 #3 #3 ",
      "b2": "2 #1 #3 #0 #0 #0 ",
      "aceAvgPerSet": "3.09",
      "dfAvgPerSet": "2.42",
      "secSrvToDf": "4.58",
      "srvGameToDf": "2.59",
      "bAvgPerSet": "0.91",
      "last_aceAvgPerSet": "2.50",
      "last_dfAvgPerSet": "1.00",
      "last_secSrvToDf": "7.89",
      "last_srvGameToDf": "4.17",
      "last_bAvgPerSet": "0.50"
    },
    "stats2": {
      "sb_a1": "4#6#6#9",
      "sb_a2": "6#9#8#8",
      "sb_am": "9#16#13#17",
      "sb_df1": "5#4#4#3",
      "sb_df2": "2#3#3#3",
      "sb_dfm": "7#8#6#5",
      "sb_b1": "1#3#3",
      "sb_b2": "4#2#3",
      "sb_bm": "5#4#5",
      "ace": "1 #3^#4 #14^#11^#11 ",
      "ace2": "6 #10^#5 #16^#21^#10 ",
      "df": "5 #2^#4 #5^#4^#2 ",
      "df2": "2 #8^#0 #4^#1^#2 ",
      "b": "0 #4^#0 #1^#0^#0 ",
      "b2": "3 #4^#3 #2^#4^#1 ",
      "aceAvgPerSet": "3.03",
      "dfAvgPerSet": "1.51",
      "secSrvToDf": "8.68",
      "srvGameToDf": "4.13",
      "bAvgPerSet": "0.97",
      "last_aceAvgPerSet": "2.33",
      "last_dfAvgPerSet": "2.00",
      "last_secSrvToDf": "5.75",
      "last_srvGameToDf": "2.86",
      "last_bAvgPerSet": "0.00"
    },
    "A": [
      {
        "book": "betclic",
        "lineType": "meczowa",
        "over": "+15.5 @1.8"
      },
      {
        "book": "betclic",
        "lineType": "player1",
        "over": "+ 8.5 @1.8"
      },
      {
        "book": "betclic",
        "lineType": "player2",
        "over": "+ 7.5 @1.8"
      }
    ],
    "A_cnt": 3,
    "A_book_cnt": 1,
    "DF": null,
    "DF_cnt": 0,
    "DF_book_cnt": 0,
    "B": null,
    "B_cnt": 0,
    "B_book_cnt": 0
  },
  {
    "id": "3810898626339712107",
    "matchStartTime": "16:00",
    "tournament": "Miami ATP • 1/64 finału",
    "eventName": "Alexandre Muller - Matteo Berrettini",
    "p1": "Alexandre Muller",
    "p2": "Matteo Berrettini",
    "atp": true,
    "tags1": null,
    "tags2": null,
    "updateTime": "10:10",
    "stats1": {
      "sb_a1": null,
      "sb_a2": null,
      "sb_am": null,
      "sb_df1": null,
      "sb_df2": null,
      "sb_dfm": null,
      "sb_b1": null,
      "sb_b2": null,
      "sb_bm": null,
      "ace": "4 #5 #3 #3 #9 #2 ",
      "ace2": "18 #40 #1 #3 #7 #9 ",
      "df": "2 #4 #3 #2 #2 #1 ",
      "df2": "1 #0 #0 #1 #0 #0 ",
      "b": "3 #3 #0 #3 #4 #1 ",
      "b2": "6 #5 #4 #4 #2 #4 ",
      "aceAvgPerSet": "1.77",
      "dfAvgPerSet": "1.25",
      "secSrvToDf": "8.57",
      "srvGameToDf": "3.97",
      "bAvgPerSet": "0.67",
      "last_aceAvgPerSet": "1.00",
      "last_dfAvgPerSet": "0.50",
      "last_secSrvToDf": "10.00",
      "last_srvGameToDf": "4.67",
      "last_bAvgPerSet": "0.67"
    },
    "stats2": {
      "sb_a1": "9#11#6#6#6#6",
      "sb_a2": "8#4#6#3#3#2",
      "sb_am": "18#14#14#9#9#8",
      "sb_df1": "2#1#2#2#2#2",
      "sb_df2": "2#1#4#2#2#2",
      "sb_dfm": "3#3#5#4#4#3",
      "sb_b1": "2#3#4#4",
      "sb_b2": "3#2#2#2",
      "sb_bm": "4#5#5#5",
      "ace": "5 #14^#3 #9^#7^#6 ",
      "ace2": "4 #6^#4 #3^#6^#3 ",
      "df": "2 #3^#2 #2^#3^#2 ",
      "df2": "1 #2^#4 #1^#0^#0 ",
      "b": "0 #3^#0 #2^#4^#1 ",
      "b2": "1 #2^#1 #3^#2^#0 ",
      "aceAvgPerSet": "3.87",
      "dfAvgPerSet": "1.00",
      "secSrvToDf": "9.25",
      "srvGameToDf": "4.14",
      "bAvgPerSet": "1.12",
      "last_aceAvgPerSet": "3.33",
      "last_dfAvgPerSet": "1.17",
      "last_secSrvToDf": "6.67",
      "last_srvGameToDf": "3.92",
      "last_bAvgPerSet": "0.67"
    },
    "A": [
      {
        "book": "betclic",
        "lineType": "meczowa",
        "over": "+16.5 @1.8"
      },
      {
        "book": "betclic",
        "lineType": "meczowa",
        "over": "+16.5 @1.8"
      },
      {
        "book": "betclic",
        "lineType": "meczowa",
        "over": "+16.5 @1.8"
      },
      {
        "book": "betclic",
        "lineType": "player1",
        "over": "+ 4.5 @1.8"
      },
      {
        "book": "betclic",
        "lineType": "player1",
        "over": "+ 4.5 @1.8"
      },
      {
        "book": "betclic",
        "lineType": "player1",
        "over": "+ 4.5 @1.8"
      },
      {
        "book": "betclic",
        "lineType": "player2",
        "over": "+12.5 @1.8"
      },
      {
        "book": "betclic",
        "lineType": "player2",
        "over": "+12.5 @1.8"
      },
      {
        "book": "betclic",
        "lineType": "player2",
        "over": "+12.5 @1.8"
      }
    ],
    "A_cnt": 9,
    "A_book_cnt": 1,
    "DF": null,
    "DF_cnt": 0,
    "DF_book_cnt": 0,
    "B": null,
    "B_cnt": 0,
    "B_book_cnt": 0
  },
  {
    "id": "8988428110580000143",
    "matchStartTime": "16:00",
    "tournament": "Miami ATP • 1/64 finału",
    "eventName": "Gabriel Diallo - Yibing Wu",
    "p1": "Gabriel Diallo",
    "p2": "Yibing Wu",
    "atp": true,
    "tags1": null,
    "tags2": null,
    "updateTime": "10:10",
    "stats1": {
      "sb_a1": "6#10#11#10#9",
      "sb_a2": "8#8#8#8#11",
      "sb_am": "14#18#19#17#19",
      "sb_df1": "3#3#4#3#2",
      "sb_df2": "3#3#3#3#2",
      "sb_dfm": "6#6#6#5#4",
      "sb_b1": "1#2#1",
      "sb_b2": "3#3#2",
      "sb_bm": "4#5#3",
      "ace": "11^#12^#10 #4 #6 #9^",
      "ace2": "9^#6^#8 #5 #13 #10^",
      "df": "0^#6^#1 #1 #3 #1^",
      "df2": "5^#3^#2 #0 #3 #3^",
      "b": "1^#4^#0 #0 #0 #2^",
      "b2": "4^#3^#0 #1 #2 #0^",
      "aceAvgPerSet": "3.44",
      "dfAvgPerSet": "1.08",
      "secSrvToDf": "6.53",
      "srvGameToDf": "3.67",
      "bAvgPerSet": "0.81",
      "last_aceAvgPerSet": "3.50",
      "last_dfAvgPerSet": "1.17",
      "last_secSrvToDf": "5.83",
      "last_srvGameToDf": "4.44",
      "last_bAvgPerSet": "1.00"
    },
    "stats2": {
      "sb_a1": "6#5#7",
      "sb_a2": "7#7#8",
      "sb_am": "13#12#14",
      "sb_df1": "3#3#3",
      "sb_df2": "3#3#3",
      "sb_dfm": "5#5#5",
      "sb_b1": "3#3#2",
      "sb_b2": "3#2",
      "sb_bm": "5#5",
      "ace": "1 #7 #6 #5 #2 #4 ",
      "ace2": "10 #14 #12 #3 #1 #11 ",
      "df": "0 #2 #0 #2 #2 #3 ",
      "df2": "4 #1 #3 #2 #1 #1 ",
      "b": "0 #1 #0 #4 #5 #1 ",
      "b2": "2 #0 #1 #2 #0 #3 ",
      "aceAvgPerSet": "2.50",
      "dfAvgPerSet": "1.20",
      "secSrvToDf": "9.57",
      "srvGameToDf": "3.93",
      "bAvgPerSet": "1.12",
      "last_aceAvgPerSet": "3.00",
      "last_dfAvgPerSet": "0.67",
      "last_secSrvToDf": "10.33",
      "last_srvGameToDf": "4.58",
      "last_bAvgPerSet": "1.00"
    },
    "A": [
      {
        "book": "betclic",
        "lineType": "meczowa",
        "over": "+15.5 @1.8"
      },
      {
        "book": "betclic",
        "lineType": "player1",
        "over": "+ 9.5 @1.8"
      },
      {
        "book": "betclic",
        "lineType": "player2",
        "over": "+ 5.5 @1.8"
      }
    ],
    "A_cnt": 3,
    "A_book_cnt": 1,
    "DF": null,
    "DF_cnt": 0,
    "DF_book_cnt": 0,
    "B": null,
    "B_cnt": 0,
    "B_book_cnt": 0
  },
  {
    "id": "-581147693485409523",
    "matchStartTime": "16:00",
    "tournament": "Miami ATP • 1/64 finału",
    "eventName": "Darwin Blanch - Jan-Lennard Struff",
    "p1": "Darwin Blanch",
    "p2": "Jan-Lennard Struff",
    "atp": true,
    "tags1": null,
    "tags2": null,
    "updateTime": "10:10",
    "stats1": {
      "sb_a1": null,
      "sb_a2": null,
      "sb_am": null,
      "sb_df1": null,
      "sb_df2": null,
      "sb_dfm": null,
      "sb_b1": null,
      "sb_b2": null,
      "sb_bm": null,
      "ace": null,
      "ace2": null,
      "df": null,
      "df2": null,
      "b": null,
      "b2": null,
      "aceAvgPerSet": null,
      "dfAvgPerSet": null,
      "secSrvToDf": null,
      "srvGameToDf": null,
      "bAvgPerSet": null,
      "last_aceAvgPerSet": null,
      "last_dfAvgPerSet": null,
      "last_secSrvToDf": null,
      "last_srvGameToDf": null,
      "last_bAvgPerSet": null
    },
    "stats2": {
      "sb_a1": "8#8#9#9",
      "sb_a2": "7#13#13#8",
      "sb_am": "16#21#21#17",
      "sb_df1": "3#2#3#3",
      "sb_df2": "4#4#4#4",
      "sb_dfm": "8#4#7#7",
      "sb_b1": "1#2#3",
      "sb_b2": "2#3#2",
      "sb_bm": "3#4#4",
      "ace": "5 #9 #13^#6 #9^#3 ",
      "ace2": "5 #12 #20^#0 #13^#1 ",
      "df": "4 #2 #4^#0 #2^#1 ",
      "df2": "2 #2 #4^#3 #7^#3 ",
      "b": "0 #0 #0^#6 #2^#5 ",
      "b2": "1 #3 #1^#0 #1^#1 ",
      "aceAvgPerSet": "3.68",
      "dfAvgPerSet": "1.45",
      "secSrvToDf": "8.00",
      "srvGameToDf": "3.59",
      "bAvgPerSet": "3.00",
      "last_aceAvgPerSet": "2.83",
      "last_dfAvgPerSet": "1.17",
      "last_secSrvToDf": "7.25",
      "last_srvGameToDf": "3.33",
      "last_bAvgPerSet": "0.83"
    },
    "A": [
      {
        "book": "betclic",
        "lineType": "meczowa",
        "over": "+20.5 @1.8"
      },
      {
        "book": "betclic",
        "lineType": "player1",
        "over": "+10.5 @1.8"
      },
      {
        "book": "betclic",
        "lineType": "player2",
        "over": "+ 9.5 @1.8"
      }
    ],
    "A_cnt": 3,
    "A_book_cnt": 1,
    "DF": null,
    "DF_cnt": 0,
    "DF_book_cnt": 0,
    "B": null,
    "B_cnt": 0,
    "B_book_cnt": 0
  },
  {
    "id": "4924448670713537965",
    "matchStartTime": "16:00",
    "tournament": "Miami ATP • 1/64 finału",
    "eventName": "Terence Atmane - Daniel Altmaier",
    "p1": "Terence Atmane",
    "p2": "Daniel Altmaier",
    "atp": true,
    "tags1": null,
    "tags2": null,
    "updateTime": "10:10",
    "stats1": {
      "sb_a1": "9#10#9#8#9#10",
      "sb_a2": "6#7#5#6#5#7",
      "sb_am": "16#17#13#13#14#18",
      "sb_df1": "3#3#4#3#3#2",
      "sb_df2": "4#2#2#4#3#2",
      "sb_dfm": "8#5#6#6#6#4",
      "sb_b1": "2#2#2#2",
      "sb_b2": "3#3#3#3",
      "sb_bm": "5#5#4#5",
      "ace": "10^#6 #6^#5 #9 #11^",
      "ace2": "3^#5 #3^#4 #9 #5^",
      "df": "8^#2 #1^#0 #4 #2^",
      "df2": "2^#0 #0^#4 #2 #2^",
      "b": "4^#1 #4^#3 #1 #2^",
      "b2": "4^#4 #1^#0 #2 #1^",
      "aceAvgPerSet": "3.32",
      "dfAvgPerSet": "1.55",
      "secSrvToDf": "6.01",
      "srvGameToDf": "2.35",
      "bAvgPerSet": "0.87",
      "last_aceAvgPerSet": "2.67",
      "last_dfAvgPerSet": "0.50",
      "last_secSrvToDf": "7.92",
      "last_srvGameToDf": "4.08",
      "last_bAvgPerSet": "1.17"
    },
    "stats2": {
      "sb_a1": "6#6",
      "sb_a2": "4#5",
      "sb_am": "11#11",
      "sb_df1": "3#5",
      "sb_df2": "2#3",
      "sb_dfm": "5#7",
      "sb_b1": "2",
      "sb_b2": "4",
      "sb_bm": "5",
      "ace": "8 #8 #2 #8^#3 #7 ",
      "ace2": "1 #2 #0 #20^#3 #7 ",
      "df": "1 #2 #4 #4^#2 #5 ",
      "df2": "0 #1 #0 #3^#2 #1 ",
      "b": "1 #1 #0 #0^#1 #1 ",
      "b2": "4 #1 #4 #6^#6 #4 ",
      "aceAvgPerSet": "3.96",
      "dfAvgPerSet": "1.29",
      "secSrvToDf": "8.64",
      "srvGameToDf": "4.18",
      "bAvgPerSet": "1.08",
      "last_aceAvgPerSet": "3.00",
      "last_dfAvgPerSet": "1.33",
      "last_secSrvToDf": "9.92",
      "last_srvGameToDf": "4.04",
      "last_bAvgPerSet": "0.50"
    },
    "A": [
      {
        "book": "betclic",
        "lineType": "meczowa",
        "over": "+16.5 @1.8"
      },
      {
        "book": "betclic",
        "lineType": "player1",
        "over": "+ 9.5 @1.8"
      },
      {
        "book": "betclic",
        "lineType": "player2",
        "over": "+ 7.5 @1.8"
      }
    ],
    "A_cnt": 3,
    "A_book_cnt": 1,
    "DF": null,
    "DF_cnt": 0,
    "DF_book_cnt": 0,
    "B": null,
    "B_cnt": 0,
    "B_book_cnt": 0
  },
  {
    "id": "3402596402820296898",
    "matchStartTime": "16:00",
    "tournament": "Miami ATP • 1/64 finału",
    "eventName": "Martin Damm - Jacob Fearnley",
    "p1": "Martin Damm",
    "p2": "Jacob Fearnley",
    "atp": true,
    "tags1": null,
    "tags2": "DF",
    "updateTime": "10:10",
    "stats1": {
      "sb_a1": "15#17#15#12",
      "sb_a2": "3#7#6#15",
      "sb_am": "18#24#21#28",
      "sb_df1": "4#3#4#6",
      "sb_df2": "3#2#2#2",
      "sb_dfm": "7#5#6#7",
      "sb_b1": "2#2",
      "sb_b2": "1#2",
      "sb_bm": "3#4",
      "ace": "9 #23^#16 #11 #13 #36^",
      "ace2": "8 #11^#5 #2 #14 #14^",
      "df": "2 #3^#0 #2 #3 #4^",
      "df2": "5 #3^#2 #0 #0 #0^",
      "b": "0 #2^#1 #4 #1 #0^",
      "b2": "1 #2^#0 #0 #0 #0^",
      "aceAvgPerSet": "6.31",
      "dfAvgPerSet": "1.56",
      "secSrvToDf": "7.29",
      "srvGameToDf": "3.53",
      "bAvgPerSet": "0.75",
      "last_aceAvgPerSet": "8.83",
      "last_dfAvgPerSet": "1.17",
      "last_secSrvToDf": "9.42",
      "last_srvGameToDf": "4.67",
      "last_bAvgPerSet": "0.00"
    },
    "stats2": {
      "sb_a1": "6#6",
      "sb_a2": "11#2",
      "sb_am": "16#9",
      "sb_df1": "5#6",
      "sb_df2": "2#2",
      "sb_dfm": "7#9",
      "sb_b1": "1",
      "sb_b2": "3",
      "sb_bm": "4",
      "ace": "5^#6 #12 #2 #14^#7 ",
      "ace2": "20^#1 #5 #11 #7^#10 ",
      "df": "6^#5 #10 #7 #10^#5 ",
      "df2": "1^#2 #1 #1 #1^#1 ",
      "b": "1^#2 #5 #2 #2^#3 ",
      "b2": "4^#0 #4 #4 #4^#3 ",
      "aceAvgPerSet": "4.10",
      "dfAvgPerSet": "2.63",
      "secSrvToDf": "8.94",
      "srvGameToDf": "3.92",
      "bAvgPerSet": "1.20",
      "last_aceAvgPerSet": "3.83",
      "last_dfAvgPerSet": "2.83",
      "last_secSrvToDf": "6.25",
      "last_srvGameToDf": "2.38",
      "last_bAvgPerSet": "1.17"
    },
    "A": [
      {
        "book": "betclic",
        "lineType": "meczowa",
        "over": "+25.5 @1.8"
      },
      {
        "book": "betclic",
        "lineType": "player1",
        "over": "+16.5 @1.8"
      },
      {
        "book": "betclic",
        "lineType": "player2",
        "over": "+ 8.5 @1.8"
      }
    ],
    "A_cnt": 3,
    "A_book_cnt": 1,
    "DF": null,
    "DF_cnt": 0,
    "DF_book_cnt": 0,
    "B": null,
    "B_cnt": 0,
    "B_book_cnt": 0
  },
  {
    "id": "-868512664282650646",
    "matchStartTime": "16:00",
    "tournament": "Miami ATP • 1/64 finału",
    "eventName": "Aleksandar Kovacevic - Rei Sakamoto",
    "p1": "Aleksandar Kovacevic",
    "p2": "Rei Sakamoto",
    "atp": true,
    "tags1": "D",
    "tags2": null,
    "updateTime": "10:10",
    "stats1": {
      "sb_a1": "9#7#10#14#9",
      "sb_a2": "8#4#15#9#6",
      "sb_am": "16#11#22#22#16",
      "sb_df1": "4#4#2#5#3",
      "sb_df2": "2#3#1#2#2",
      "sb_dfm": "6#6#3#7#6",
      "sb_b1": "1#3#3",
      "sb_b2": "4#3#2",
      "sb_bm": "4#5#5",
      "ace": "16^#2 #9 #19^#15 #14 ",
      "ace2": "6^#4 #10 #9^#6 #17 ",
      "df": "1^#0 #4 #3^#3 #4 ",
      "df2": "4^#5 #5 #0^#1 #2 ",
      "b": "1^#2 #1 #1^#1 #0 ",
      "b2": "2^#0 #1 #1^#0 #1 ",
      "aceAvgPerSet": "4.37",
      "dfAvgPerSet": "1.39",
      "secSrvToDf": "9.15",
      "srvGameToDf": "3.92",
      "bAvgPerSet": "0.50",
      "last_aceAvgPerSet": "5.67",
      "last_dfAvgPerSet": "1.00",
      "last_secSrvToDf": "10.00",
      "last_srvGameToDf": "4.17",
      "last_bAvgPerSet": "0.67"
    },
    "stats2": {
      "sb_a1": null,
      "sb_a2": null,
      "sb_am": null,
      "sb_df1": null,
      "sb_df2": null,
      "sb_dfm": null,
      "sb_b1": null,
      "sb_b2": null,
      "sb_bm": null,
      "ace": "9 #14 #10 #6 #5 #4 ",
      "ace2": "5 #9 #0 #4 #6 #10 ",
      "df": "1 #1 #3 #4 #0 #2 ",
      "df2": "4 #1 #1 #1 #1 #2 ",
      "b": "0 #2 #2 #3 #4 #2 ",
      "b2": "1 #0 #0 #5 #0 #0 ",
      "aceAvgPerSet": "3.85",
      "dfAvgPerSet": "1.16",
      "secSrvToDf": "8.60",
      "srvGameToDf": "4.13",
      "bAvgPerSet": "1.50",
      "last_aceAvgPerSet": "1.50",
      "last_dfAvgPerSet": "0.83",
      "last_secSrvToDf": "10.75",
      "last_srvGameToDf": "4.67",
      "last_bAvgPerSet": "0.67"
    },
    "A": [
      {
        "book": "betclic",
        "lineType": "meczowa",
        "over": "+19.5 @1.8"
      },
      {
        "book": "betclic",
        "lineType": "player1",
        "over": "+10.5 @1.8"
      },
      {
        "book": "betclic",
        "lineType": "player2",
        "over": "+ 9.5 @1.8"
      }
    ],
    "A_cnt": 3,
    "A_book_cnt": 1,
    "DF": null,
    "DF_cnt": 0,
    "DF_book_cnt": 0,
    "B": null,
    "B_cnt": 0,
    "B_book_cnt": 0
  },
  {
    "id": "401363580085631576",
    "matchStartTime": "16:00",
    "tournament": "Miami ATP • 1/64 finału",
    "eventName": "Emilio Nava - Tomas Machac",
    "p1": "Emilio Nava",
    "p2": "Tomas Machac",
    "atp": true,
    "tags1": null,
    "tags2": null,
    "updateTime": "10:10",
    "stats1": {
      "sb_a1": "9#4#6#5#6",
      "sb_a2": "6#2#6#3#3",
      "sb_am": "16#8#14#8#8",
      "sb_df1": "4#3#4#2#3",
      "sb_df2": "2#2#2#2#3",
      "sb_dfm": "6#6#5#5#6",
      "sb_b1": "2#3",
      "sb_b2": "4#3",
      "sb_bm": "5#6",
      "ace": "12 #2 #12 #4 #6 #1 ",
      "ace2": "3 #1 #3 #3 #3 #1 ",
      "df": "3 #2 #3 #4 #3 #2 ",
      "df2": "2 #1 #2 #2 #0 #1 ",
      "b": "0 #0 #3 #1 #0 #0 ",
      "b2": "1 #4 #1 #0 #2 #5 ",
      "aceAvgPerSet": "3.69",
      "dfAvgPerSet": "1.26",
      "secSrvToDf": "8.28",
      "srvGameToDf": "3.83",
      "bAvgPerSet": "0.94",
      "last_aceAvgPerSet": "4.67",
      "last_dfAvgPerSet": "1.67",
      "last_secSrvToDf": "7.92",
      "last_srvGameToDf": "3.67",
      "last_bAvgPerSet": "0.83"
    },
    "stats2": {
      "sb_a1": "4#9",
      "sb_a2": "6#9",
      "sb_am": "11#17",
      "sb_df1": "2#4",
      "sb_df2": "2#3",
      "sb_dfm": "3#7",
      "sb_b1": "1#4",
      "sb_b2": "4#5",
      "sb_bm": "5#8",
      "ace": "1 #3 #6 #21^#5^#8^",
      "ace2": "7 #10 #24 #11^#8^#3^",
      "df": "4 #3 #6 #1^#1^#2^",
      "df2": "0 #5 #8 #4^#3^#0^",
      "b": "0 #5 #3 #4^#4^#3^",
      "b2": "3 #8 #3 #0^#1^#2^",
      "aceAvgPerSet": "2.96",
      "dfAvgPerSet": "1.24",
      "secSrvToDf": "8.96",
      "srvGameToDf": "3.91",
      "bAvgPerSet": "1.06",
      "last_aceAvgPerSet": "2.17",
      "last_dfAvgPerSet": "1.33",
      "last_secSrvToDf": "7.14",
      "last_srvGameToDf": "3.42",
      "last_bAvgPerSet": "0.67"
    },
    "A": [
      {
        "book": "betclic",
        "lineType": "meczowa",
        "over": "+16.5 @1.8"
      },
      {
        "book": "betclic",
        "lineType": "player1",
        "over": "+10.5 @1.8"
      },
      {
        "book": "betclic",
        "lineType": "player2",
        "over": "+ 6.5 @1.8"
      }
    ],
    "A_cnt": 3,
    "A_book_cnt": 1,
    "DF": null,
    "DF_cnt": 0,
    "DF_book_cnt": 0,
    "B": null,
    "B_cnt": 0,
    "B_book_cnt": 0
  },
  {
    "id": "-1787205205562754043",
    "matchStartTime": "19:30",
    "tournament": "Miami ATP • 1/64 finału",
    "eventName": "Zhizhen Zhang - Adrian Mannarino",
    "p1": "Zhizhen Zhang",
    "p2": "Adrian Mannarino",
    "atp": true,
    "tags1": null,
    "tags2": null,
    "updateTime": "10:10",
    "stats1": {
      "sb_a1": "5#8#5",
      "sb_a2": "10#12#5",
      "sb_am": "18#20#13",
      "sb_df1": "1#2#1",
      "sb_df2": "1#4#1",
      "sb_dfm": "3#5#2",
      "sb_b1": "1#2#3",
      "sb_b2": "3#3#3",
      "sb_bm": "4#4#5",
      "ace": "10 #2 #10 #8^#2 #12^",
      "ace2": "11 #7 #7 #7^#6 #18^",
      "df": "1 #3 #0 #1^#2 #0^",
      "df2": "3 #1 #2 #2^#0 #5^",
      "b": "0 #0 #2 #2^#0 #1^",
      "b2": "1 #1 #0 #4^#2 #0^",
      "aceAvgPerSet": "3.32",
      "dfAvgPerSet": "0.84",
      "secSrvToDf": "8.64",
      "srvGameToDf": "3.80",
      "bAvgPerSet": "0.50",
      "last_aceAvgPerSet": "2.00",
      "last_dfAvgPerSet": "0.67",
      "last_secSrvToDf": "11.33",
      "last_srvGameToDf": "4.83",
      "last_bAvgPerSet": "0.33"
    },
    "stats2": {
      "sb_a1": "4#5#5#5#7",
      "sb_a2": "11#9#13#17#17",
      "sb_am": "14#14#17#22#24",
      "sb_df1": "1#2#2#2#2",
      "sb_df2": "1#3#3#2#3",
      "sb_dfm": "3#5#4#4#5",
      "sb_b1": "1#2#1",
      "sb_b2": "3#3#4#2",
      "sb_bm": "4#5#3",
      "ace": "6^#5 #12^#5 #4 #11^",
      "ace2": "14^#3 #23^#4 #13 #23^",
      "df": "2^#4 #4^#0 #1 #3^",
      "df2": "3^#2 #1^#0 #1 #3^",
      "b": "2^#0 #1^#5 #0 #2^",
      "b2": "3^#3 #2^#2 #2 #2^",
      "aceAvgPerSet": "4.81",
      "dfAvgPerSet": "1.22",
      "secSrvToDf": "8.63",
      "srvGameToDf": "3.91",
      "bAvgPerSet": "1.07",
      "last_aceAvgPerSet": "2.17",
      "last_dfAvgPerSet": "1.50",
      "last_secSrvToDf": "8.72",
      "last_srvGameToDf": "3.56",
      "last_bAvgPerSet": "0.67"
    },
    "A": [
      {
        "book": "betclic",
        "lineType": "meczowa",
        "over": "+18.5 @1.8"
      },
      {
        "book": "betclic",
        "lineType": "player1",
        "over": "+11.5 @1.8"
      },
      {
        "book": "betclic",
        "lineType": "player2",
        "over": "+ 7.5 @1.8"
      }
    ],
    "A_cnt": 3,
    "A_book_cnt": 1,
    "DF": null,
    "DF_cnt": 0,
    "DF_book_cnt": 0,
    "B": null,
    "B_cnt": 0,
    "B_book_cnt": 0
  },
  {
    "id": "6996676656476890625",
    "matchStartTime": "16:00",
    "tournament": "Miami ATP • 1/64 finału",
    "eventName": "Giovanni Mpetshi Perricard - Camilo Ugo Carabelli",
    "p1": "Giovanni Mpetshi Perricard",
    "p2": "Camilo Ugo Carabelli",
    "atp": true,
    "tags1": "A",
    "tags2": null,
    "updateTime": "10:10",
    "stats1": {
      "sb_a1": "18#16#16#13",
      "sb_a2": "5#11#6#7",
      "sb_am": "25#28#21#20",
      "sb_df1": "2#3#2#2",
      "sb_df2": "1#2#3#2",
      "sb_dfm": "3#6#4#5",
      "sb_b1": "1#2#1",
      "sb_b2": "2#1#2",
      "sb_bm": "2#3#3",
      "ace": "11^#11 #29^#19^#20 #7^",
      "ace2": "6^#8 #16^#9^#4 #17^",
      "df": "7^#1 #2^#1^#2 #2^",
      "df2": "1^#3 #2^#0^#4 #2^",
      "b": "3^#1 #0^#1^#2 #0^",
      "b2": "1^#3 #1^#1^#0 #1^",
      "aceAvgPerSet": "6.20",
      "dfAvgPerSet": "1.17",
      "secSrvToDf": "6.46",
      "srvGameToDf": "3.82",
      "bAvgPerSet": "0.42",
      "last_aceAvgPerSet": "7.00",
      "last_dfAvgPerSet": "0.83",
      "last_secSrvToDf": "7.33",
      "last_srvGameToDf": "4.50",
      "last_bAvgPerSet": "0.33"
    },
    "stats2": {
      "sb_a1": "4#3#4#2#2",
      "sb_a2": "9#15#6#2#2",
      "sb_am": "13#18#9#3#4",
      "sb_df1": "4#3#3#2#3",
      "sb_df2": "2#4#2#2#2",
      "sb_dfm": "4#7#5#3#5",
      "sb_b1": "2#3#4#4#4",
      "sb_b2": "4#3#4#4#4",
      "sb_bm": "5#5#7#7#7",
      "ace": "3 #8 #4 #2 #2 #1 ",
      "ace2": "13 #9 #5 #5 #1 #0 ",
      "df": "1 #5 #7 #4 #4 #1 ",
      "df2": "0 #2 #1 #3 #1 #4 ",
      "b": "0 #1 #1 #0 #1 #5 ",
      "b2": "0 #0 #3 #1 #3 #2 ",
      "aceAvgPerSet": "4.96",
      "dfAvgPerSet": "1.41",
      "secSrvToDf": "9.33",
      "srvGameToDf": "3.90",
      "bAvgPerSet": "1.34",
      "last_aceAvgPerSet": "2.00",
      "last_dfAvgPerSet": "1.17",
      "last_secSrvToDf": "9.11",
      "last_srvGameToDf": "3.94",
      "last_bAvgPerSet": "1.00"
    },
    "A": [
      {
        "book": "betclic",
        "lineType": "meczowa",
        "over": "+22.5 @1.8"
      },
      {
        "book": "betclic",
        "lineType": "player1",
        "over": "+17.5 @1.8"
      },
      {
        "book": "betclic",
        "lineType": "player2",
        "over": "+ 4.5 @1.8"
      }
    ],
    "A_cnt": 3,
    "A_book_cnt": 1,
    "DF": null,
    "DF_cnt": 0,
    "DF_book_cnt": 0,
    "B": null,
    "B_cnt": 0,
    "B_book_cnt": 0
  },
  {
    "id": "-8648268154373214286",
    "matchStartTime": "16:00",
    "tournament": "Miami ATP • 1/64 finału",
    "eventName": "Denis Shapovalov - Botic Van De Zandschulp",
    "p1": "Denis Shapovalov",
    "p2": "Botic Van De Zandschulp",
    "atp": true,
    "tags1": "DF",
    "tags2": "DF",
    "updateTime": "10:10",
    "stats1": {
      "sb_a1": "6#8#8#10#10#12",
      "sb_a2": "4#5#6#3#9#3",
      "sb_am": "10#13#14#13#20#15",
      "sb_df1": "6#5#6#4#5#5",
      "sb_df2": "2#2#2#2#3#2",
      "sb_dfm": "7#7#8#6#7#7",
      "sb_b1": "1#4#3#2#2",
      "sb_b2": "4#3#2#2#2",
      "sb_bm": "5#6#5#4#4",
      "ace": "2 #14^#3^#8 #4^#17^",
      "ace2": "6 #4^#0^#0 #8^#2^",
      "df": "7 #9^#2^#4 #2^#2^",
      "df2": "2 #0^#3^#2 #4^#3^",
      "b": "1 #2^#4^#2 #1^#2^",
      "b2": "4 #3^#2^#5 #0^#1^",
      "aceAvgPerSet": "3.57",
      "dfAvgPerSet": "1.96",
      "secSrvToDf": "6.52",
      "srvGameToDf": "2.88",
      "bAvgPerSet": "1.20",
      "last_aceAvgPerSet": "3.67",
      "last_dfAvgPerSet": "3.17",
      "last_secSrvToDf": "4.50",
      "last_srvGameToDf": "2.11",
      "last_bAvgPerSet": "0.83"
    },
    "stats2": {
      "sb_a1": "6#5#7#8#6",
      "sb_a2": "4#4#8#10#7",
      "sb_am": "10#9#14#19#15",
      "sb_df1": "4#5#5#2#4",
      "sb_df2": "3#2#3#2#2",
      "sb_dfm": "8#7#8#6#6",
      "sb_b1": "1#2#3",
      "sb_b2": "3#3#1",
      "sb_bm": "4#4#4",
      "ace": "4^#6 #12^#4 #6 #9 ",
      "ace2": "12^#5 #4^#8 #8 #9 ",
      "df": "9^#5 #8^#4 #6 #1 ",
      "df2": "1^#3 #3^#4 #1 #1 ",
      "b": "3^#1 #1^#0 #3 #0 ",
      "b2": "4^#4 #2^#0 #2 #2 ",
      "aceAvgPerSet": "3.29",
      "dfAvgPerSet": "1.89",
      "secSrvToDf": "8.03",
      "srvGameToDf": "3.67",
      "bAvgPerSet": "1.00",
      "last_aceAvgPerSet": "2.50",
      "last_dfAvgPerSet": "2.33",
      "last_secSrvToDf": "7.23",
      "last_srvGameToDf": "3.17",
      "last_bAvgPerSet": "0.67"
    },
    "A": [
      {
        "book": "betclic",
        "lineType": "meczowa",
        "over": "+15.5 @1.8"
      },
      {
        "book": "betclic",
        "lineType": "player1",
        "over": "+10.5 @1.8"
      },
      {
        "book": "betclic",
        "lineType": "player2",
        "over": "+ 5.5 @1.8"
      }
    ],
    "A_cnt": 3,
    "A_book_cnt": 1,
    "DF": null,
    "DF_cnt": 0,
    "DF_book_cnt": 0,
    "B": null,
    "B_cnt": 0,
    "B_book_cnt": 0
  },
  {
    "id": "876525342255340098",
    "matchStartTime": "16:00",
    "tournament": "Miami ATP • 1/64 finału",
    "eventName": "Alejandro Tabilo - Francisco Comesana",
    "p1": "Alejandro Tabilo",
    "p2": "Francisco Comesana",
    "atp": true,
    "tags1": null,
    "tags2": null,
    "updateTime": "10:10",
    "stats1": {
      "sb_a1": "5#5#4#4",
      "sb_a2": "10#5#7#4",
      "sb_am": "13#12#12#9",
      "sb_df1": "2#1#2#2",
      "sb_df2": "4#1#2#2",
      "sb_dfm": "5#3#4#4",
      "sb_b1": "2#3#3",
      "sb_b2": "4#3#2",
      "sb_bm": "5#6#5",
      "ace": "3 #4 #6 #7^#7 #11^",
      "ace2": "6 #3 #1 #6^#2 #14^",
      "df": "0 #0 #0 #2^#0 #0^",
      "df2": "1 #3 #3 #5^#4 #4^",
      "b": "0 #4 #0 #4^#3 #3^",
      "b2": "3 #0 #2 #2^#1 #2^",
      "aceAvgPerSet": "2.54",
      "dfAvgPerSet": "0.53",
      "secSrvToDf": "8.97",
      "srvGameToDf": "4.63",
      "bAvgPerSet": "1.03",
      "last_aceAvgPerSet": "3.50",
      "last_dfAvgPerSet": "0.00",
      "last_secSrvToDf": "10.00",
      "last_srvGameToDf": "5.33",
      "last_bAvgPerSet": "1.00"
    },
    "stats2": {
      "sb_a1": "8#9#9#5#5",
      "sb_a2": "9#5#3#5#3",
      "sb_am": "16#13#11#10#8",
      "sb_df1": "4#4#3#3#3",
      "sb_df2": "2#3#4#2#3",
      "sb_dfm": "6#7#8#4#6",
      "sb_b1": "3#2",
      "sb_b2": "2#3",
      "sb_bm": "5#4",
      "ace": "1 #9^#12^#8^#2 #6 ",
      "ace2": "0 #3^#1^#6^#1 #0 ",
      "df": "1 #11^#7^#4^#4 #2 ",
      "df2": "2 #5^#4^#2^#2 #0 ",
      "b": "3 #2^#2^#1^#2 #4 ",
      "b2": "7 #2^#4^#1^#3 #2 ",
      "aceAvgPerSet": "3.35",
      "dfAvgPerSet": "1.54",
      "secSrvToDf": "9.88",
      "srvGameToDf": "3.51",
      "bAvgPerSet": "1.33",
      "last_aceAvgPerSet": "2.67",
      "last_dfAvgPerSet": "1.33",
      "last_secSrvToDf": "9.67",
      "last_srvGameToDf": "3.78",
      "last_bAvgPerSet": "1.50"
    },
    "A": [
      {
        "book": "betclic",
        "lineType": "meczowa",
        "over": "+18.5 @1.8"
      },
      {
        "book": "betclic",
        "lineType": "player1",
        "over": "+ 7.5 @1.8"
      },
      {
        "book": "betclic",
        "lineType": "player2",
        "over": "+10.5 @1.8"
      }
    ],
    "A_cnt": 3,
    "A_book_cnt": 1,
    "DF": null,
    "DF_cnt": 0,
    "DF_book_cnt": 0,
    "B": null,
    "B_cnt": 0,
    "B_book_cnt": 0
  },
  {
    "id": "5618149024427124053",
    "matchStartTime": "16:00",
    "tournament": "Miami ATP • 1/64 finału",
    "eventName": "Ethan Quinn - Hubert Hurkacz",
    "p1": "Ethan Quinn",
    "p2": "Hubert Hurkacz",
    "atp": true,
    "tags1": null,
    "tags2": "A",
    "updateTime": "10:10",
    "stats1": {
      "sb_a1": "8#9#10",
      "sb_a2": "20#10#22",
      "sb_am": "27#18#32",
      "sb_df1": "3#3#4",
      "sb_df2": "3#4#6",
      "sb_dfm": "6#6#9",
      "sb_b1": "2#3",
      "sb_b2": "2#4",
      "sb_bm": "3#6",
      "ace": "5 #4 #12 #8 #9^#12^",
      "ace2": "17 #2 #15 #6 #11^#9^",
      "df": "3 #3 #1 #3 #7^#2^",
      "df2": "6 #2 #5 #1 #8^#1^",
      "b": "1 #2 #0 #2 #3^#3^",
      "b2": "0 #5 #1 #1 #5^#0^",
      "aceAvgPerSet": "3.37",
      "dfAvgPerSet": "1.19",
      "secSrvToDf": "8.19",
      "srvGameToDf": "3.96",
      "bAvgPerSet": "0.88",
      "last_aceAvgPerSet": "3.50",
      "last_dfAvgPerSet": "1.50",
      "last_secSrvToDf": "10.67",
      "last_srvGameToDf": "4.06",
      "last_bAvgPerSet": "1.00"
    },
    "stats2": {
      "sb_a1": "15#11#13#15",
      "sb_a2": "10#11#13#12",
      "sb_am": "22#23#26#28",
      "sb_df1": "1#2#4#2",
      "sb_df2": "2#2#4#6",
      "sb_dfm": "3#4#6#7",
      "sb_b1": "1#2",
      "sb_b2": "2#2",
      "sb_bm": "3#3",
      "ace": "10 #10 #25^#14 #9^#18 ",
      "ace2": "9 #11 #13^#13 #12^#15 ",
      "df": "5 #2 #9^#0 #1^#2 ",
      "df2": "4 #3 #4^#3 #2^#6 ",
      "b": "1 #0 #1^#0 #0^#3 ",
      "b2": "1 #1 #2^#1 #3^#0 ",
      "aceAvgPerSet": "5.23",
      "dfAvgPerSet": "1.56",
      "secSrvToDf": "9.68",
      "srvGameToDf": "4.60",
      "bAvgPerSet": "1.10",
      "last_aceAvgPerSet": "3.83",
      "last_dfAvgPerSet": "0.67",
      "last_secSrvToDf": "9.83",
      "last_srvGameToDf": "4.75",
      "last_bAvgPerSet": "0.00"
    },
    "A": [
      {
        "book": "betclic",
        "lineType": "meczowa",
        "over": "+26.5 @1.8"
      },
      {
        "book": "betclic",
        "lineType": "player1",
        "over": "+11.5 @1.8"
      },
      {
        "book": "betclic",
        "lineType": "player2",
        "over": "+14.5 @1.8"
      }
    ],
    "A_cnt": 3,
    "A_book_cnt": 1,
    "DF": null,
    "DF_cnt": 0,
    "DF_book_cnt": 0,
    "B": null,
    "B_cnt": 0,
    "B_book_cnt": 0
  },
  {
    "id": "-7101437697153762384",
    "matchStartTime": "16:00",
    "tournament": "Miami ATP • 1/64 finału",
    "eventName": "James Duckworth - Roberto Bautista",
    "p1": "James Duckworth",
    "p2": "Roberto Bautista",
    "atp": true,
    "tags1": null,
    "tags2": "D",
    "updateTime": "10:10",
    "stats1": {
      "sb_a1": "5#6",
      "sb_a2": "2#4",
      "sb_am": "8#10",
      "sb_df1": "2#3",
      "sb_df2": "3#4",
      "sb_dfm": "6#6",
      "sb_b1": "3",
      "sb_b2": "3",
      "sb_bm": "5",
      "ace": "4 #5 #5 #9^#16 #7 ",
      "ace2": "3 #2 #8 #18^#9 #11 ",
      "df": "0 #10 #1 #4^#5 #0 ",
      "df2": "5 #3 #0 #2^#12 #0 ",
      "b": "0 #1 #0 #0^#4 #0 ",
      "b2": "1 #5 #3 #5^#6 #3 ",
      "aceAvgPerSet": "3.00",
      "dfAvgPerSet": "1.00",
      "secSrvToDf": "9.90",
      "srvGameToDf": "4.05",
      "bAvgPerSet": "0.93",
      "last_aceAvgPerSet": "2.83",
      "last_dfAvgPerSet": "2.33",
      "last_secSrvToDf": "7.07",
      "last_srvGameToDf": "2.57",
      "last_bAvgPerSet": "0.17"
    },
    "stats2": {
      "sb_a1": "3#4#6#4",
      "sb_a2": "9#6#8#9",
      "sb_am": "12#11#13#14",
      "sb_df1": "2#2#3#1",
      "sb_df2": "2#2#3#1",
      "sb_dfm": "3#4#5#3",
      "sb_b1": "2#2",
      "sb_b2": "4#3",
      "sb_bm": "5#5",
      "ace": "1^#4^#2 #2 #6^#11 ",
      "ace2": "9^#7^#9 #11 #11^#11 ",
      "df": "1^#2^#0 #0 #0^#1 ",
      "df2": "2^#3^#3 #2 #1^#6 ",
      "b": "0^#3^#2 #0 #4^#1 ",
      "b2": "3^#1^#4 #4 #3^#6 ",
      "aceAvgPerSet": "3.28",
      "dfAvgPerSet": "1.07",
      "secSrvToDf": "9.13",
      "srvGameToDf": "4.35",
      "bAvgPerSet": "1.07",
      "last_aceAvgPerSet": "1.67",
      "last_dfAvgPerSet": "0.33",
      "last_secSrvToDf": "6.17",
      "last_srvGameToDf": "4.83",
      "last_bAvgPerSet": "0.33"
    },
    "A": [
      {
        "book": "betclic",
        "lineType": "meczowa",
        "over": "+19.5 @1.8"
      },
      {
        "book": "betclic",
        "lineType": "player1",
        "over": "+13.5 @1.8"
      },
      {
        "book": "betclic",
        "lineType": "player2",
        "over": "+ 6.5 @1.8"
      }
    ],
    "A_cnt": 3,
    "A_book_cnt": 1,
    "DF": null,
    "DF_cnt": 0,
    "DF_book_cnt": 0,
    "B": null,
    "B_cnt": 0,
    "B_book_cnt": 0
  },
  {
    "id": "2209738515302512688",
    "matchStartTime": "16:00",
    "tournament": "Miami ATP • 1/64 finału",
    "eventName": "Zizou Bergs - Jenson Brooksby",
    "p1": "Zizou Bergs",
    "p2": "Jenson Brooksby",
    "atp": true,
    "tags1": "DF",
    "tags2": null,
    "updateTime": "10:10",
    "stats1": {
      "sb_a1": "6#7#6#7#7",
      "sb_a2": "6#8#2#7#13",
      "sb_am": "12#16#9#13#20",
      "sb_df1": "4#4#3#3#2",
      "sb_df2": "2#3#2#2#2",
      "sb_dfm": "6#8#5#5#5",
      "sb_b1": "2#3#2#2",
      "sb_b2": "4#3#3#1",
      "sb_bm": "6#5#5#3",
      "ace": "3 #5 #4 #2 #17^#10 ",
      "ace2": "1 #5 #3 #9 #7^#8 ",
      "df": "4 #2 #4 #4 #2^#4 ",
      "df2": "1 #4 #3 #1 #2^#6 ",
      "b": "0 #1 #0 #0 #1^#3 ",
      "b2": "4 #0 #2 #4 #0^#3 ",
      "aceAvgPerSet": "2.96",
      "dfAvgPerSet": "1.61",
      "secSrvToDf": "7.75",
      "srvGameToDf": "3.08",
      "bAvgPerSet": "0.87",
      "last_aceAvgPerSet": "2.00",
      "last_dfAvgPerSet": "1.67",
      "last_secSrvToDf": "8.58",
      "last_srvGameToDf": "3.08",
      "last_bAvgPerSet": "0.33"
    },
    "stats2": {
      "sb_a1": "4#2#2#3#2#3",
      "sb_a2": "6#8#8#7#6#6",
      "sb_am": "11#10#10#10#9#9",
      "sb_df1": "2#2#3#3#2#2",
      "sb_df2": "2#2#4#2#3#2",
      "sb_dfm": "4#5#7#5#5#4",
      "sb_b1": "3#3#2#3#2",
      "sb_b2": "3#4#3#3#3",
      "sb_bm": "6#6#4#5#5",
      "ace": "6 #2 #0 #4 #3 #0 ",
      "ace2": "6 #8 #7 #7 #4 #5 ",
      "df": "1 #1 #2 #1 #3 #3 ",
      "df2": "1 #0 #0 #1 #4 #3 ",
      "b": "1 #2 #0 #1 #2 #1 ",
      "b2": "3 #0 #1 #0 #0 #2 ",
      "aceAvgPerSet": "3.80",
      "dfAvgPerSet": "1.17",
      "secSrvToDf": "8.94",
      "srvGameToDf": "4.26",
      "bAvgPerSet": "1.07",
      "last_aceAvgPerSet": "1.17",
      "last_dfAvgPerSet": "1.00",
      "last_secSrvToDf": "9.67",
      "last_srvGameToDf": "4.42",
      "last_bAvgPerSet": "0.50"
    },
    "A": [
      {
        "book": "betclic",
        "lineType": "meczowa",
        "over": "+10.5 @1.8"
      },
      {
        "book": "betclic",
        "lineType": "player1",
        "over": "+ 7.5 @1.8"
      },
      {
        "book": "betclic",
        "lineType": "player2",
        "over": "+ 3.5 @1.8"
      }
    ],
    "A_cnt": 3,
    "A_book_cnt": 1,
    "DF": null,
    "DF_cnt": 0,
    "DF_book_cnt": 0,
    "B": null,
    "B_cnt": 0,
    "B_book_cnt": 0
  },
  {
    "id": "3840732470265801983",
    "matchStartTime": "16:00",
    "tournament": "Miami WTA • 1/64 finału",
    "eventName": "Emiliana Arango - Oksana Selekhmeteva",
    "p1": "Emiliana Arango",
    "p2": "Oksana Selekhmeteva",
    "atp": false,
    "tags1": null,
    "tags2": null,
    "updateTime": "10:10",
    "stats1": {
      "sb_a1": "1#1#1#1",
      "sb_a2": "3#1#3#1",
      "sb_am": "3#2#2",
      "sb_df1": "3#3#3#3",
      "sb_df2": "4#5#4#4",
      "sb_dfm": "7",
      "sb_b1": "3#5",
      "sb_b2": "5#5",
      "sb_bm": "7#9",
      "ace": "1^#0 #0 #0 #0 #0 ",
      "ace2": "0^#0 #1 #3 #1 #1 ",
      "df": "6^#2 #3 #0 #0 #4 ",
      "df2": "4^#4 #6 #2 #2 #2 ",
      "b": "3^#6 #3 #2 #1 #3 ",
      "b2": "4^#4 #7 #4 #4 #6 ",
      "aceAvgPerSet": "0.45",
      "dfAvgPerSet": "1.44",
      "secSrvToDf": "5.05",
      "srvGameToDf": "2.78",
      "bAvgPerSet": "1.61",
      "last_aceAvgPerSet": "0.00",
      "last_dfAvgPerSet": "1.00",
      "last_secSrvToDf": "6.33",
      "last_srvGameToDf": "3.25",
      "last_bAvgPerSet": "1.67"
    },
    "stats2": {
      "sb_a1": "3#3#2#1",
      "sb_a2": "2#2#7#1",
      "sb_am": "4#4#8",
      "sb_df1": "6#5#5#5",
      "sb_df2": "7#5#9#4",
      "sb_dfm": null,
      "sb_b1": "4#4",
      "sb_b2": "5#4",
      "sb_bm": "8#7",
      "ace": "1 #2^#3 #1^#2^#2 ",
      "ace2": "0 #5^#1 #3^#3^#1 ",
      "df": "4 #10^#6 #8^#5^#4 ",
      "df2": "3 #8^#1 #2^#8^#1 ",
      "b": "0 #6^#6 #5^#6^#4 ",
      "b2": "2 #8^#3 #4^#7^#0 ",
      "aceAvgPerSet": "1.75",
      "dfAvgPerSet": "2.16",
      "secSrvToDf": "5.74",
      "srvGameToDf": "2.69",
      "bAvgPerSet": "2.00",
      "last_aceAvgPerSet": "0.50",
      "last_dfAvgPerSet": "2.17",
      "last_secSrvToDf": "4.88",
      "last_srvGameToDf": "2.54",
      "last_bAvgPerSet": "1.50"
    },
    "A": [
      {
        "book": "betclic",
        "lineType": "meczowa",
        "over": "+ 2.5 @1.8"
      },
      {
        "book": "superbet",
        "lineType": "player1",
        "over": "+ 0.5 @2.55"
      },
      {
        "book": "betclic",
        "lineType": "player1",
        "over": "+ 0.5 @1.6"
      },
      {
        "book": "superbet",
        "lineType": "player2",
        "over": "+ 0.5 @1.7"
      },
      {
        "book": "betclic",
        "lineType": "player2",
        "over": "+ 1.5 @1.8"
      }
    ],
    "A_cnt": 5,
    "A_book_cnt": 2,
    "DF": [
      {
        "book": "superbet",
        "lineType": "player1",
        "over": "+ 2.5 @1.73"
      },
      {
        "book": "superbet",
        "lineType": "player2",
        "over": "+ 4.5 @1.72"
      }
    ],
    "DF_cnt": 2,
    "DF_book_cnt": 1,
    "B": null,
    "B_cnt": 0,
    "B_book_cnt": 0
  },
  {
    "id": "-3596400467739095444",
    "matchStartTime": "19:30",
    "tournament": "Miami WTA • 1/64 finału",
    "eventName": "Sofia Kenin - Anna Blinkova",
    "p1": "Sofia Kenin",
    "p2": "Anna Blinkova",
    "atp": false,
    "tags1": null,
    "tags2": null,
    "updateTime": "10:10",
    "stats1": {
      "sb_a1": "1#2#1#2",
      "sb_a2": "5#11#11#9",
      "sb_am": "7",
      "sb_df1": "5#5#5#5",
      "sb_df2": "4#3#4#4",
      "sb_dfm": null,
      "sb_b1": null,
      "sb_b2": null,
      "sb_bm": null,
      "ace": "2^#0 #1^#0 #1 #6 ",
      "ace2": "5^#20 #20^#4 #15 #5 ",
      "df": "7^#5 #4^#5 #4 #4 ",
      "df2": "3^#5 #4^#6 #1 #1 ",
      "b": "3^#1 #1^#2 #0 #2 ",
      "b2": "4^#3 #4^#6 #3 #3 ",
      "aceAvgPerSet": "0.80",
      "dfAvgPerSet": "2.07",
      "secSrvToDf": "4.16",
      "srvGameToDf": "2.27",
      "bAvgPerSet": "1.11",
      "last_aceAvgPerSet": "1.17",
      "last_dfAvgPerSet": "2.17",
      "last_secSrvToDf": "5.15",
      "last_srvGameToDf": "2.50",
      "last_bAvgPerSet": "0.67"
    },
    "stats2": {
      "sb_a1": "1#1#2#2",
      "sb_a2": "4#6#2#4",
      "sb_am": "5#5#4#6",
      "sb_df1": "4#4#4#4",
      "sb_df2": "4#3#2#5",
      "sb_dfm": "9",
      "sb_b1": "2",
      "sb_b2": "5",
      "sb_bm": "7",
      "ace": "0^#2 #1 #1 #1 #0 ",
      "ace2": "1^#7 #6 #5 #5 #3 ",
      "df": "5^#2 #3 #1 #1 #3 ",
      "df2": "2^#3 #1 #2 #4 #1 ",
      "b": "4^#4 #0 #1 #1 #3 ",
      "b2": "8^#2 #2 #3 #5 #6 ",
      "aceAvgPerSet": "1.35",
      "dfAvgPerSet": "1.90",
      "secSrvToDf": "6.10",
      "srvGameToDf": "2.89",
      "bAvgPerSet": "1.63",
      "last_aceAvgPerSet": "0.33",
      "last_dfAvgPerSet": "1.17",
      "last_secSrvToDf": "4.92",
      "last_srvGameToDf": "3.72",
      "last_bAvgPerSet": "0.67"
    },
    "A": [
      {
        "book": "betclic",
        "lineType": "meczowa",
        "over": "+ 7.5 @1.8"
      },
      {
        "book": "betfan",
        "lineType": "meczowa",
        "over": "+10.5 @1.7"
      },
      {
        "book": "betfan",
        "lineType": "meczowa",
        "over": "+11.5 @2"
      },
      {
        "book": "betclic",
        "lineType": "player1",
        "over": "+ 2.5 @1.8"
      },
      {
        "book": "betclic",
        "lineType": "player2",
        "over": "+ 5.5 @1.6"
      }
    ],
    "A_cnt": 5,
    "A_book_cnt": 2,
    "DF": null,
    "DF_cnt": 0,
    "DF_book_cnt": 0,
    "B": null,
    "B_cnt": 0,
    "B_book_cnt": 0
  },
  {
    "id": "-4644500651826367411",
    "matchStartTime": "16:00",
    "tournament": "Miami WTA • 1/64 finału",
    "eventName": "Francesca Jones - Venus Williams",
    "p1": "Francesca Jones",
    "p2": "Venus Williams",
    "atp": false,
    "tags1": null,
    "tags2": null,
    "updateTime": "10:10",
    "stats1": {
      "sb_a1": "2#3",
      "sb_a2": "6#4",
      "sb_am": "8#7",
      "sb_df1": "3#4",
      "sb_df2": "3#4",
      "sb_dfm": null,
      "sb_b1": null,
      "sb_b2": null,
      "sb_bm": null,
      "ace": "0 #0^#1^#1^#0 #1 ",
      "ace2": "4 #5^#8^#4^#2 #8 ",
      "df": "1 #1^#3^#6^#4 #6 ",
      "df2": "2 #3^#6^#4^#3 #5 ",
      "b": "0 #5^#5^#6^#2 #1 ",
      "b2": "4 #7^#4^#6^#4 #2 ",
      "aceAvgPerSet": "0.84",
      "dfAvgPerSet": "1.58",
      "secSrvToDf": "4.56",
      "srvGameToDf": "2.58",
      "bAvgPerSet": "1.81",
      "last_aceAvgPerSet": "0.17",
      "last_dfAvgPerSet": "1.17",
      "last_secSrvToDf": "2.92",
      "last_srvGameToDf": "3.42",
      "last_bAvgPerSet": "1.83"
    },
    "stats2": {
      "sb_a1": "4#5",
      "sb_a2": "5#3",
      "sb_am": "8",
      "sb_df1": "5#6",
      "sb_df2": "3#6",
      "sb_dfm": null,
      "sb_b1": null,
      "sb_b2": null,
      "sb_bm": null,
      "ace": "4^#2 #9^#1 #7^#4^",
      "ace2": "10^#0 #5^#1 #7^#7^",
      "df": "6^#3 #5^#5 #4^#10^",
      "df2": "2^#5 #1^#1 #1^#2^",
      "b": "1^#2 #3^#2 #3^#3^",
      "b2": "4^#5 #5^#5 #5^#5^",
      "aceAvgPerSet": "1.60",
      "dfAvgPerSet": "2.34",
      "secSrvToDf": "7.02",
      "srvGameToDf": "3.69",
      "bAvgPerSet": "1.68",
      "last_aceAvgPerSet": "2.00",
      "last_dfAvgPerSet": "1.67",
      "last_secSrvToDf": "6.61",
      "last_srvGameToDf": "3.33",
      "last_bAvgPerSet": "1.00"
    },
    "A": [
      {
        "book": "betclic",
        "lineType": "meczowa",
        "over": "+ 7.5 @1.8"
      },
      {
        "book": "superbet",
        "lineType": "player1",
        "over": "+ 1.5 @1.52"
      },
      {
        "book": "betclic",
        "lineType": "player1",
        "over": "+ 2.5 @1.8"
      },
      {
        "book": "superbet",
        "lineType": "player2",
        "over": "+ 4.5 @1.85"
      },
      {
        "book": "betclic",
        "lineType": "player2",
        "over": "+ 4.5 @1.8"
      }
    ],
    "A_cnt": 5,
    "A_book_cnt": 2,
    "DF": [
      {
        "book": "superbet",
        "lineType": "player1",
        "over": "+ 2.5 @1.61"
      },
      {
        "book": "superbet",
        "lineType": "player2",
        "over": "+ 4.5 @2.05"
      }
    ],
    "DF_cnt": 2,
    "DF_book_cnt": 1,
    "B": null,
    "B_cnt": 0,
    "B_book_cnt": 0
  },
  {
    "id": "-234971367161486736",
    "matchStartTime": "16:00",
    "tournament": "Miami WTA • 1/64 finału",
    "eventName": "Dayana Yastremska - Ashlyn Krueger",
    "p1": "Dayana Yastremska",
    "p2": "Ashlyn Krueger",
    "atp": false,
    "tags1": null,
    "tags2": null,
    "updateTime": "10:10",
    "stats1": {
      "sb_a1": "4#4#2#2#3",
      "sb_a2": "1#3#2#4#2",
      "sb_am": "5#7#4",
      "sb_df1": "6#6#5#4#4",
      "sb_df2": "3#3#5#3#3",
      "sb_dfm": null,
      "sb_b1": "5#5#3",
      "sb_b2": "5#4#5",
      "sb_bm": "9#8#8",
      "ace": "8^#5 #0 #0 #1 #4^",
      "ace2": "2^#0 #0 #3 #4 #0^",
      "df": "15^#5 #4 #7 #4 #4^",
      "df2": "4^#3 #1 #3 #2 #2^",
      "b": "6^#5 #1 #0 #2 #8^",
      "b2": "7^#2 #3 #4 #6 #8^",
      "aceAvgPerSet": "1.25",
      "dfAvgPerSet": "2.30",
      "secSrvToDf": "6.87",
      "srvGameToDf": "2.72",
      "bAvgPerSet": "1.59",
      "last_aceAvgPerSet": "1.67",
      "last_dfAvgPerSet": "3.83",
      "last_secSrvToDf": "4.91",
      "last_srvGameToDf": "1.78",
      "last_bAvgPerSet": "1.83"
    },
    "stats2": {
      "sb_a1": "4#5#4#5",
      "sb_a2": "4#3#3#1",
      "sb_am": "8#8#8#6",
      "sb_df1": "4#5#5#5",
      "sb_df2": "4#5#3#3",
      "sb_dfm": "8",
      "sb_b1": "3#4#4#5",
      "sb_b2": "5#4#5#4",
      "sb_bm": "8#7#8#8",
      "ace": "3 #11^#1 #5 #5 #10 ",
      "ace2": "2 #0^#1 #5 #9 #0 ",
      "df": "4 #7^#4 #7 #1 #5 ",
      "df2": "1 #5^#3 #5 #0 #1 ",
      "b": "1 #6^#4 #2 #2 #4 ",
      "b2": "4 #5^#1 #4 #1 #2 ",
      "aceAvgPerSet": "2.06",
      "dfAvgPerSet": "2.14",
      "secSrvToDf": "7.29",
      "srvGameToDf": "3.64",
      "bAvgPerSet": "1.58",
      "last_aceAvgPerSet": "3.00",
      "last_dfAvgPerSet": "2.17",
      "last_secSrvToDf": "4.72",
      "last_srvGameToDf": "3.14",
      "last_bAvgPerSet": "1.50"
    },
    "A": [
      {
        "book": "superbet",
        "lineType": "meczowa",
        "over": "+ 6.5 @1.65"
      },
      {
        "book": "betclic",
        "lineType": "meczowa",
        "over": "+ 8.5 @1.8"
      },
      {
        "book": "superbet",
        "lineType": "player1",
        "over": "+ 2.5 @1.88"
      },
      {
        "book": "betclic",
        "lineType": "player1",
        "over": "+ 3.5 @1.6"
      },
      {
        "book": "superbet",
        "lineType": "player2",
        "over": "+ 4.5 @2.17"
      },
      {
        "book": "betclic",
        "lineType": "player2",
        "over": "+ 4.5 @1.8"
      }
    ],
    "A_cnt": 6,
    "A_book_cnt": 2,
    "DF": [
      {
        "book": "superbet",
        "lineType": "meczowa",
        "over": "+10.5 @2"
      },
      {
        "book": "superbet",
        "lineType": "player1",
        "over": "+ 5.5 @1.8"
      },
      {
        "book": "superbet",
        "lineType": "player2",
        "over": "+ 4.5 @1.97"
      }
    ],
    "DF_cnt": 3,
    "DF_book_cnt": 1,
    "B": null,
    "B_cnt": 0,
    "B_book_cnt": 0
  },
  {
    "id": "-4456289241264459465",
    "matchStartTime": "16:00",
    "tournament": "Miami WTA • 1/64 finału",
    "eventName": "Hailey Baptiste - Tatjana Maria",
    "p1": "Hailey Baptiste",
    "p2": "Tatjana Maria",
    "atp": false,
    "tags1": null,
    "tags2": null,
    "updateTime": "10:10",
    "stats1": {
      "sb_a1": "3#3#4#5",
      "sb_a2": "6#1#4#4",
      "sb_am": "9#3#8#8",
      "sb_df1": "4#4#4#4",
      "sb_df2": "2#3#4#5",
      "sb_dfm": "8#8",
      "sb_b1": "2#3#3",
      "sb_b2": "5#5#4",
      "sb_bm": "6#7#6",
      "ace": "6^#0^#8 #10 #3^#4^",
      "ace2": "6^#1^#6 #0 #5^#0^",
      "df": "4^#4^#4 #5 #5^#4^",
      "df2": "5^#6^#2 #2 #6^#3^",
      "b": "3^#4^#1 #4 #4^#7^",
      "b2": "3^#3^#4 #2 #3^#5^",
      "aceAvgPerSet": "1.52",
      "dfAvgPerSet": "1.65",
      "secSrvToDf": "6.68",
      "srvGameToDf": "3.27",
      "bAvgPerSet": "1.25",
      "last_aceAvgPerSet": "1.00",
      "last_dfAvgPerSet": "1.33",
      "last_secSrvToDf": "5.64",
      "last_srvGameToDf": "3.72",
      "last_bAvgPerSet": "1.17"
    },
    "stats2": {
      "sb_a1": "3#3#7#4#4",
      "sb_a2": "4#4#2#2#1",
      "sb_am": "7#7#5",
      "sb_df1": "3#3#3#3#3",
      "sb_df2": "3#2#5#3#1",
      "sb_dfm": "4",
      "sb_b1": "3",
      "sb_b2": "5",
      "sb_bm": "8",
      "ace": "4^#0 #7^#4 #3 #7 ",
      "ace2": "4^#4 #2^#1 #2 #1 ",
      "df": "3^#1 #4^#1 #3 #2 ",
      "df2": "1^#2 #9^#1 #0 #1 ",
      "b": "4^#2 #2^#1 #1 #3 ",
      "b2": "5^#4 #3^#3 #5 #5 ",
      "aceAvgPerSet": "1.72",
      "dfAvgPerSet": "1.88",
      "secSrvToDf": "7.56",
      "srvGameToDf": "3.22",
      "bAvgPerSet": "1.77",
      "last_aceAvgPerSet": "1.50",
      "last_dfAvgPerSet": "0.83",
      "last_secSrvToDf": "13.50",
      "last_srvGameToDf": "4.75",
      "last_bAvgPerSet": "1.50"
    },
    "A": [
      {
        "book": "betclic",
        "lineType": "meczowa",
        "over": "+ 9.5 @1.8"
      },
      {
        "book": "superbet",
        "lineType": "player1",
        "over": "+ 3.5 @1.67"
      },
      {
        "book": "betclic",
        "lineType": "player1",
        "over": "+ 4.5 @1.8"
      },
      {
        "book": "superbet",
        "lineType": "player2",
        "over": "+ 3.5 @2.12"
      },
      {
        "book": "betclic",
        "lineType": "player2",
        "over": "+ 4.5 @1.8"
      }
    ],
    "A_cnt": 5,
    "A_book_cnt": 2,
    "DF": [
      {
        "book": "superbet",
        "lineType": "player1",
        "over": "+ 2.5 @1.76"
      },
      {
        "book": "superbet",
        "lineType": "player2",
        "over": "+ 1.5 @1.59"
      }
    ],
    "DF_cnt": 2,
    "DF_book_cnt": 1,
    "B": null,
    "B_cnt": 0,
    "B_book_cnt": 0
  },
  {
    "id": "553194260124852905",
    "matchStartTime": "01:10",
    "tournament": "Miami WTA • 1/64 finału",
    "eventName": "Katerina Siniakova - Camila Osorio",
    "p1": "Katerina Siniakova",
    "p2": "Camila Osorio",
    "atp": false,
    "tags1": null,
    "tags2": "DF",
    "updateTime": "10:10",
    "stats1": {
      "sb_a1": "1#2#5#2#2#2",
      "sb_a2": "2#2#1#4#2#4",
      "sb_am": "3#4#7#6",
      "sb_df1": "5#5#4#5#5#5",
      "sb_df2": "4#5#5#6#6#4",
      "sb_dfm": "8",
      "sb_b1": "4#5#5",
      "sb_b2": "6#4#5",
      "sb_bm": "8#8#9",
      "ace": "0^#2^#5^#1 #1^#0 ",
      "ace2": "6^#2^#2^#6 #0^#1 ",
      "df": "3^#6^#3^#2 #5^#3 ",
      "df2": "10^#5^#7^#9 #6^#2 ",
      "b": "7^#4^#4^#2 #4^#6 ",
      "b2": "7^#4^#3^#4 #5^#2 ",
      "aceAvgPerSet": "0.83",
      "dfAvgPerSet": "1.73",
      "secSrvToDf": "5.96",
      "srvGameToDf": "2.90",
      "bAvgPerSet": "1.81",
      "last_aceAvgPerSet": "1.17",
      "last_dfAvgPerSet": "1.50",
      "last_secSrvToDf": "7.89",
      "last_srvGameToDf": "3.78",
      "last_bAvgPerSet": "1.33"
    },
    "stats2": {
      "sb_a1": "2#2#2#2#3#2",
      "sb_a2": "5#2#2#3#4#2",
      "sb_am": "6#4#3#4#6",
      "sb_df1": "6#5#5#5#5#6",
      "sb_df2": "2#2#2#4#6#5",
      "sb_dfm": "8#11",
      "sb_b1": "4#4#4#5#5",
      "sb_b2": "5#6#5#5#5",
      "sb_bm": "8#9#8#9#9",
      "ace": "1^#5^#0 #4 #1 #0^",
      "ace2": "9^#3^#0 #2 #4 #1^",
      "df": "5^#10^#4 #6 #4 #6^",
      "df2": "1^#2^#1 #5 #3 #5^",
      "b": "2^#5^#6 #4 #2 #5^",
      "b2": "5^#4^#3 #3 #6 #4^",
      "aceAvgPerSet": "1.59",
      "dfAvgPerSet": "2.33",
      "secSrvToDf": "6.83",
      "srvGameToDf": "3.14",
      "bAvgPerSet": "1.89",
      "last_aceAvgPerSet": "1.67",
      "last_dfAvgPerSet": "3.00",
      "last_secSrvToDf": "2.88",
      "last_srvGameToDf": "2.10",
      "last_bAvgPerSet": "1.83"
    },
    "A": [
      {
        "book": "betclic",
        "lineType": "meczowa",
        "over": "+ 2.5 @1.6"
      },
      {
        "book": "betfan",
        "lineType": "meczowa",
        "over": "+ 5.5 @1.7"
      },
      {
        "book": "betfan",
        "lineType": "meczowa",
        "over": "+ 6.5 @2"
      },
      {
        "book": "betclic",
        "lineType": "player1",
        "over": "+ 1.5 @1.8"
      },
      {
        "book": "betclic",
        "lineType": "player2",
        "over": "+ 1.5 @1.6"
      }
    ],
    "A_cnt": 5,
    "A_book_cnt": 2,
    "DF": null,
    "DF_cnt": 0,
    "DF_book_cnt": 0,
    "B": null,
    "B_cnt": 0,
    "B_book_cnt": 0
  },
  {
    "id": "7791686662154866856",
    "matchStartTime": "17:10",
    "tournament": "Miami WTA • 1/64 finału",
    "eventName": "Magda Linette - Varvara Gracheva",
    "p1": "Magda Linette",
    "p2": "Varvara Gracheva",
    "atp": false,
    "tags1": null,
    "tags2": "DF",
    "updateTime": "10:10",
    "stats1": {
      "sb_a1": "3#3#4#5#5#6",
      "sb_a2": "4#1#3#7#5#6",
      "sb_am": "8#4#7#10#9",
      "sb_df1": "3#3#2#3#3#3",
      "sb_df2": "5#7#3#3#4#4",
      "sb_dfm": "5",
      "sb_b1": "5#5#3#3",
      "sb_b2": "4#3#4#4",
      "sb_bm": "8#8#6#7",
      "ace": "1 #4^#4 #2 #5^#10^",
      "ace2": "1 #2^#0 #3 #1^#5^",
      "df": "3 #5^#2 #2 #1^#4^",
      "df2": "4 #6^#1 #3 #4^#5^",
      "b": "1 #4^#4 #1 #6^#4^",
      "b2": "4 #4^#2 #4 #3^#2^",
      "aceAvgPerSet": "1.57",
      "dfAvgPerSet": "1.16",
      "secSrvToDf": "6.83",
      "srvGameToDf": "3.44",
      "bAvgPerSet": "1.33",
      "last_aceAvgPerSet": "2.17",
      "last_dfAvgPerSet": "0.83",
      "last_secSrvToDf": "7.33",
      "last_srvGameToDf": "3.61",
      "last_bAvgPerSet": "1.17"
    },
    "stats2": {
      "sb_a1": "2#3#4#3",
      "sb_a2": "4#4#5#4",
      "sb_am": "6#7#6",
      "sb_df1": "4#4#4#4",
      "sb_df2": "3#2#3#2",
      "sb_dfm": "6",
      "sb_b1": "2#3",
      "sb_b2": "5#5",
      "sb_bm": "7#7",
      "ace": "0 #2 #3^#6^#3 #1 ",
      "ace2": "5 #4 #5^#9^#2 #6 ",
      "df": "8 #3 #5^#1^#4 #3 ",
      "df2": "3 #1 #1^#3^#3 #0 ",
      "b": "1 #1 #5^#4^#2 #2 ",
      "b2": "4 #5 #6^#3^#0 #5 ",
      "aceAvgPerSet": "1.55",
      "dfAvgPerSet": "1.79",
      "secSrvToDf": "7.47",
      "srvGameToDf": "3.39",
      "bAvgPerSet": "1.71",
      "last_aceAvgPerSet": "0.67",
      "last_dfAvgPerSet": "2.17",
      "last_secSrvToDf": "3.67",
      "last_srvGameToDf": "2.99",
      "last_bAvgPerSet": "0.83"
    },
    "A": [
      {
        "book": "superbet",
        "lineType": "meczowa",
        "over": "+ 6.5 @1.65"
      },
      {
        "book": "betclic",
        "lineType": "meczowa",
        "over": "+ 7.5 @1.8"
      },
      {
        "book": "betfan",
        "lineType": "meczowa",
        "over": "+ 7.5 @1.6"
      },
      {
        "book": "betfan",
        "lineType": "meczowa",
        "over": "+ 8.5 @2"
      },
      {
        "book": "betclic",
        "lineType": "player1",
        "over": "+ 4.5 @1.8"
      },
      {
        "book": "superbet",
        "lineType": "player1",
        "over": "+ 4.5 @1.65"
      },
      {
        "book": "betfan",
        "lineType": "player1",
        "over": "+ 5.5 @1.6"
      },
      {
        "book": "betfan",
        "lineType": "player1",
        "over": "+ 6.5 @2"
      },
      {
        "book": "superbet",
        "lineType": "player2",
        "over": "+ 1.5 @1.6"
      },
      {
        "book": "betfan",
        "lineType": "player2",
        "over": "+ 1.5 @1.4"
      },
      {
        "book": "betfan",
        "lineType": "player2",
        "over": "+ 2.5 @2"
      },
      {
        "book": "betclic",
        "lineType": "player2",
        "over": "+ 2.5 @1.8"
      }
    ],
    "A_cnt": 12,
    "A_book_cnt": 3,
    "DF": [
      {
        "book": "superbet",
        "lineType": "meczowa",
        "over": "+ 5.5 @1.9"
      },
      {
        "book": "superbet",
        "lineType": "player1",
        "over": "+ 1.5 @1.85"
      },
      {
        "book": "superbet",
        "lineType": "player2",
        "over": "+ 3.5 @1.76"
      }
    ],
    "DF_cnt": 3,
    "DF_book_cnt": 1,
    "B": null,
    "B_cnt": 0,
    "B_book_cnt": 0
  },
  {
    "id": "-5326675914979565940",
    "matchStartTime": "18:20",
    "tournament": "Miami WTA • 1/64 finału",
    "eventName": "Laura Siegemund - Petra Marcinko",
    "p1": "Laura Siegemund",
    "p2": "Petra Marcinko",
    "atp": false,
    "tags1": null,
    "tags2": null,
    "updateTime": "10:10",
    "stats1": {
      "sb_a1": "1#1#1#2",
      "sb_a2": "3#2#2#2",
      "sb_am": "4#3#3",
      "sb_df1": "3#4#4#3",
      "sb_df2": "3#4#6#4",
      "sb_dfm": null,
      "sb_b1": "3",
      "sb_b2": "6",
      "sb_bm": "8",
      "ace": "0^#2^#1 #1 #7^#1^",
      "ace2": "4^#5^#2 #0 #2^#2^",
      "df": "3^#3^#2 #4 #4^#3^",
      "df2": "4^#4^#7 #2 #3^#5^",
      "b": "3^#5^#3 #2 #5^#5^",
      "b2": "4^#4^#6 #3 #6^#6^",
      "aceAvgPerSet": "0.57",
      "dfAvgPerSet": "1.48",
      "secSrvToDf": "5.42",
      "srvGameToDf": "3.45",
      "bAvgPerSet": "1.63",
      "last_aceAvgPerSet": "1.33",
      "last_dfAvgPerSet": "1.17",
      "last_secSrvToDf": "7.58",
      "last_srvGameToDf": "4.42",
      "last_bAvgPerSet": "1.67"
    },
    "stats2": {
      "sb_a1": "2#4#3#2",
      "sb_a2": "1#2#4#3",
      "sb_am": "3#6#7",
      "sb_df1": "4#4#5#4",
      "sb_df2": "4#6#4#4",
      "sb_dfm": null,
      "sb_b1": null,
      "sb_b2": null,
      "sb_bm": null,
      "ace": "5^#4^#1 #0 #3 #1 ",
      "ace2": "2^#1^#3 #3 #4 #7 ",
      "df": "4^#5^#7 #5 #5 #1 ",
      "df2": "3^#11^#3 #6 #1 #2 ",
      "b": "4^#6^#1 #2 #1 #5 ",
      "b2": "5^#6^#6 #4 #4 #3 ",
      "aceAvgPerSet": "1.46",
      "dfAvgPerSet": "1.87",
      "secSrvToDf": "5.93",
      "srvGameToDf": "3.76",
      "bAvgPerSet": "1.62",
      "last_aceAvgPerSet": "1.33",
      "last_dfAvgPerSet": "1.67",
      "last_secSrvToDf": "5.11",
      "last_srvGameToDf": "3.31",
      "last_bAvgPerSet": "1.33"
    },
    "A": [
      {
        "book": "superbet",
        "lineType": "meczowa",
        "over": "+ 2.5 @1.55"
      },
      {
        "book": "betclic",
        "lineType": "meczowa",
        "over": "+ 6.5 @1.8"
      },
      {
        "book": "superbet",
        "lineType": "player1",
        "over": "+ 0.5 @1.49"
      },
      {
        "book": "betclic",
        "lineType": "player1",
        "over": "+ 2.5 @1.8"
      },
      {
        "book": "superbet",
        "lineType": "player2",
        "over": "+ 1.5 @1.56"
      },
      {
        "book": "betclic",
        "lineType": "player2",
        "over": "+ 3.5 @1.6"
      }
    ],
    "A_cnt": 6,
    "A_book_cnt": 2,
    "DF": [
      {
        "book": "superbet",
        "lineType": "meczowa",
        "over": "+ 5.5 @1.85"
      },
      {
        "book": "superbet",
        "lineType": "player1",
        "over": "+ 2.5 @2.17"
      },
      {
        "book": "superbet",
        "lineType": "player2",
        "over": "+ 3.5 @2.3"
      }
    ],
    "DF_cnt": 3,
    "DF_book_cnt": 1,
    "B": null,
    "B_cnt": 0,
    "B_book_cnt": 0
  },
  {
    "id": "1920677478098364102",
    "matchStartTime": "17:10",
    "tournament": "Miami WTA • 1/64 finału",
    "eventName": "Darja Vidmanova - Elsa Jacquemot",
    "p1": "Darja Vidmanova",
    "p2": "Elsa Jacquemot",
    "atp": false,
    "tags1": null,
    "tags2": "DF",
    "updateTime": "10:10",
    "stats1": {
      "sb_a1": "3#4#6",
      "sb_a2": "2#5#4",
      "sb_am": "5",
      "sb_df1": "2#3#3",
      "sb_df2": "3#4#3",
      "sb_dfm": null,
      "sb_b1": null,
      "sb_b2": null,
      "sb_bm": null,
      "ace": "0 #3 #4 #7^#1 #8^",
      "ace2": "0 #4 #0 #5^#1 #0^",
      "df": "4 #1 #1 #5^#1 #7^",
      "df2": "0 #3 #9 #3^#4 #1^",
      "b": "1 #3 #5 #3^#2 #5^",
      "b2": "5 #2 #2 #4^#4 #7^",
      "aceAvgPerSet": "1.72",
      "dfAvgPerSet": "1.28",
      "secSrvToDf": "3.83",
      "srvGameToDf": "2.78",
      "bAvgPerSet": "1.48",
      "last_aceAvgPerSet": "2.50",
      "last_dfAvgPerSet": "2.00",
      "last_secSrvToDf": "4.22",
      "last_srvGameToDf": "2.64",
      "last_bAvgPerSet": "1.33"
    },
    "stats2": {
      "sb_a1": "4#3",
      "sb_a2": "4#3",
      "sb_am": "8",
      "sb_df1": "7#6",
      "sb_df2": "2#7",
      "sb_dfm": null,
      "sb_b1": null,
      "sb_b2": null,
      "sb_bm": null,
      "ace": "3 #3^#4 #2^#1 #4^",
      "ace2": "4 #3^#1 #4^#0 #8^",
      "df": "3 #13^#2 #8^#2 #11^",
      "df2": "0 #1^#1 #7^#1 #5^",
      "b": "4 #2^#2 #5^#1 #3^",
      "b2": "5 #5^#4 #6^#5 #3^",
      "aceAvgPerSet": "1.97",
      "dfAvgPerSet": "2.84",
      "secSrvToDf": "8.07",
      "srvGameToDf": "4.00",
      "bAvgPerSet": "1.76",
      "last_aceAvgPerSet": "1.33",
      "last_dfAvgPerSet": "2.33",
      "last_secSrvToDf": "10.38",
      "last_srvGameToDf": "3.58",
      "last_bAvgPerSet": "1.17"
    },
    "A": [
      {
        "book": "betclic",
        "lineType": "meczowa",
        "over": "+10.5 @1.8"
      },
      {
        "book": "betfan",
        "lineType": "meczowa",
        "over": "+10.5 @1.7"
      },
      {
        "book": "betfan",
        "lineType": "meczowa",
        "over": "+11.5 @2"
      },
      {
        "book": "betclic",
        "lineType": "player1",
        "over": "+ 5.5 @1.8"
      },
      {
        "book": "betclic",
        "lineType": "player2",
        "over": "+ 4.5 @1.6"
      }
    ],
    "A_cnt": 5,
    "A_book_cnt": 2,
    "DF": null,
    "DF_cnt": 0,
    "DF_book_cnt": 0,
    "B": null,
    "B_cnt": 0,
    "B_book_cnt": 0
  },
  {
    "id": "2503469572375611479",
    "matchStartTime": "16:00",
    "tournament": "Miami WTA • 1/64 finału",
    "eventName": "Janice Tjen - Yulia Putintseva",
    "p1": "Janice Tjen",
    "p2": "Yulia Putintseva",
    "atp": false,
    "tags1": null,
    "tags2": null,
    "updateTime": "10:10",
    "stats1": {
      "sb_a1": "3#3#4#4#3",
      "sb_a2": "3#2#4#4#3",
      "sb_am": "6#4#8#8",
      "sb_df1": "5#4#4#4#3",
      "sb_df2": "4#5#4#4#2",
      "sb_dfm": "8",
      "sb_b1": "5#2#2",
      "sb_b2": "4#4#5",
      "sb_bm": "8#6#6",
      "ace": "2^#2 #0 #5 #3 #1 ",
      "ace2": "6^#4 #2 #6 #0 #4 ",
      "df": "2^#5 #6 #5 #3 #1 ",
      "df2": "6^#6 #4 #6 #7 #2 ",
      "b": "4^#3 #2 #4 #4 #1 ",
      "b2": "4^#4 #6 #3 #0 #5 ",
      "aceAvgPerSet": "1.61",
      "dfAvgPerSet": "1.61",
      "secSrvToDf": "6.71",
      "srvGameToDf": "3.05",
      "bAvgPerSet": "1.31",
      "last_aceAvgPerSet": "0.83",
      "last_dfAvgPerSet": "1.33",
      "last_secSrvToDf": "7.53",
      "last_srvGameToDf": "4.00",
      "last_bAvgPerSet": "1.17"
    },
    "stats2": {
      "sb_a1": "1#1#2#2",
      "sb_a2": "6#5#1#2",
      "sb_am": "7#6#3#3",
      "sb_df1": "2#2#2#2",
      "sb_df2": "4#7#7#2",
      "sb_dfm": "3",
      "sb_b1": "3#5#3",
      "sb_b2": "5#4#5",
      "sb_bm": "8#8#7",
      "ace": "1 #0 #0^#0 #2^#0 ",
      "ace2": "4 #4 #0^#3 #1^#1 ",
      "df": "1 #1 #5^#3 #1^#1 ",
      "df2": "3 #10 #9^#1 #4^#2 ",
      "b": "3 #5 #8^#1 #6^#5 ",
      "b2": "5 #2 #6^#6 #4^#1 ",
      "aceAvgPerSet": "2.32",
      "dfAvgPerSet": "2.21",
      "secSrvToDf": "6.46",
      "srvGameToDf": "3.71",
      "bAvgPerSet": "1.76",
      "last_aceAvgPerSet": "0.17",
      "last_dfAvgPerSet": "1.00",
      "last_secSrvToDf": "6.11",
      "last_srvGameToDf": "4.00",
      "last_bAvgPerSet": "2.50"
    },
    "A": [
      {
        "book": "betclic",
        "lineType": "meczowa",
        "over": "+ 6.5 @1.8"
      },
      {
        "book": "superbet",
        "lineType": "player1",
        "over": "+ 3.5 @2.02"
      },
      {
        "book": "betclic",
        "lineType": "player1",
        "over": "+ 4.5 @1.8"
      },
      {
        "book": "superbet",
        "lineType": "player2",
        "over": "+ 1.5 @2.55"
      },
      {
        "book": "betclic",
        "lineType": "player2",
        "over": "+ 1.5 @1.6"
      }
    ],
    "A_cnt": 5,
    "A_book_cnt": 2,
    "DF": [
      {
        "book": "superbet",
        "lineType": "player1",
        "over": "+ 2.5 @1.57"
      },
      {
        "book": "superbet",
        "lineType": "player2",
        "over": "+ 1.5 @2.42"
      }
    ],
    "DF_cnt": 2,
    "DF_book_cnt": 1,
    "B": null,
    "B_cnt": 0,
    "B_book_cnt": 0
  },
  {
    "id": "-9151504876523211837",
    "matchStartTime": "18:20",
    "tournament": "Miami WTA • 1/64 finału",
    "eventName": "Katie Boulter - Jessica Bouzas Maneiro",
    "p1": "Katie Boulter",
    "p2": "Jessica Bouzas Maneiro",
    "atp": false,
    "tags1": null,
    "tags2": "DF",
    "updateTime": "10:10",
    "stats1": {
      "sb_a1": "2#3#2#3",
      "sb_a2": "1#2#2#1",
      "sb_am": "5#4#4",
      "sb_df1": "6#4#4#5",
      "sb_df2": "5#5#4#1",
      "sb_dfm": "8#6",
      "sb_b1": "4#5#5#5",
      "sb_b2": "5#4#4#4",
      "sb_bm": "8#8#8#8",
      "ace": "3^#0 #0^#3 #3^#3 ",
      "ace2": "1^#2 #1^#0 #5^#0 ",
      "df": "6^#4 #6^#9 #0^#3 ",
      "df2": "1^#5 #2^#7 #2^#2 ",
      "b": "4^#5 #6^#7 #6^#5 ",
      "b2": "5^#2 #6^#5 #2^#1 ",
      "aceAvgPerSet": "0.99",
      "dfAvgPerSet": "2.21",
      "secSrvToDf": "5.22",
      "srvGameToDf": "2.51",
      "bAvgPerSet": "1.72",
      "last_aceAvgPerSet": "0.83",
      "last_dfAvgPerSet": "2.83",
      "last_secSrvToDf": "2.38",
      "last_srvGameToDf": "1.71",
      "last_bAvgPerSet": "2.67"
    },
    "stats2": {
      "sb_a1": "4#3#2#2#2#2",
      "sb_a2": "4#2#2#2#2#2",
      "sb_am": "8#4#3#4#4",
      "sb_df1": "6#6#6#6#5#6",
      "sb_df2": "5#6#2#5#3#4",
      "sb_dfm": "11",
      "sb_b1": "3#5",
      "sb_b2": "5#5",
      "sb_bm": "7#8",
      "ace": "3 #1^#0 #1 #3^#2 ",
      "ace2": "5 #2^#0 #0 #2^#0 ",
      "df": "4 #6^#3 #1 #6^#5 ",
      "df2": "5 #8^#0 #4 #2^#4 ",
      "b": "1 #5^#2 #3 #2^#0 ",
      "b2": "4 #1^#6 #1 #4^#5 ",
      "aceAvgPerSet": "2.62",
      "dfAvgPerSet": "2.53",
      "secSrvToDf": "8.07",
      "srvGameToDf": "3.54",
      "bAvgPerSet": "1.69",
      "last_aceAvgPerSet": "0.33",
      "last_dfAvgPerSet": "1.33",
      "last_secSrvToDf": "7.67",
      "last_srvGameToDf": "3.00",
      "last_bAvgPerSet": "1.67"
    },
    "A": [
      {
        "book": "superbet",
        "lineType": "meczowa",
        "over": "+ 4.5 @2.05"
      },
      {
        "book": "betclic",
        "lineType": "meczowa",
        "over": "+ 5.5 @1.8"
      },
      {
        "book": "betfan",
        "lineType": "meczowa",
        "over": "+ 7.5 @1.7"
      },
      {
        "book": "betfan",
        "lineType": "meczowa",
        "over": "+ 8.5 @2"
      },
      {
        "book": "superbet",
        "lineType": "player1",
        "over": "+ 1.5 @1.65"
      },
      {
        "book": "betclic",
        "lineType": "player1",
        "over": "+ 2.5 @1.6"
      },
      {
        "book": "superbet",
        "lineType": "player2",
        "over": "+ 2.5 @2.02"
      },
      {
        "book": "betclic",
        "lineType": "player2",
        "over": "+ 2.5 @1.6"
      }
    ],
    "A_cnt": 8,
    "A_book_cnt": 3,
    "DF": [
      {
        "book": "superbet",
        "lineType": "meczowa",
        "over": "+10.5 @2.15"
      },
      {
        "book": "superbet",
        "lineType": "player1",
        "over": "+ 5.5 @2.12"
      },
      {
        "book": "superbet",
        "lineType": "player2",
        "over": "+ 4.5 @1.83"
      }
    ],
    "DF_cnt": 3,
    "DF_book_cnt": 1,
    "B": null,
    "B_cnt": 0,
    "B_book_cnt": 0
  },
  {
    "id": "-2643661650830303481",
    "matchStartTime": "19:30",
    "tournament": "Miami WTA • 1/64 finału",
    "eventName": "Shuai Zhang - Sorana Cirstea",
    "p1": "Shuai Zhang",
    "p2": "Sorana Cirstea",
    "atp": false,
    "tags1": null,
    "tags2": null,
    "updateTime": "10:10",
    "stats1": {
      "sb_a1": "3#2#2",
      "sb_a2": "4#3#3",
      "sb_am": "7#5#5",
      "sb_df1": "3#3#3",
      "sb_df2": "6#4#3",
      "sb_dfm": null,
      "sb_b1": "4#5#4",
      "sb_b2": "5#4#5",
      "sb_bm": "8#8#8",
      "ace": "0 #1^#1 #1 #3 #0 ",
      "ace2": "5 #3^#0 #4 #1 #0 ",
      "df": "3 #1^#3 #2 #1 #3 ",
      "df2": "5 #6^#2 #5 #2 #4 ",
      "b": "2 #4^#8 #4 #5 #6 ",
      "b2": "5 #8^#4 #2 #1 #3 ",
      "aceAvgPerSet": "1.08",
      "dfAvgPerSet": "0.99",
      "secSrvToDf": "4.73",
      "srvGameToDf": "3.52",
      "bAvgPerSet": "1.65",
      "last_aceAvgPerSet": "0.67",
      "last_dfAvgPerSet": "1.00",
      "last_secSrvToDf": "3.92",
      "last_srvGameToDf": "3.58",
      "last_bAvgPerSet": "2.50"
    },
    "stats2": {
      "sb_a1": "6#5#4#6#7#6",
      "sb_a2": "5#2#3#1#4#2",
      "sb_am": "11#6#7#7#11#8",
      "sb_df1": "3#3#3#3#3#3",
      "sb_df2": "5#4#3#3#5#4",
      "sb_dfm": "8#5#6",
      "sb_b1": "4#5#5#4",
      "sb_b2": "4#4#4#4",
      "sb_bm": "7#8#8#7",
      "ace": "12^#5 #4^#2 #10 #5 ",
      "ace2": "10^#0 #4^#0 #2 #0 ",
      "df": "3^#1 #1^#3 #1 #3 ",
      "df2": "6^#5 #3^#3 #4 #2 ",
      "b": "1^#2 #5^#2 #4 #4 ",
      "b2": "3^#0 #4^#4 #0 #3 ",
      "aceAvgPerSet": "2.67",
      "dfAvgPerSet": "1.77",
      "secSrvToDf": "6.32",
      "srvGameToDf": "3.20",
      "bAvgPerSet": "1.84",
      "last_aceAvgPerSet": "2.50",
      "last_dfAvgPerSet": "0.33",
      "last_secSrvToDf": "9.50",
      "last_srvGameToDf": "5.17",
      "last_bAvgPerSet": "1.33"
    },
    "A": [
      {
        "book": "superbet",
        "lineType": "meczowa",
        "over": "+ 8.5 @2.05"
      },
      {
        "book": "betclic",
        "lineType": "meczowa",
        "over": "+10.5 @1.8"
      },
      {
        "book": "betfan",
        "lineType": "meczowa",
        "over": "+11.5 @1.7"
      },
      {
        "book": "betfan",
        "lineType": "meczowa",
        "over": "+12.5 @2"
      },
      {
        "book": "superbet",
        "lineType": "player1",
        "over": "+ 1.5 @2.15"
      },
      {
        "book": "betclic",
        "lineType": "player1",
        "over": "+ 1.5 @1.6"
      },
      {
        "book": "superbet",
        "lineType": "player2",
        "over": "+ 6.5 @1.78"
      },
      {
        "book": "betclic",
        "lineType": "player2",
        "over": "+ 8.5 @1.8"
      }
    ],
    "A_cnt": 8,
    "A_book_cnt": 3,
    "DF": [
      {
        "book": "superbet",
        "lineType": "meczowa",
        "over": "+ 4.5 @1.95"
      },
      {
        "book": "superbet",
        "lineType": "player1",
        "over": "+ 2.5 @2.02"
      },
      {
        "book": "superbet",
        "lineType": "player2",
        "over": "+ 1.5 @1.61"
      }
    ],
    "DF_cnt": 3,
    "DF_book_cnt": 1,
    "B": null,
    "B_cnt": 0,
    "B_book_cnt": 0
  },
  {
    "id": "-5289517107057553052",
    "matchStartTime": "16:00",
    "tournament": "Miami WTA • 1/64 finału",
    "eventName": "Elena Gabriela Ruse - Antonia Ruzic",
    "p1": "Elena Gabriela Ruse",
    "p2": "Antonia Ruzic",
    "atp": false,
    "tags1": null,
    "tags2": null,
    "updateTime": "10:10",
    "stats1": {
      "sb_a1": "5#4#3#2",
      "sb_a2": "2#3#2#5",
      "sb_am": "6#7",
      "sb_df1": "6#5#4#5",
      "sb_df2": "5#3#3#5",
      "sb_dfm": "9",
      "sb_b1": null,
      "sb_b2": null,
      "sb_bm": null,
      "ace": "2 #5 #6^#4^#1^#0 ",
      "ace2": "2 #1 #7^#0^#6^#1 ",
      "df": "4 #8 #7^#7^#3^#3 ",
      "df2": "5 #6 #4^#2^#5^#3 ",
      "b": "3 #2 #7^#6^#1^#2 ",
      "b2": "6 #4 #5^#2^#4^#4 ",
      "aceAvgPerSet": "1.26",
      "dfAvgPerSet": "1.93",
      "secSrvToDf": "6.03",
      "srvGameToDf": "3.03",
      "bAvgPerSet": "1.55",
      "last_aceAvgPerSet": "0.50",
      "last_dfAvgPerSet": "1.50",
      "last_secSrvToDf": "6.83",
      "last_srvGameToDf": "2.97",
      "last_bAvgPerSet": "1.00"
    },
    "stats2": {
      "sb_a1": "2#2#2#4#3",
      "sb_a2": "3#3#5#3#4",
      "sb_am": "5#5#7#6#7",
      "sb_df1": "4#3#4#3#4",
      "sb_df2": "2#3#3#3#3",
      "sb_dfm": "5#6",
      "sb_b1": "3#3#2#4",
      "sb_b2": "5#5#5#4",
      "sb_bm": "7#7#7#7",
      "ace": "0 #1 #5^#0^#2^#10^",
      "ace2": "2 #4 #4^#7^#3^#6^",
      "df": "1 #4 #4^#1^#4^#6^",
      "df2": "0 #5 #2^#7^#2^#7^",
      "b": "0 #3 #6^#3^#5^#6^",
      "b2": "5 #2 #4^#5^#1^#3^",
      "aceAvgPerSet": "1.40",
      "dfAvgPerSet": "1.98",
      "secSrvToDf": "7.60",
      "srvGameToDf": "3.57",
      "bAvgPerSet": "1.63",
      "last_aceAvgPerSet": "1.00",
      "last_dfAvgPerSet": "1.50",
      "last_secSrvToDf": "6.17",
      "last_srvGameToDf": "3.19",
      "last_bAvgPerSet": "1.67"
    },
    "A": [
      {
        "book": "betclic",
        "lineType": "meczowa",
        "over": "+ 6.5 @1.8"
      },
      {
        "book": "superbet",
        "lineType": "player1",
        "over": "+ 3.5 @1.64"
      },
      {
        "book": "betclic",
        "lineType": "player1",
        "over": "+ 3.5 @1.6"
      },
      {
        "book": "superbet",
        "lineType": "player2",
        "over": "+ 1.5 @1.8"
      },
      {
        "book": "betclic",
        "lineType": "player2",
        "over": "+ 2.5 @1.8"
      }
    ],
    "A_cnt": 5,
    "A_book_cnt": 2,
    "DF": [
      {
        "book": "superbet",
        "lineType": "player1",
        "over": "+ 4.5 @1.92"
      },
      {
        "book": "superbet",
        "lineType": "player2",
        "over": "+ 2.5 @1.7"
      }
    ],
    "DF_cnt": 2,
    "DF_book_cnt": 1,
    "B": null,
    "B_cnt": 0,
    "B_book_cnt": 0
  },
  {
    "id": "-341879410672719015",
    "matchStartTime": "18:20",
    "tournament": "Miami WTA • 1/64 finału",
    "eventName": "McCartney Kessler - Magdalena Frech",
    "p1": "McCartney Kessler",
    "p2": "Magdalena Frech",
    "atp": false,
    "tags1": null,
    "tags2": null,
    "updateTime": "10:10",
    "stats1": {
      "sb_a1": "3#3#3#3",
      "sb_a2": "1#5#3#3",
      "sb_am": "4#5",
      "sb_df1": "4#4#3#3",
      "sb_df2": "4#3#5#5",
      "sb_dfm": "7",
      "sb_b1": "4#4#5",
      "sb_b2": "4#4#4",
      "sb_bm": "7#7#7",
      "ace": "3 #1 #3 #5 #3 #1 ",
      "ace2": "0 #4 #2 #1 #0 #0 ",
      "df": "2 #1 #3 #6 #2 #2 ",
      "df2": "3 #5 #8 #11 #0 #0 ",
      "b": "1 #1 #5 #4 #1 #4 ",
      "b2": "4 #3 #1 #1 #6 #1 ",
      "aceAvgPerSet": "1.05",
      "dfAvgPerSet": "1.21",
      "secSrvToDf": "5.17",
      "srvGameToDf": "2.59",
      "bAvgPerSet": "1.57",
      "last_aceAvgPerSet": "1.50",
      "last_dfAvgPerSet": "1.67",
      "last_secSrvToDf": "7.63",
      "last_srvGameToDf": "3.21",
      "last_bAvgPerSet": "1.50"
    },
    "stats2": {
      "sb_a1": "3#2#1",
      "sb_a2": "3#2#1",
      "sb_am": "6#3#3",
      "sb_df1": "3#2#2",
      "sb_df2": "4#6#4",
      "sb_dfm": null,
      "sb_b1": "5#5#5",
      "sb_b2": "4#5#5",
      "sb_bm": "8#8#8",
      "ace": "4^#1^#3^#3^#0 #0 ",
      "ace2": "1^#2^#1^#1^#0 #0 ",
      "df": "2^#6^#6^#4^#0 #5 ",
      "df2": "7^#4^#1^#5^#3 #3 ",
      "b": "3^#4^#8^#8^#6 #7 ",
      "b2": "4^#7^#4^#6^#2 #6 ",
      "aceAvgPerSet": "1.63",
      "dfAvgPerSet": "1.83",
      "secSrvToDf": "7.88",
      "srvGameToDf": "3.40",
      "bAvgPerSet": "1.91",
      "last_aceAvgPerSet": "0.50",
      "last_dfAvgPerSet": "1.50",
      "last_secSrvToDf": "6.67",
      "last_srvGameToDf": "3.11",
      "last_bAvgPerSet": "2.83"
    },
    "A": [
      {
        "book": "superbet",
        "lineType": "meczowa",
        "over": "+ 4.5 @2.1"
      },
      {
        "book": "betfan",
        "lineType": "meczowa",
        "over": "+ 5.5 @1.6"
      },
      {
        "book": "betfan",
        "lineType": "meczowa",
        "over": "+ 6.5 @2"
      },
      {
        "book": "betclic",
        "lineType": "meczowa",
        "over": "+ 6.5 @1.8"
      },
      {
        "book": "superbet",
        "lineType": "player1",
        "over": "+ 1.5 @1.67"
      },
      {
        "book": "betfan",
        "lineType": "player1",
        "over": "+ 1.5 @1.3"
      },
      {
        "book": "betfan",
        "lineType": "player1",
        "over": "+ 2.5 @1.7"
      },
      {
        "book": "betclic",
        "lineType": "player1",
        "over": "+ 3.5 @2"
      },
      {
        "book": "superbet",
        "lineType": "player2",
        "over": "+ 2.5 @2.12"
      },
      {
        "book": "betfan",
        "lineType": "player2",
        "over": "+ 2.5 @1.5"
      },
      {
        "book": "betfan",
        "lineType": "player2",
        "over": "+ 3.5 @2"
      },
      {
        "book": "betclic",
        "lineType": "player2",
        "over": "+ 3.5 @1.6"
      }
    ],
    "A_cnt": 12,
    "A_book_cnt": 3,
    "DF": [
      {
        "book": "superbet",
        "lineType": "meczowa",
        "over": "+ 5.5 @1.9"
      },
      {
        "book": "superbet",
        "lineType": "player1",
        "over": "+ 2.5 @1.62"
      },
      {
        "book": "superbet",
        "lineType": "player2",
        "over": "+ 2.5 @2"
      }
    ],
    "DF_cnt": 3,
    "DF_book_cnt": 1,
    "B": null,
    "B_cnt": 0,
    "B_book_cnt": 0
  },
  {
    "id": "615529115895622064",
    "matchStartTime": "16:00",
    "tournament": "Miami WTA • 1/64 finału",
    "eventName": "Jennifer Brady - Sloane Stephens",
    "p1": "Jennifer Brady",
    "p2": "Sloane Stephens",
    "atp": false,
    "tags1": null,
    "tags2": null,
    "updateTime": "10:10",
    "stats1": {
      "sb_a1": "3#5",
      "sb_a2": "2#2",
      "sb_am": "5",
      "sb_df1": "3#3",
      "sb_df2": "3#5",
      "sb_dfm": null,
      "sb_b1": null,
      "sb_b2": null,
      "sb_bm": null,
      "ace": "4^#2^#5 #0 #2 #0 ",
      "ace2": "5^#2^#3 #1 #3 #0 ",
      "df": "2^#4^#2 #5 #2 #4 ",
      "df2": "4^#3^#3 #0 #9 #7 ",
      "b": "4^#4^# #1 #4 #2 ",
      "b2": "6^#5^# #4 #0 #6 ",
      "aceAvgPerSet": "1.05",
      "dfAvgPerSet": "1.50",
      "secSrvToDf": "8.66",
      "srvGameToDf": "3.34",
      "bAvgPerSet": "1.48",
      "last_aceAvgPerSet": "0.67",
      "last_dfAvgPerSet": "1.33",
      "last_secSrvToDf": "7.75",
      "last_srvGameToDf": "3.42",
      "last_bAvgPerSet": "1.50"
    },
    "stats2": {
      "sb_a1": "2",
      "sb_a2": "2",
      "sb_am": "3",
      "sb_df1": "2",
      "sb_df2": "5",
      "sb_dfm": null,
      "sb_b1": null,
      "sb_b2": null,
      "sb_bm": null,
      "ace": "0 #2 #0 #2^#3 #1^",
      "ace2": "0 #3 #1 #1^#1 #0^",
      "df": "1 #2 #3 #5^#0 #1^",
      "df2": "4 #8 #2 #1^#3 #1^",
      "b": "3 #4 #5 #4^#5 #4^",
      "b2": "6 #6 #2 #2^#2 #6^",
      "aceAvgPerSet": "0.91",
      "dfAvgPerSet": "2.02",
      "secSrvToDf": "7.86",
      "srvGameToDf": "3.70",
      "bAvgPerSet": "1.76",
      "last_aceAvgPerSet": "0.67",
      "last_dfAvgPerSet": "0.50",
      "last_secSrvToDf": "6.83",
      "last_srvGameToDf": "4.33",
      "last_bAvgPerSet": "1.67"
    },
    "A": [
      {
        "book": "betclic",
        "lineType": "meczowa",
        "over": "+ 5.5 @1.8"
      },
      {
        "book": "superbet",
        "lineType": "player1",
        "over": "+ 2.5 @2.25"
      },
      {
        "book": "betclic",
        "lineType": "player1",
        "over": "+ 2.5 @1.6"
      },
      {
        "book": "superbet",
        "lineType": "player2",
        "over": "+ 1.5 @2.37"
      },
      {
        "book": "betclic",
        "lineType": "player2",
        "over": "+ 2.5 @2"
      }
    ],
    "A_cnt": 5,
    "A_book_cnt": 2,
    "DF": [
      {
        "book": "superbet",
        "lineType": "player1",
        "over": "+ 1.5 @1.68"
      },
      {
        "book": "superbet",
        "lineType": "player2",
        "over": "+ 1.5 @2.17"
      }
    ],
    "DF_cnt": 2,
    "DF_book_cnt": 1,
    "B": null,
    "B_cnt": 0,
    "B_book_cnt": 0
  },
  {
    "id": "7497284430040524420",
    "matchStartTime": "00:00",
    "tournament": "Miami WTA • 1/64 finału",
    "eventName": "Zeynep Sonmez - Beatriz Haddad Maia",
    "p1": "Zeynep Sonmez",
    "p2": "Beatriz Haddad Maia",
    "atp": false,
    "tags1": null,
    "tags2": "DF",
    "updateTime": "10:10",
    "stats1": {
      "sb_a1": "1#1#1#1#1",
      "sb_a2": "2#3#4#1#1",
      "sb_am": "3#4#4#2",
      "sb_df1": "4#4#3#4#4",
      "sb_df2": "4#4#2#4#3",
      "sb_dfm": null,
      "sb_b1": "4#5#5",
      "sb_b2": "5#5#5",
      "sb_bm": "8#8#8",
      "ace": "1 #0 #0 #0^#0 #0 ",
      "ace2": "1 #3 #0 #6^#0 #2 ",
      "df": "6 #3 #4 #6^#1 #5 ",
      "df2": "2 #2 #2 #2^#3 #5 ",
      "b": "3 #4 #3 #3^#7 #2 ",
      "b2": "4 #1 #6 #3^#2 #6 ",
      "aceAvgPerSet": "0.36",
      "dfAvgPerSet": "1.35",
      "secSrvToDf": "5.79",
      "srvGameToDf": "3.10",
      "bAvgPerSet": "1.77",
      "last_aceAvgPerSet": "0.00",
      "last_dfAvgPerSet": "1.67",
      "last_secSrvToDf": "6.31",
      "last_srvGameToDf": "2.94",
      "last_bAvgPerSet": "1.83"
    },
    "stats2": {
      "sb_a1": "2#2#3#3",
      "sb_a2": "3#3#4#3",
      "sb_am": "4#5#6",
      "sb_df1": "6#5#6#5",
      "sb_df2": "6#4#4#4",
      "sb_dfm": "11#9",
      "sb_b1": "4#4",
      "sb_b2": "5#5",
      "sb_bm": "8#8",
      "ace": "2^#0 #2 #2 #0 #2 ",
      "ace2": "1^#3 #3 #2 #0 #2 ",
      "df": "8^#7 #2 #4 #1 #10 ",
      "df2": "6^#9 #1 #5 #1 #4 ",
      "b": "1^#5 #0 #2 #6 #2 ",
      "b2": "5^#7 #5 #4 #0 #5 ",
      "aceAvgPerSet": "1.04",
      "dfAvgPerSet": "2.33",
      "secSrvToDf": "6.00",
      "srvGameToDf": "3.00",
      "bAvgPerSet": "3.00",
      "last_aceAvgPerSet": "0.33",
      "last_dfAvgPerSet": "3.67",
      "last_secSrvToDf": "3.61",
      "last_srvGameToDf": "1.49",
      "last_bAvgPerSet": "1.33"
    },
    "A": [
      {
        "book": "superbet",
        "lineType": "meczowa",
        "over": "+ 2.5 @1.95"
      },
      {
        "book": "betclic",
        "lineType": "meczowa",
        "over": "+ 4.5 @1.8"
      },
      {
        "book": "betfan",
        "lineType": "meczowa",
        "over": "+ 5.5 @1.7"
      },
      {
        "book": "betfan",
        "lineType": "meczowa",
        "over": "+ 6.5 @2"
      },
      {
        "book": "superbet",
        "lineType": "player1",
        "over": "+ 0.5 @2.42"
      },
      {
        "book": "betclic",
        "lineType": "player1",
        "over": "+ 1.5 @1.6"
      },
      {
        "book": "superbet",
        "lineType": "player2",
        "over": "+ 1.5 @1.53"
      },
      {
        "book": "betclic",
        "lineType": "player2",
        "over": "+ 2.5 @1.6"
      }
    ],
    "A_cnt": 8,
    "A_book_cnt": 3,
    "DF": [
      {
        "book": "superbet",
        "lineType": "meczowa",
        "over": "+ 9.5 @2"
      },
      {
        "book": "superbet",
        "lineType": "player1",
        "over": "+ 3.5 @1.82"
      },
      {
        "book": "superbet",
        "lineType": "player2",
        "over": "+ 5.5 @1.9"
      }
    ],
    "DF_cnt": 3,
    "DF_book_cnt": 1,
    "B": null,
    "B_cnt": 0,
    "B_book_cnt": 0
  },
  {
    "id": "-3953603892683356404",
    "matchStartTime": "17:10",
    "tournament": "Miami WTA • 1/64 finału",
    "eventName": "Simona Waltert - Ajla Tomljanovic",
    "p1": "Simona Waltert",
    "p2": "Ajla Tomljanovic",
    "atp": false,
    "tags1": null,
    "tags2": "DF",
    "updateTime": "10:10",
    "stats1": {
      "sb_a1": "2#3",
      "sb_a2": "2#5",
      "sb_am": null,
      "sb_df1": "4#5",
      "sb_df2": "1#3",
      "sb_dfm": null,
      "sb_b1": "3#4",
      "sb_b2": "4#5",
      "sb_bm": "6#8",
      "ace": "3 #0^#1 #3^#2 #2 ",
      "ace2": "3 #4^#3 #0^#0 #2 ",
      "df": "9 #1^#1 #5^#4 #6 ",
      "df2": "1 #0^#0 #9^#0 #3 ",
      "b": "2 #4^#2 #5^#4 #1 ",
      "b2": "4 #4^#6 #5^#0 #4 ",
      "aceAvgPerSet": "0.59",
      "dfAvgPerSet": "1.77",
      "secSrvToDf": "4.95",
      "srvGameToDf": "3.05",
      "bAvgPerSet": "1.96",
      "last_aceAvgPerSet": "1.00",
      "last_dfAvgPerSet": "2.17",
      "last_secSrvToDf": "5.56",
      "last_srvGameToDf": "2.55",
      "last_bAvgPerSet": "1.50"
    },
    "stats2": {
      "sb_a1": "2#3#2#3#3",
      "sb_a2": "2#4#5#3#5",
      "sb_am": "4#6#6#6#8",
      "sb_df1": "6#6#5#6#6",
      "sb_df2": "2#4#6#2#6",
      "sb_dfm": "8",
      "sb_b1": "4#4#5#3",
      "sb_b2": "5#5#4#5",
      "sb_bm": "8#8#8#7",
      "ace": "4^#2 #2 #2 #1^#0 ",
      "ace2": "6^#1 #2 #3 #1^#2 ",
      "df": "5^#5 #5 #5 #2^#5 ",
      "df2": "4^#2 #4 #8 #5^#3 ",
      "b": "4^#3 #6 #2 #3^#5 ",
      "b2": "7^#0 #3 #5 #2^#2 ",
      "aceAvgPerSet": "1.30",
      "dfAvgPerSet": "2.58",
      "secSrvToDf": "6.54",
      "srvGameToDf": "3.22",
      "bAvgPerSet": "1.67",
      "last_aceAvgPerSet": "0.17",
      "last_dfAvgPerSet": "1.83",
      "last_secSrvToDf": "1.46",
      "last_srvGameToDf": "3.36",
      "last_bAvgPerSet": "1.83"
    },
    "A": [
      {
        "book": "superbet",
        "lineType": "meczowa",
        "over": "+ 5.5 @1.75"
      },
      {
        "book": "betclic",
        "lineType": "meczowa",
        "over": "+ 8.5 @1.8"
      },
      {
        "book": "betfan",
        "lineType": "meczowa",
        "over": "+ 8.5 @1.6"
      },
      {
        "book": "betfan",
        "lineType": "meczowa",
        "over": "+ 9.5 @2"
      },
      {
        "book": "superbet",
        "lineType": "player1",
        "over": "+ 2.5 @1.61"
      },
      {
        "book": "betclic",
        "lineType": "player1",
        "over": "+ 5.5 @1.8"
      },
      {
        "book": "superbet",
        "lineType": "player2",
        "over": "+ 2.5 @1.82"
      },
      {
        "book": "betclic",
        "lineType": "player2",
        "over": "+ 3.5 @1.8"
      }
    ],
    "A_cnt": 8,
    "A_book_cnt": 3,
    "DF": [
      {
        "book": "superbet",
        "lineType": "meczowa",
        "over": "+ 8.5 @1.75"
      },
      {
        "book": "superbet",
        "lineType": "player1",
        "over": "+ 3.5 @1.62"
      },
      {
        "book": "superbet",
        "lineType": "player2",
        "over": "+ 4.5 @1.75"
      }
    ],
    "DF_cnt": 3,
    "DF_book_cnt": 1,
    "B": null,
    "B_cnt": 0,
    "B_book_cnt": 0
  }
]
