[
    {
        "id": "-6237132559265833270",
        "matchStartTime": "02:00",
        "tournament": "Delray Beach ATP • Półfinał",
        "eventName": "Tommy Paul - Learner Tien",
        "p1": "Tommy Paul",
        "p2": "Learner Tien",
        "atp": true,
        "tags1": null,
        "tags2": "DF",
        "updateTime": "06:50",
        "stats1": {
            "ace": "6#10#11#14#10#7",
            "ace2": "10#7#4#6#3#2",
            "df": "0#2#2#1#1#5",
            "df2": "3#0#6#2#1#0",
            "b": "2#1#4#2#1#1",
            "b2": "0#1#3#3#1#3",
            "aceAvgPerSet": "2.17",
            "dfAvgPerSet": "0.68",
            "secSrvToDf": "9.35",
            "srvGameToDf": "4.09",
            "bAvgPerSet": "1.14"
        },
        "stats2": {
            "ace": "13#20#9#11#5#8",
            "ace2": "11#12#9#24#6#8",
            "df": "3#5#6#9#1#5",
            "df2": "1#2#3#1#6#2",
            "b": "5#2#2#0#7#5",
            "b2": "3#0#3#3#1#2",
            "aceAvgPerSet": "3.59",
            "dfAvgPerSet": "1.35",
            "secSrvToDf": "8.80",
            "srvGameToDf": "4.11",
            "bAvgPerSet": "1.21"
        },
        "A": [
            {
                "book": "superbet",
                "under": "-11.5 @2.25",
                "lineType": "meczowa",
                "over": "+11.5 @1.57"
            },
            {
                "book": "superbet",
                "under": "-12.5 @1.9",
                "lineType": "meczowa",
                "over": "+12.5 @1.8"
            },
            {
                "book": "superbet",
                "under": "-13.5 @1.65",
                "lineType": "meczowa",
                "over": "+13.5 @2.1"
            },
            {
                "book": "etoto",
                "under": "-13.5 @1.8",
                "lineType": "meczowa",
                "over": "+13.5 @1.9"
            },
            {
                "book": "sts",
                "under": "-13.5 @1.85",
                "lineType": "meczowa",
                "over": "+13.5 @1.85"
            },
            {
                "book": "betclic",
                "lineType": "meczowa",
                "over": "+13.5 @1.8"
            },
            {
                "book": "sts",
                "under": "- 7.5 @1.9",
                "lineType": "player1",
                "over": "+ 7.5 @1.8"
            },
            {
                "book": "superbet",
                "under": "- 7.5 @1.95",
                "lineType": "player1",
                "over": "+ 7.5 @1.75"
            },
            {
                "book": "etoto",
                "under": "- 7.5 @2",
                "lineType": "player1",
                "over": "+ 7.5 @1.72"
            },
            {
                "book": "betclic",
                "lineType": "player1",
                "over": "+ 7.5 @1.7"
            },
            {
                "book": "superbet",
                "under": "- 4.5 @2.1",
                "lineType": "player2",
                "over": "+ 4.5 @1.66"
            },
            {
                "book": "etoto",
                "under": "- 5.5 @1.85",
                "lineType": "player2",
                "over": "+ 5.5 @1.85"
            },
            {
                "book": "sts",
                "under": "- 5.5 @1.85",
                "lineType": "player2",
                "over": "+ 5.5 @1.85"
            },
            {
                "book": "betclic",
                "lineType": "player2",
                "over": "+ 5.5 @1.8"
            }
        ],
        "A_cnt": 14,
        "A_book_cnt": 4,
        "DF": [
            {
                "book": "superbet",
                "under": "- 4.5 @1.95",
                "lineType": "meczowa",
                "over": "+ 4.5 @1.75"
            },
            {
                "book": "etoto",
                "under": "- 4.5 @2.02",
                "lineType": "meczowa",
                "over": "+ 4.5 @1.7"
            },
            {
                "book": "superbet",
                "under": "- 5.5 @1.55",
                "lineType": "meczowa",
                "over": "+ 5.5 @2.3"
            },
            {
                "book": "betclic",
                "under": "- 5.5 @1.88",
                "lineType": "meczowa",
                "over": "+ 5.5 @1.6"
            },
            {
                "book": "superbet",
                "under": "- 1.5 @1.6",
                "lineType": "player1",
                "over": "+ 1.5 @2.2"
            },
            {
                "book": "etoto",
                "under": "- 1.5 @1.7",
                "lineType": "player1",
                "over": "+ 1.5 @2.02"
            },
            {
                "book": "betclic",
                "under": "- 1.5 @1.65",
                "lineType": "player1",
                "over": "+ 1.5 @1.8"
            },
            {
                "book": "superbet",
                "under": "- 3.5 @1.75",
                "lineType": "player2",
                "over": "+ 3.5 @1.95"
            },
            {
                "book": "etoto",
                "under": "- 3.5 @1.85",
                "lineType": "player2",
                "over": "+ 3.5 @1.85"
            },
            {
                "book": "betclic",
                "under": "- 4.5 @1.55",
                "lineType": "player2",
                "over": "+ 4.5 @1.95"
            }
        ],
        "DF_cnt": 10,
        "DF_book_cnt": 3,
        "B": [
            {
                "book": "etoto",
                "under": "- 4.5 @2.1",
                "lineType": "meczowa",
                "over": "+ 4.5 @1.65"
            },
            {
                "book": "superbet",
                "lineType": "meczowa",
                "over": "+ 4.5 @1.6"
            },
            {
                "book": "betclic",
                "under": "- 4.5 @1.95",
                "lineType": "meczowa",
                "over": "+ 4.5 @1.55"
            },
            {
                "book": "etoto",
                "under": "- 2.5 @2.2",
                "lineType": "player1",
                "over": "+ 2.5 @1.6"
            },
            {
                "book": "betclic",
                "under": "- 2.5 @1.95",
                "lineType": "player1",
                "over": "+ 2.5 @1.55"
            },
            {
                "book": "superbet",
                "lineType": "player1",
                "over": "+ 2.5 @1.55"
            },
            {
                "book": "etoto",
                "under": "- 2.5 @1.72",
                "lineType": "player2",
                "over": "+ 2.5 @2"
            },
            {
                "book": "superbet",
                "lineType": "player2",
                "over": "+ 2.5 @1.9"
            },
            {
                "book": "betclic",
                "under": "- 2.5 @1.6",
                "lineType": "player2",
                "over": "+ 2.5 @1.88"
            }
        ],
        "B_cnt": 9,
        "B_book_cnt": 3
    },
    {
        "id": "-4542026286788850082",
        "matchStartTime": "21:00",
        "tournament": "Delray Beach ATP • Półfinał",
        "eventName": "Flavio Cobolli - Sebastian Korda",
        "p1": "Flavio Cobolli",
        "p2": "Sebastian Korda",
        "atp": true,
        "tags1": null,
        "tags2": null,
        "updateTime": "06:50",
        "stats1": {
            "ace": "11#9#4#3#7#5",
            "ace2": "15#9#11#7#6#13",
            "df": "0#2#2#1#8#5",
            "df2": "2#4#2#1#0#3",
            "b": "3#2#0#0#3#4",
            "b2": "1#1#4#4#6#5",
            "aceAvgPerSet": "2.15",
            "dfAvgPerSet": "1.11",
            "secSrvToDf": "10.35",
            "srvGameToDf": "4.07",
            "bAvgPerSet": "0.91"
        },
        "stats2": {
            "ace": "10#10#14#12#8#9",
            "ace2": "3#7#2#22#8#3",
            "df": "3#2#0#0#1#1",
            "df2": "1#2#3#3#1#1",
            "b": "4#4#2#0#4#2",
            "b2": "0#2#0#1#1#0",
            "aceAvgPerSet": "4.14",
            "dfAvgPerSet": "1.27",
            "secSrvToDf": "8.28",
            "srvGameToDf": "4.16",
            "bAvgPerSet": "1.06"
        },
        "A": [
            {
                "book": "superbet",
                "under": "-13.5 @2.2",
                "lineType": "meczowa",
                "over": "+13.5 @1.6"
            },
            {
                "book": "superbet",
                "under": "-14.5 @1.9",
                "lineType": "meczowa",
                "over": "+14.5 @1.8"
            },
            {
                "book": "superbet",
                "under": "-15.5 @1.65",
                "lineType": "meczowa",
                "over": "+15.5 @2.1"
            },
            {
                "book": "etoto",
                "under": "-15.5 @1.8",
                "lineType": "meczowa",
                "over": "+15.5 @1.9"
            },
            {
                "book": "sts",
                "under": "-16.5 @1.85",
                "lineType": "meczowa",
                "over": "+16.5 @1.85"
            },
            {
                "book": "superbet",
                "under": "- 5.5 @1.7",
                "lineType": "player1",
                "over": "+ 5.5 @2.05"
            },
            {
                "book": "etoto",
                "under": "- 5.5 @1.8",
                "lineType": "player1",
                "over": "+ 5.5 @1.9"
            },
            {
                "book": "sts",
                "under": "- 5.5 @1.85",
                "lineType": "player1",
                "over": "+ 5.5 @1.85"
            },
            {
                "book": "betclic",
                "lineType": "player1",
                "over": "+ 6.5 @1.8"
            },
            {
                "book": "superbet",
                "under": "- 9.5 @1.8",
                "lineType": "player2",
                "over": "+ 9.5 @1.9"
            },
            {
                "book": "etoto",
                "under": "- 9.5 @1.85",
                "lineType": "player2",
                "over": "+ 9.5 @1.85"
            },
            {
                "book": "sts",
                "under": "-10.5 @1.85",
                "lineType": "player2",
                "over": "+10.5 @1.85"
            },
            {
                "book": "betclic",
                "lineType": "player2",
                "over": "+10.5 @1.8"
            }
        ],
        "A_cnt": 13,
        "A_book_cnt": 4,
        "DF": [
            {
                "book": "betclic",
                "under": "- 3.5 @1.88",
                "lineType": "meczowa",
                "over": "+ 3.5 @1.6"
            },
            {
                "book": "superbet",
                "under": "- 3.5 @2.25",
                "lineType": "meczowa",
                "over": "+ 3.5 @1.57"
            },
            {
                "book": "etoto",
                "under": "- 3.5 @2.3",
                "lineType": "meczowa",
                "over": "+ 3.5 @1.55"
            },
            {
                "book": "superbet",
                "under": "- 4.5 @1.6",
                "lineType": "meczowa",
                "over": "+ 4.5 @2.2"
            },
            {
                "book": "etoto",
                "under": "- 1.5 @2.3",
                "lineType": "player1",
                "over": "+ 1.5 @1.55"
            },
            {
                "book": "betclic",
                "under": "- 1.5 @2.25",
                "lineType": "player1",
                "over": "+ 1.5 @1.4"
            },
            {
                "book": "superbet",
                "under": "- 2.5 @1.57",
                "lineType": "player1",
                "over": "+ 2.5 @2.25"
            },
            {
                "book": "etoto",
                "under": "- 1.5 @2.02",
                "lineType": "player2",
                "over": "+ 1.5 @1.7"
            },
            {
                "book": "superbet",
                "under": "- 1.5 @2.1",
                "lineType": "player2",
                "over": "+ 1.5 @1.65"
            },
            {
                "book": "betclic",
                "under": "- 1.5 @1.88",
                "lineType": "player2",
                "over": "+ 1.5 @1.6"
            }
        ],
        "DF_cnt": 10,
        "DF_book_cnt": 3,
        "B": [
            {
                "book": "etoto",
                "under": "- 3.5 @2.1",
                "lineType": "meczowa",
                "over": "+ 3.5 @1.65"
            },
            {
                "book": "superbet",
                "lineType": "meczowa",
                "over": "+ 3.5 @1.6"
            },
            {
                "book": "betclic",
                "under": "- 3.5 @1.95",
                "lineType": "meczowa",
                "over": "+ 3.5 @1.55"
            },
            {
                "book": "etoto",
                "under": "- 1.5 @1.6",
                "lineType": "player1",
                "over": "+ 1.5 @2.2"
            },
            {
                "book": "superbet",
                "lineType": "player1",
                "over": "+ 1.5 @2.1"
            },
            {
                "book": "betclic",
                "under": "- 1.5 @1.52",
                "lineType": "player1",
                "over": "+ 1.5 @2"
            },
            {
                "book": "etoto",
                "under": "- 2.5 @1.9",
                "lineType": "player2",
                "over": "+ 2.5 @1.8"
            },
            {
                "book": "superbet",
                "lineType": "player2",
                "over": "+ 2.5 @1.75"
            },
            {
                "book": "betclic",
                "under": "- 2.5 @1.7",
                "lineType": "player2",
                "over": "+ 2.5 @1.7"
            }
        ],
        "B_cnt": 9,
        "B_book_cnt": 3
    },
    {
        "id": "6526869035426812609",
        "matchStartTime": "19:00",
        "tournament": "Doha ATP • Finał",
        "eventName": "Carlos Alcaraz - Arthur Fils",
        "p1": "Carlos Alcaraz",
        "p2": "Arthur Fils",
        "atp": true,
        "tags1": null,
        "tags2": null,
        "updateTime": "06:50",
        "stats1": {
            "ace": "3#8#4#2#9#12",
            "ace2": "1#4#2#6#4#17",
            "df": "2#2#2#1#2#5",
            "df2": "1#2#2#1#2#4",
            "b": "4#2#3#1#5#4",
            "b2": "3#0#0#0#2#2",
            "aceAvgPerSet": "2.22",
            "dfAvgPerSet": "0.78",
            "secSrvToDf": "7.85",
            "srvGameToDf": "4.11",
            "bAvgPerSet": "1.47"
        },
        "stats2": {
            "ace": "5#3#5#5#4#2",
            "ace2": "8#2#5#7#2#12",
            "df": "1#0#2#5#3#1",
            "df2": "5#2#1#5#1#0",
            "b": "1#5#2#3#1#0",
            "b2": "1#2#0#1#3#3",
            "aceAvgPerSet": "3.99",
            "dfAvgPerSet": "1.40",
            "secSrvToDf": "9.13",
            "srvGameToDf": "3.99",
            "bAvgPerSet": "1.12"
        },
        "A": [
            {
                "book": "fortuna",
                "under": "- 6.5 @1.91",
                "lineType": "meczowa",
                "over": "+ 6.5 @1.74"
            },
            {
                "book": "superbet",
                "under": "- 6.5 @2.3",
                "lineType": "meczowa",
                "over": "+ 6.5 @1.55"
            },
            {
                "book": "fortuna",
                "under": "- 7.5 @1.62",
                "lineType": "meczowa",
                "over": "+ 7.5 @2.08"
            },
            {
                "book": "superbet",
                "under": "- 7.5 @1.85",
                "lineType": "meczowa",
                "over": "+ 7.5 @1.85"
            },
            {
                "book": "etoto",
                "under": "- 7.5 @1.9",
                "lineType": "meczowa",
                "over": "+ 7.5 @1.8"
            },
            {
                "book": "forbet",
                "under": "- 7.5 @1.87",
                "lineType": "meczowa",
                "over": "+ 7.5 @1.8"
            },
            {
                "book": "superbet",
                "under": "- 8.5 @1.55",
                "lineType": "meczowa",
                "over": "+ 8.5 @2.3"
            },
            {
                "book": "sts",
                "under": "- 8.5 @1.8",
                "lineType": "meczowa",
                "over": "+ 8.5 @1.88"
            },
            {
                "book": "betclic",
                "lineType": "meczowa",
                "over": "+ 9.5 @1.8"
            },
            {
                "book": "forbet",
                "under": "- 3.5 @1.62",
                "lineType": "player1",
                "over": "+ 3.5 @2.12"
            },
            {
                "book": "fortuna",
                "under": "- 3.5 @1.87",
                "lineType": "player1",
                "over": "+ 3.5 @1.77"
            },
            {
                "book": "superbet",
                "under": "- 3.5 @2.4",
                "lineType": "player1",
                "over": "+ 3.5 @1.5"
            },
            {
                "book": "fortuna",
                "under": "- 4.5 @1.47",
                "lineType": "player1",
                "over": "+ 4.5 @2.39"
            },
            {
                "book": "superbet",
                "under": "- 4.5 @1.72",
                "lineType": "player1",
                "over": "+ 4.5 @2"
            },
            {
                "book": "etoto",
                "under": "- 4.5 @1.75",
                "lineType": "player1",
                "over": "+ 4.5 @1.95"
            },
            {
                "book": "forbet",
                "under": "- 4.5 @1.74",
                "lineType": "player1",
                "over": "+ 4.5 @1.94"
            },
            {
                "book": "sts",
                "under": "- 4.5 @1.8",
                "lineType": "player1",
                "over": "+ 4.5 @1.88"
            },
            {
                "book": "fortuna-BB",
                "lineType": "player1",
                "over": "+ 4.5 @1.85"
            },
            {
                "book": "fortuna-BB",
                "lineType": "player1",
                "over": "+ 5.5 @2.63"
            },
            {
                "book": "betclic",
                "lineType": "player1",
                "over": "+ 5.5 @1.8"
            },
            {
                "book": "fortuna-BB",
                "lineType": "player1",
                "over": "+ 6.5 @3.9"
            },
            {
                "book": "fortuna-BB",
                "lineType": "player1",
                "over": "+ 7.5 @5.75"
            },
            {
                "book": "fortuna",
                "under": "- 2.5 @2.15",
                "lineType": "player2",
                "over": "+ 2.5 @1.58"
            },
            {
                "book": "superbet",
                "under": "- 2.5 @2.4",
                "lineType": "player2",
                "over": "+ 2.5 @1.5"
            },
            {
                "book": "fortuna",
                "under": "- 3.5 @1.6",
                "lineType": "player2",
                "over": "+ 3.5 @2.11"
            },
            {
                "book": "etoto",
                "under": "- 3.5 @1.65",
                "lineType": "player2",
                "over": "+ 3.5 @2.1"
            },
            {
                "book": "superbet",
                "under": "- 3.5 @1.65",
                "lineType": "player2",
                "over": "+ 3.5 @2.1"
            },
            {
                "book": "sts",
                "under": "- 3.5 @2",
                "lineType": "player2",
                "over": "+ 3.5 @1.7"
            },
            {
                "book": "fortuna-BB",
                "lineType": "player2",
                "over": "+ 3.5 @1.65"
            },
            {
                "book": "fortuna-BB",
                "lineType": "player2",
                "over": "+ 4.5 @2.25"
            },
            {
                "book": "betclic",
                "lineType": "player2",
                "over": "+ 4.5 @1.8"
            },
            {
                "book": "fortuna-BB",
                "lineType": "player2",
                "over": "+ 5.5 @3.25"
            },
            {
                "book": "fortuna-BB",
                "lineType": "player2",
                "over": "+ 6.5 @4.75"
            }
        ],
        "A_cnt": 33,
        "A_book_cnt": 7,
        "DF": [
            {
                "book": "fortuna",
                "under": "- 3.5 @1.92",
                "lineType": "meczowa",
                "over": "+ 3.5 @1.73"
            },
            {
                "book": "superbet",
                "under": "- 3.5 @2.55",
                "lineType": "meczowa",
                "over": "+ 3.5 @1.45"
            },
            {
                "book": "etoto",
                "under": "- 4.5 @1.75",
                "lineType": "meczowa",
                "over": "+ 4.5 @1.95"
            },
            {
                "book": "superbet",
                "under": "- 4.5 @1.85",
                "lineType": "meczowa",
                "over": "+ 4.5 @1.85"
            },
            {
                "book": "forbet",
                "under": "- 4.5 @1.87",
                "lineType": "meczowa",
                "over": "+ 4.5 @1.8"
            },
            {
                "book": "sts",
                "under": "- 4.5 @2.15",
                "lineType": "meczowa",
                "over": "+ 4.5 @1.6"
            },
            {
                "book": "superbet",
                "under": "- 5.5 @1.47",
                "lineType": "meczowa",
                "over": "+ 5.5 @2.5"
            },
            {
                "book": "betclic",
                "under": "- 5.5 @1.65",
                "lineType": "meczowa",
                "over": "+ 5.5 @1.8"
            },
            {
                "book": "fortuna",
                "under": "- 1.5 @1.77",
                "lineType": "player1",
                "over": "+ 1.5 @1.87"
            },
            {
                "book": "fortuna-BB",
                "lineType": "player1",
                "over": "+ 1.5 @1.67"
            },
            {
                "book": "etoto",
                "under": "- 1.5 @2.1",
                "lineType": "player1",
                "over": "+ 1.5 @1.65"
            },
            {
                "book": "forbet",
                "under": "- 1.5 @2.07",
                "lineType": "player1",
                "over": "+ 1.5 @1.65"
            },
            {
                "book": "superbet",
                "under": "- 1.5 @2.1",
                "lineType": "player1",
                "over": "+ 1.5 @1.65"
            },
            {
                "book": "sts",
                "under": "- 1.5 @2.15",
                "lineType": "player1",
                "over": "+ 1.5 @1.6"
            },
            {
                "book": "fortuna-BB",
                "lineType": "player1",
                "over": "+ 2.5 @2.75"
            },
            {
                "book": "superbet",
                "under": "- 2.5 @1.45",
                "lineType": "player1",
                "over": "+ 2.5 @2.55"
            },
            {
                "book": "betclic",
                "under": "- 2.5 @1.45",
                "lineType": "player1",
                "over": "+ 2.5 @2.2"
            },
            {
                "book": "fortuna-BB",
                "lineType": "player1",
                "over": "+ 3.5 @4.75"
            },
            {
                "book": "fortuna-BB",
                "lineType": "player1",
                "over": "+ 4.5 @8.5"
            },
            {
                "book": "fortuna",
                "under": "- 2.5 @1.64",
                "lineType": "player2",
                "over": "+ 2.5 @2.04"
            },
            {
                "book": "etoto",
                "under": "- 2.5 @1.8",
                "lineType": "player2",
                "over": "+ 2.5 @1.9"
            },
            {
                "book": "forbet",
                "under": "- 2.5 @1.8",
                "lineType": "player2",
                "over": "+ 2.5 @1.87"
            },
            {
                "book": "superbet",
                "under": "- 2.5 @1.85",
                "lineType": "player2",
                "over": "+ 2.5 @1.85"
            },
            {
                "book": "fortuna-BB",
                "lineType": "player2",
                "over": "+ 2.5 @1.53"
            },
            {
                "book": "betclic",
                "under": "- 2.5 @2",
                "lineType": "player2",
                "over": "+ 2.5 @1.52"
            },
            {
                "book": "fortuna-BB",
                "lineType": "player2",
                "over": "+ 3.5 @2.2"
            },
            {
                "book": "sts",
                "under": "- 3.5 @1.6",
                "lineType": "player2",
                "over": "+ 3.5 @2.15"
            },
            {
                "book": "fortuna-BB",
                "lineType": "player2",
                "over": "+ 4.5 @3.6"
            }
        ],
        "DF_cnt": 28,
        "DF_book_cnt": 7,
        "B": [
            {
                "book": "betclic",
                "under": "- 3.5 @2.25",
                "lineType": "meczowa",
                "over": "+ 3.5 @1.4"
            },
            {
                "book": "etoto",
                "under": "- 4.5 @1.72",
                "lineType": "meczowa",
                "over": "+ 4.5 @2"
            },
            {
                "book": "sts",
                "under": "- 4.5 @1.8",
                "lineType": "meczowa",
                "over": "+ 4.5 @1.88"
            },
            {
                "book": "fortuna",
                "under": "- 4.5 @1.8",
                "lineType": "meczowa",
                "over": "+ 4.5 @1.86"
            },
            {
                "book": "superbet",
                "lineType": "meczowa",
                "over": "+ 4.5 @1.85"
            },
            {
                "book": "forbet",
                "under": "- 4.5 @1.83",
                "lineType": "meczowa",
                "over": "+ 4.5 @1.83"
            },
            {
                "book": "betclic",
                "under": "- 3.5 @1.35",
                "lineType": "player1",
                "over": "+ 3.5 @2.4"
            },
            {
                "book": "sts",
                "under": "- 3.5 @1.6",
                "lineType": "player1",
                "over": "+ 3.5 @2.15"
            },
            {
                "book": "etoto",
                "under": "- 3.5 @1.65",
                "lineType": "player1",
                "over": "+ 3.5 @2.1"
            },
            {
                "book": "superbet",
                "lineType": "player1",
                "over": "+ 3.5 @2.1"
            },
            {
                "book": "betclic",
                "under": "- 0.5 @2.25",
                "lineType": "player2",
                "over": "+ 0.5 @1.4"
            },
            {
                "book": "etoto",
                "under": "- 1.5 @1.5",
                "lineType": "player2",
                "over": "+ 1.5 @2.4"
            },
            {
                "book": "sts",
                "under": "- 1.5 @1.52",
                "lineType": "player2",
                "over": "+ 1.5 @2.33"
            },
            {
                "book": "superbet",
                "lineType": "player2",
                "over": "+ 1.5 @2.3"
            }
        ],
        "B_cnt": 14,
        "B_book_cnt": 6
    },
    {
        "id": "3291579549693940632",
        "matchStartTime": "16:00",
        "tournament": "Dubaj WTA • Finał",
        "eventName": "Elina Svitolina - Jessica Pegula",
        "p1": "Elina Svitolina",
        "p2": "Jessica Pegula",
        "atp": false,
        "tags1": null,
        "tags2": null,
        "updateTime": "06:50",
        "stats1": {
            "ace": "3#7#9#5#4#2",
            "ace2": "2#0#0#1#1#0",
            "df": "2#7#4#2#2#3",
            "df2": "12#1#5#2#4#1",
            "b": "6#5#7#1#6#1",
            "b2": "4#3#4#4#2#4",
            "aceAvgPerSet": "1.54",
            "dfAvgPerSet": "1.31",
            "secSrvToDf": "8.30",
            "srvGameToDf": "3.57",
            "bAvgPerSet": "1.94"
        },
        "stats2": {
            "ace": "2#7#5#4#2#6",
            "ace2": "7#6#3#2#6#2",
            "df": "3#2#1#1#0#2",
            "df2": "4#3#1#3#0#7",
            "b": "4#1#3#5#3#4",
            "b2": "4#2#0#1#4#2",
            "aceAvgPerSet": "2.01",
            "dfAvgPerSet": "1.84",
            "secSrvToDf": "7.56",
            "srvGameToDf": "3.78",
            "bAvgPerSet": "1.81"
        },
        "A": [
            {
                "book": "superbet",
                "under": "- 5.5 @2.3",
                "lineType": "meczowa",
                "over": "+ 5.5 @1.55"
            },
            {
                "book": "sts",
                "under": "- 6.5 @1.8",
                "lineType": "meczowa",
                "over": "+ 6.5 @1.9"
            },
            {
                "book": "superbet",
                "under": "- 6.5 @1.8",
                "lineType": "meczowa",
                "over": "+ 6.5 @1.9"
            },
            {
                "book": "etoto",
                "under": "- 6.5 @1.85",
                "lineType": "meczowa",
                "over": "+ 6.5 @1.85"
            },
            {
                "book": "forbet",
                "under": "- 6.5 @1.83",
                "lineType": "meczowa",
                "over": "+ 6.5 @1.83"
            },
            {
                "book": "fortuna",
                "under": "- 6.5 @1.99",
                "lineType": "meczowa",
                "over": "+ 6.5 @1.68"
            },
            {
                "book": "superbet",
                "under": "- 7.5 @1.5",
                "lineType": "meczowa",
                "over": "+ 7.5 @2.4"
            },
            {
                "book": "fortuna",
                "under": "- 7.5 @1.67",
                "lineType": "meczowa",
                "over": "+ 7.5 @2"
            },
            {
                "book": "betclic",
                "lineType": "meczowa",
                "over": "+ 7.5 @1.8"
            },
            {
                "book": "superbet",
                "under": "- 3.5 @2.4",
                "lineType": "player1",
                "over": "+ 3.5 @1.5"
            },
            {
                "book": "forbet",
                "under": "- 4.5 @1.7",
                "lineType": "player1",
                "over": "+ 4.5 @2"
            },
            {
                "book": "sts",
                "under": "- 4.5 @1.7",
                "lineType": "player1",
                "over": "+ 4.5 @2"
            },
            {
                "book": "superbet",
                "under": "- 4.5 @1.72",
                "lineType": "player1",
                "over": "+ 4.5 @2"
            },
            {
                "book": "etoto",
                "under": "- 4.5 @1.8",
                "lineType": "player1",
                "over": "+ 4.5 @1.9"
            },
            {
                "book": "fortuna",
                "under": "- 4.5 @1.92",
                "lineType": "player1",
                "over": "+ 4.5 @1.73"
            },
            {
                "book": "fortuna",
                "under": "- 5.5 @1.51",
                "lineType": "player1",
                "over": "+ 5.5 @2.29"
            },
            {
                "book": "betclic",
                "lineType": "player1",
                "over": "+ 5.5 @1.8"
            },
            {
                "book": "fortuna-BB",
                "lineType": "player1",
                "over": "+ 6.5 @1.5"
            },
            {
                "book": "fortuna-BB",
                "lineType": "player1",
                "over": "+ 7.5 @1.83"
            },
            {
                "book": "fortuna-BB",
                "lineType": "player1",
                "over": "+ 8.5 @2.3"
            },
            {
                "book": "fortuna-BB",
                "lineType": "player1",
                "over": "+ 9.5 @2.9"
            },
            {
                "book": "sts",
                "under": "- 1.5 @2.25",
                "lineType": "player2",
                "over": "+ 1.5 @1.55"
            },
            {
                "book": "superbet",
                "under": "- 1.5 @2.3",
                "lineType": "player2",
                "over": "+ 1.5 @1.55"
            },
            {
                "book": "fortuna",
                "under": "- 1.5 @2.29",
                "lineType": "player2",
                "over": "+ 1.5 @1.51"
            },
            {
                "book": "etoto",
                "under": "- 2.5 @1.5",
                "lineType": "player2",
                "over": "+ 2.5 @2.4"
            },
            {
                "book": "superbet",
                "under": "- 2.5 @1.5",
                "lineType": "player2",
                "over": "+ 2.5 @2.4"
            },
            {
                "book": "forbet",
                "under": "- 2.5 @1.51",
                "lineType": "player2",
                "over": "+ 2.5 @2.33"
            },
            {
                "book": "fortuna",
                "under": "- 2.5 @1.62",
                "lineType": "player2",
                "over": "+ 2.5 @2.08"
            },
            {
                "book": "betclic",
                "lineType": "player2",
                "over": "+ 2.5 @1.8"
            },
            {
                "book": "fortuna-BB",
                "lineType": "player2",
                "over": "+ 3.5 @1.6"
            },
            {
                "book": "fortuna-BB",
                "lineType": "player2",
                "over": "+ 4.5 @2.2"
            },
            {
                "book": "fortuna-BB",
                "lineType": "player2",
                "over": "+ 5.5 @3.3"
            },
            {
                "book": "fortuna-BB",
                "lineType": "player2",
                "over": "+ 6.5 @5"
            }
        ],
        "A_cnt": 33,
        "A_book_cnt": 7,
        "DF": [
            {
                "book": "superbet",
                "under": "- 4.5 @2.25",
                "lineType": "meczowa",
                "over": "+ 4.5 @1.57"
            },
            {
                "book": "sts",
                "under": "- 5.5 @1.7",
                "lineType": "meczowa",
                "over": "+ 5.5 @2"
            },
            {
                "book": "superbet",
                "under": "- 5.5 @1.72",
                "lineType": "meczowa",
                "over": "+ 5.5 @2"
            },
            {
                "book": "etoto",
                "under": "- 5.5 @1.75",
                "lineType": "meczowa",
                "over": "+ 5.5 @1.95"
            },
            {
                "book": "forbet",
                "under": "- 5.5 @1.77",
                "lineType": "meczowa",
                "over": "+ 5.5 @1.9"
            },
            {
                "book": "fortuna",
                "under": "- 5.5 @1.79",
                "lineType": "meczowa",
                "over": "+ 5.5 @1.85"
            },
            {
                "book": "betclic",
                "under": "- 6.5 @1.7",
                "lineType": "meczowa",
                "over": "+ 6.5 @1.7"
            },
            {
                "book": "fortuna",
                "under": "- 2.5 @2.25",
                "lineType": "player1",
                "over": "+ 2.5 @1.53"
            },
            {
                "book": "superbet",
                "under": "- 2.5 @2.4",
                "lineType": "player1",
                "over": "+ 2.5 @1.5"
            },
            {
                "book": "etoto",
                "under": "- 3.5 @1.65",
                "lineType": "player1",
                "over": "+ 3.5 @2.1"
            },
            {
                "book": "sts",
                "under": "- 3.5 @1.65",
                "lineType": "player1",
                "over": "+ 3.5 @2.1"
            },
            {
                "book": "superbet",
                "under": "- 3.5 @1.65",
                "lineType": "player1",
                "over": "+ 3.5 @2.1"
            },
            {
                "book": "forbet",
                "under": "- 3.5 @1.67",
                "lineType": "player1",
                "over": "+ 3.5 @2.04"
            },
            {
                "book": "betclic",
                "under": "- 4.5 @1.65",
                "lineType": "player1",
                "over": "+ 4.5 @1.8"
            },
            {
                "book": "superbet",
                "under": "- 1.5 @2.15",
                "lineType": "player2",
                "over": "+ 1.5 @1.62"
            },
            {
                "book": "etoto",
                "under": "- 1.5 @2.2",
                "lineType": "player2",
                "over": "+ 1.5 @1.6"
            },
            {
                "book": "sts",
                "under": "- 1.5 @2.15",
                "lineType": "player2",
                "over": "+ 1.5 @1.6"
            },
            {
                "book": "forbet",
                "under": "- 2.5 @1.45",
                "lineType": "player2",
                "over": "+ 2.5 @2.5"
            },
            {
                "book": "fortuna",
                "under": "- 2.5 @1.64",
                "lineType": "player2",
                "over": "+ 2.5 @2.04"
            },
            {
                "book": "betclic",
                "under": "- 2.5 @1.6",
                "lineType": "player2",
                "over": "+ 2.5 @1.88"
            }
        ],
        "DF_cnt": 20,
        "DF_book_cnt": 6,
        "B": [
            {
                "book": "sts",
                "under": "- 7.5 @1.65",
                "lineType": "meczowa",
                "over": "+ 7.5 @2.1"
            },
            {
                "book": "etoto",
                "under": "- 7.5 @1.7",
                "lineType": "meczowa",
                "over": "+ 7.5 @2.05"
            },
            {
                "book": "superbet",
                "lineType": "meczowa",
                "over": "+ 7.5 @2.05"
            },
            {
                "book": "forbet",
                "under": "- 7.5 @1.68",
                "lineType": "meczowa",
                "over": "+ 7.5 @2.02"
            },
            {
                "book": "fortuna",
                "under": "- 7.5 @1.68",
                "lineType": "meczowa",
                "over": "+ 7.5 @2.01"
            },
            {
                "book": "betclic",
                "under": "- 7.5 @1.6",
                "lineType": "meczowa",
                "over": "+ 7.5 @1.88"
            },
            {
                "book": "sts",
                "under": "- 3.5 @1.8",
                "lineType": "player1",
                "over": "+ 3.5 @1.9"
            },
            {
                "book": "etoto",
                "under": "- 3.5 @1.85",
                "lineType": "player1",
                "over": "+ 3.5 @1.85"
            },
            {
                "book": "superbet",
                "lineType": "player1",
                "over": "+ 3.5 @1.85"
            },
            {
                "book": "betclic",
                "under": "- 3.5 @1.7",
                "lineType": "player1",
                "over": "+ 3.5 @1.7"
            },
            {
                "book": "sts",
                "under": "- 4.5 @1.6",
                "lineType": "player2",
                "over": "+ 4.5 @2.15"
            },
            {
                "book": "etoto",
                "under": "- 4.5 @1.65",
                "lineType": "player2",
                "over": "+ 4.5 @2.1"
            },
            {
                "book": "superbet",
                "lineType": "player2",
                "over": "+ 4.5 @2.1"
            },
            {
                "book": "betclic",
                "under": "- 4.5 @1.55",
                "lineType": "player2",
                "over": "+ 4.5 @1.95"
            }
        ],
        "B_cnt": 14,
        "B_book_cnt": 6
    },
    {
        "id": "-5035935442124801563",
        "matchStartTime": "21:00",
        "tournament": "Rio de Janeiro ATP • Półfinał",
        "eventName": "Tomas Martin Etcheverry - Vit Kopriva",
        "p1": "Tomas Martin Etcheverry",
        "p2": "Vit Kopriva",
        "atp": true,
        "tags1": null,
        "tags2": null,
        "updateTime": "06:50",
        "stats1": {
            "ace": "9#7#6#4#9#6",
            "ace2": "9#1#8#3#2#4",
            "df": "1#0#2#1#0#3",
            "df2": "2#3#4#0#3#5",
            "b": "1#3#1#0#3#5",
            "b2": "0#2#1#1#3#4",
            "aceAvgPerSet": "3.61",
            "dfAvgPerSet": "0.58",
            "secSrvToDf": "8.42",
            "srvGameToDf": "4.16",
            "bAvgPerSet": "1.04"
        },
        "stats2": {
            "ace": "6#3#2#2#0#4",
            "ace2": "3#6#1#3#4#4",
            "df": "4#2#1#4#0#5",
            "df2": "4#2#1#2#0#4",
            "b": "0#3#3#2#2#5",
            "b2": "0#0#0#3#0#4",
            "aceAvgPerSet": "3.05",
            "dfAvgPerSet": "1.25",
            "secSrvToDf": "7.47",
            "srvGameToDf": "3.93",
            "bAvgPerSet": "1.26"
        },
        "A": [
            {
                "book": "betclic",
                "lineType": "meczowa",
                "over": "+ 8.5 @1.7"
            },
            {
                "book": "etoto",
                "under": "- 9.5 @1.75",
                "lineType": "meczowa",
                "over": "+ 9.5 @1.95"
            },
            {
                "book": "sts",
                "under": "- 9.5 @1.85",
                "lineType": "meczowa",
                "over": "+ 9.5 @1.85"
            },
            {
                "book": "etoto",
                "under": "- 6.5 @1.72",
                "lineType": "player1",
                "over": "+ 6.5 @2"
            },
            {
                "book": "sts",
                "under": "- 6.5 @1.8",
                "lineType": "player1",
                "over": "+ 6.5 @1.9"
            },
            {
                "book": "betclic",
                "lineType": "player1",
                "over": "+ 6.5 @1.8"
            },
            {
                "book": "betclic",
                "lineType": "player2",
                "over": "+ 2.5 @1.7"
            },
            {
                "book": "etoto",
                "under": "- 2.5 @2.02",
                "lineType": "player2",
                "over": "+ 2.5 @1.7"
            },
            {
                "book": "sts",
                "under": "- 2.5 @2.1",
                "lineType": "player2",
                "over": "+ 2.5 @1.65"
            }
        ],
        "A_cnt": 9,
        "A_book_cnt": 3,
        "DF": [
            {
                "book": "betclic",
                "under": "- 3.5 @1.88",
                "lineType": "meczowa",
                "over": "+ 3.5 @1.6"
            },
            {
                "book": "etoto",
                "under": "- 4.5 @1.65",
                "lineType": "meczowa",
                "over": "+ 4.5 @2.1"
            },
            {
                "book": "etoto",
                "under": "- 1.5 @1.5",
                "lineType": "player1",
                "over": "+ 1.5 @2.4"
            },
            {
                "book": "betclic",
                "under": "- 1.5 @1.4",
                "lineType": "player1",
                "over": "+ 1.5 @2.25"
            },
            {
                "book": "etoto",
                "under": "- 2.5 @1.95",
                "lineType": "player2",
                "over": "+ 2.5 @1.75"
            },
            {
                "book": "betclic",
                "under": "- 2.5 @1.88",
                "lineType": "player2",
                "over": "+ 2.5 @1.6"
            }
        ],
        "DF_cnt": 6,
        "DF_book_cnt": 2,
        "B": [
            {
                "book": "etoto",
                "under": "- 5.5 @1.6",
                "lineType": "meczowa",
                "over": "+ 5.5 @2.2"
            },
            {
                "book": "superbet",
                "lineType": "meczowa",
                "over": "+ 5.5 @2.1"
            },
            {
                "book": "betclic",
                "under": "- 5.5 @1.65",
                "lineType": "meczowa",
                "over": "+ 5.5 @1.8"
            },
            {
                "book": "etoto",
                "under": "- 3.5 @1.6",
                "lineType": "player1",
                "over": "+ 3.5 @2.2"
            },
            {
                "book": "superbet",
                "lineType": "player1",
                "over": "+ 3.5 @2.1"
            },
            {
                "book": "betclic",
                "under": "- 3.5 @1.52",
                "lineType": "player1",
                "over": "+ 3.5 @2"
            },
            {
                "book": "etoto",
                "under": "- 2.5 @1.6",
                "lineType": "player2",
                "over": "+ 2.5 @2.2"
            },
            {
                "book": "superbet",
                "lineType": "player2",
                "over": "+ 2.5 @2.1"
            },
            {
                "book": "betclic",
                "under": "- 2.5 @1.52",
                "lineType": "player2",
                "over": "+ 2.5 @2"
            }
        ],
        "B_cnt": 9,
        "B_book_cnt": 3
    },
    {
        "id": "-5492912594574711343",
        "matchStartTime": "23:00",
        "tournament": "Rio de Janeiro ATP • Półfinał",
        "eventName": "Alejandro Tabilo - Ignacio Buse",
        "p1": "Alejandro Tabilo",
        "p2": "Ignacio Buse",
        "atp": true,
        "tags1": null,
        "tags2": null,
        "updateTime": "06:50",
        "stats1": {
            "ace": "7#4#3#2#5#2",
            "ace2": "12#4#6#9#5#6",
            "df": "3#0#0#3#1#1",
            "df2": "1#1#3#0#0#2",
            "b": "4#3#2#3#4#1",
            "b2": "2#2#0#3#3#0",
            "aceAvgPerSet": "2.55",
            "dfAvgPerSet": "0.60",
            "secSrvToDf": "8.94",
            "srvGameToDf": "4.61",
            "bAvgPerSet": "1.01"
        },
        "stats2": {
            "ace": "3#8#3#2#4#3",
            "ace2": "9#2#6#1#1#2",
            "df": "1#5#1#0#2#3",
            "df2": "2#3#2#1#3#3",
            "b": "3#2#3#1#4#2",
            "b2": "2#1#2#4#3#6",
            "aceAvgPerSet": "3.00",
            "dfAvgPerSet": "0.97",
            "secSrvToDf": "9.69",
            "srvGameToDf": "4.13",
            "bAvgPerSet": "1.37"
        },
        "A": [
            {
                "book": "sts",
                "under": "- 7.5 @1.8",
                "lineType": "meczowa",
                "over": "+ 7.5 @1.9"
            },
            {
                "book": "betclic",
                "lineType": "meczowa",
                "over": "+ 9.5 @1.8"
            },
            {
                "book": "sts",
                "under": "- 3.5 @1.85",
                "lineType": "player1",
                "over": "+ 3.5 @1.85"
            },
            {
                "book": "betclic",
                "lineType": "player1",
                "over": "+ 4.5 @1.8"
            },
            {
                "book": "sts",
                "under": "- 3.5 @1.85",
                "lineType": "player2",
                "over": "+ 3.5 @1.85"
            },
            {
                "book": "betclic",
                "lineType": "player2",
                "over": "+ 5.5 @1.8"
            }
        ],
        "A_cnt": 6,
        "A_book_cnt": 2,
        "DF": [
            {
                "book": "betclic",
                "under": "- 3.5 @1.55",
                "lineType": "meczowa",
                "over": "+ 3.5 @1.95"
            },
            {
                "book": "betclic",
                "under": "- 1.5 @1.6",
                "lineType": "player1",
                "over": "+ 1.5 @1.88"
            },
            {
                "book": "betclic",
                "under": "- 1.5 @1.7",
                "lineType": "player2",
                "over": "+ 1.5 @1.7"
            }
        ],
        "DF_cnt": 3,
        "DF_book_cnt": 1,
        "B": [
            {
                "book": "superbet",
                "lineType": "meczowa",
                "over": "+ 4.5 @1.53"
            },
            {
                "book": "betclic",
                "under": "- 4.5 @2.1",
                "lineType": "meczowa",
                "over": "+ 4.5 @1.48"
            },
            {
                "book": "superbet",
                "lineType": "player1",
                "over": "+ 2.5 @1.55"
            },
            {
                "book": "betclic",
                "under": "- 2.5 @2",
                "lineType": "player1",
                "over": "+ 2.5 @1.52"
            },
            {
                "book": "superbet",
                "lineType": "player2",
                "over": "+ 2.5 @1.85"
            },
            {
                "book": "betclic",
                "under": "- 2.5 @1.65",
                "lineType": "player2",
                "over": "+ 2.5 @1.8"
            }
        ],
        "B_cnt": 6,
        "B_book_cnt": 2
    }
]